Workbook
Name BHT: 'Precios bases'!$G$285:$G$299
Name BHT: Parametros!$G$288:$G$302
Name CAMPO: #REF!
Name CEX: 'Precios bases'!$D$285:$D$299
Name CEX: Parametros!$D$288:$D$302
Name CRE: Parametros!$J$288:$J$302
Name CREATIVE: 'Precios bases'!$J$285:$J$299
Name CREATIVE: Parametros!$J$288:$J$302
Name Guidelines_1: #REF!
Name Guidelines_1: #REF!
Name Guidelines_2: #REF!,#REF!,#REF!,#REF!
Name Guidelines_2: #REF!,#REF!,#REF!,#REF!
Name Guidelines_2: #REF!,#REF!,#REF!,#REF!
Name Guidelines10: '[1]Auxiliary Sheet'!$AA$2:$AA$11
Name Guidelines10: '[2]Auxiliary Sheet'!$AA$2:$AA$11
Name HEC: 'Precios bases'!$F$285:$F$299
Name HEC: Parametros!$F$288:$F$302
Name Horas: Horas!$E$2:$E$1048576
Name INNO: 'Precios bases'!$C$285:$C$299
Name INNO: Parametros!$C$288:$C$302
Name Metodologia: Horas!$D$2:$D$1048576
Name MSU: 'Precios bases'!$E$285:$E$299
Name MSU: Parametros!$E$288:$E$302
Name N: #REF!,#REF!,#REF!,#REF!
Name N: #REF!,#REF!,#REF!,#REF!
Name OBS: Parametros!$K$288:$K$302
Name OPS: Parametros!$K$288:$K$302
Name PA: 'Precios bases'!$H$285:$H$299
Name PA: Parametros!$H$288:$H$302
Name Record_Detail_Level: Horas!$C$2:$C$1048576
Name SL: Horas!$B$2:$B$1048576
Name UX: 'Precios bases'!$I$285:$I$299
Name UX: Parametros!$I$288:$I$302

Sheet Entradas
C4: Nombre Propuesta/#
C5: Grupo Objetivo
C6: Cliente
C7: Fecha de aprobación estimada
C8: Fecha de campo
C9: Probabilidad de aprobación | D9: Alta
C10: SL | D10: MSU
C11: Metodología SL | D11: MSC005 - U&A
C12: Record Detail | D12: Ops
C13: Categoria /Producto | D13: Otro | E13: =VLOOKUP(D13,Parametros!C243:D272,2,0) -> 0 | F13: =IF(E13>17,"Revisar con el área de cotización, Sara Vergara o Sandra Guecha",IF(E13=2,"Agregar en la descripción del grupo objetivo la hora de inicio de labor en campo",0)) -> 0
C14: Valor proveedor EXTERNO COLOMBIA | G14: Días de campo | H14: No Enc por Locación
C15: Valor proveedor INTERNACIONAL
C16: Metodología de Recolección | D16: Hogares | E16: =VLOOKUP(D16,Parametros!$B$230:$C$239,2,0) -> 0 | F16: TIPO VISITA 1 | G16: Básica - Video | I16: TIPO VISITA 2 | J16: Ninguna | L16: TIPO VISITA 3 | M16: Ninguna
C17: =HYPERLINK("#MuestraTec1!J20","Técnica de Recolección 1: Ir a diligenciar muestra") -> Técnica de Recolección 1: Ir a diligenciar muestra | D17: F2F | E17: =VLOOKUP(D17,Parametros!$F$232:$G$242,2,0) -> 1 | F17: TIPO VISITA 1 | I17: TIPO VISITA 2 | L17: TIPO VISITA 3
C18: =HYPERLINK("#MuestraTec2!J20","Técnica de Recolección 2: Ir a diligenciar muestra") -> Técnica de Recolección 2: Ir a diligenciar muestra | D18: NINGUNA | E18: =VLOOKUP(D18,Parametros!$F$232:$G$242,2,0) -> 0
C19: Base de datos | D19: No requiere | E19: =VLOOKUP(D19,Parametros!E204:F206,2,0) -> 0 | F19: 0 | G19: =IF(E19=1,"Revisar con el área de cotización, Sara Vergara o Sandra Guecha",0) -> 0
C20: Penetración | D20: =VLOOKUP(E20,Parametros!B24:C34,2,0) -> 0.82 | E20: Mas 82% | F20: =IF(D20>54%,"Recuerde siempre revisar la incidencia con el área de costos, Sara Vergara o Sandra Guecha",0) -> Recuerde siempre revisar la incidencia con el área de costos, Sara Vergara o Sandra Guecha
C21: Duracion | D21: =VLOOKUP(E21,Parametros!B15:C22,2,0) -> 20 | E21: 16-20minutos | F21: =IF(D21>31,"Recuerde que un cuestionario más extenso genera costos y tiempos mayores, debe revisarse con el area de cotización",0) -> 0
C22: # Preguntas abiertas
C23: # Preguntas abiertas Multiples
C24: Otros
C25: Top line | D25: No | E25: {=VLOOKUP(D25,+Parametros!$B$218:$C$220,2,0)} -> 0
C26: Datacleaning | D26: =VLOOKUP(D25,Parametros!$B$222:$C$223,2,FALSE) -> Total | E26: =VLOOKUP($D$26,Parametros!$B$203:$C$205,2,0) -> 1
C27: Conversión/generación archivos ASCII y otros | D27: No | E27: {=VLOOKUP(D27,+Parametros!$B$218:$C$220,2,0)} -> 0
C28: Requiere Script para reclutamiento | D28: No | E28: {=VLOOKUP(D28,+Parametros!$B$218:$C$220,2,0)} -> 0
C29: Scripting | D29: Si | E29: {=VLOOKUP(D29,+Parametros!$B$218:$C$220,2,0)} -> 1 | F29: Nuevo
C30: Codificación | D30: No | E30: {=VLOOKUP(D30,+Parametros!$B$218:$C$220,2,0)} -> 0
C31: Procesamiento | D31: Si | E31: =VLOOKUP(D31,Parametros!$B$219:$C$220,2,0) -> 1
C32: # Procesamientos | E32: 1
C33: Requiere proceso Estadistico | D33: No | E33: {=VLOOKUP(D33,+Parametros!$B$218:$C$220,2,0)} -> 0 | F33: =IF(E33>0,"Diligenciar pestaña Tarifario Estadistica",0) -> 0
C34: Valor GMU (Brasil, francia, EEUU, etc.) | D34: 0
C35: Días de Set up | D35: 2 | E35: 4
C36: #Días de campo | D36: 10 | E36: =+'Costos Directos discriminados'!C57 -> 15
C37: Harmoni | D37: No | E37: =VLOOKUP(D37,Parametros!$B$219:$C$220,2,0) -> 0
C38: Graficación | D38: No | E38: =VLOOKUP(D38,Parametros!$B$219:$C$220,2,0) -> 0
C39: Otros costos
C40: Viáticos para Campo
C41: Otros Incentivos
C42: # Pag. Reprografia/ Tarjetas
C43: Número de Olas/rondas | D43: 1 | E43: =IF(D43>1,"Revisar con el área de cotización o Sara Vergara",0) -> 0
C44: Envío a ciudades | D44: No | E44: 18 | G44: 17 | H44: 16 | I44: 15
C45: Si requiere traslado del producto indique el Peso en gramos
C46: Porcentaje de Sobre Muestra | D46: 0
C47: Ciudades | D47: =COUNTIF(B49:B55,"VERDADERO") -> 1 | E47: =SUM(E49:E55) -> 30.946187 | F47: =SUM(F49:F55) -> 136.05273 | G47: =SUM(G49:G55) -> 142.28695 | H47: =SUM(H49:H55) -> 57.320198 | I47: =SUM(I49:I55) -> 18.726261 | J47: =SUM(J49:J55) -> 14.667678 | K47: CATI
C48: Muestra | D48: =SUM(D49:D55,K48) -> 400 | E48: NSE 1 | F48: NSE 2 | G48: NSE 3 | H48: NSE 4 | I48: NSE 5 | J48: NSE 6
B49: =IF(D49<>0,TRUE,FALSE) -> TRUE | C49: Bogota | D49: =SUM(E49:J49) -> 400 | E49: =+MuestraTec1!D23+MuestraTec2!D23 -> 30.946187 | F49: =+MuestraTec1!E23+MuestraTec2!E23 -> 136.05273 | G49: =+MuestraTec1!F23+MuestraTec2!F23 -> 142.28695 | H49: =+MuestraTec1!G23+MuestraTec2!G23 -> 57.320198 | I49: =+MuestraTec1!H23+MuestraTec2!H23 -> 18.726261 | J49: =+MuestraTec1!I23+MuestraTec2!I23 -> 14.667678
B50: =IF(D50<>0,TRUE,FALSE) -> FALSE | C50: B/quilla | D50: =SUM(E50:J50) -> 0 | E50: =+MuestraTec1!D24+MuestraTec2!D24 -> 0 | F50: =+MuestraTec1!E24+MuestraTec2!E24 -> 0 | G50: =+MuestraTec1!F24+MuestraTec2!F24 -> 0 | H50: =+MuestraTec1!G24+MuestraTec2!G24 -> 0 | I50: =+MuestraTec1!H24+MuestraTec2!H24 -> 0 | J50: =+MuestraTec1!I24+MuestraTec2!I24 -> 0
B51: =IF(D51<>0,TRUE,FALSE) -> FALSE | C51: M/llin | D51: =SUM(E51:J51) -> 0 | E51: =+MuestraTec1!D25+MuestraTec2!D25 -> 0 | F51: =+MuestraTec1!E25+MuestraTec2!E25 -> 0 | G51: =+MuestraTec1!F25+MuestraTec2!F25 -> 0 | H51: =+MuestraTec1!G25+MuestraTec2!G25 -> 0 | I51: =+MuestraTec1!H25+MuestraTec2!H25 -> 0 | J51: =+MuestraTec1!I25+MuestraTec2!I25 -> 0
B52: =IF(D52<>0,TRUE,FALSE) -> FALSE | C52: Cali | D52: =SUM(E52:J52) -> 0 | E52: =+MuestraTec1!D26+MuestraTec2!D26 -> 0 | F52: =+MuestraTec1!E26+MuestraTec2!E26 -> 0 | G52: =+MuestraTec1!F26+MuestraTec2!F26 -> 0 | H52: =+MuestraTec1!G26+MuestraTec2!G26 -> 0 | I52: =+MuestraTec1!H26+MuestraTec2!H26 -> 0 | J52: =+MuestraTec1!I26+MuestraTec2!I26 -> 0
B53: =IF(D53<>0,TRUE,FALSE) -> FALSE | C53: B/manga | D53: =SUM(E53:J53) -> 0 | E53: =+MuestraTec1!D27+MuestraTec2!D27 -> 0 | F53: =+MuestraTec1!E27+MuestraTec2!E27 -> 0 | G53: =+MuestraTec1!F27+MuestraTec2!F27 -> 0 | H53: =+MuestraTec1!G27+MuestraTec2!G27 -> 0 | I53: =+MuestraTec1!H27+MuestraTec2!H27 -> 0 | J53: =+MuestraTec1!I27+MuestraTec2!I27 -> 0
B54: =IF(D54<>0,TRUE,FALSE) -> FALSE | C54: C/gena | D54: =SUM(E54:J54) -> 0 | E54: =+MuestraTec1!D28+MuestraTec2!D28 -> 0 | F54: =+MuestraTec1!E28+MuestraTec2!E28 -> 0 | G54: =+MuestraTec1!F28+MuestraTec2!F28 -> 0 | H54: =+MuestraTec1!G28+MuestraTec2!G28 -> 0 | I54: =+MuestraTec1!H28+MuestraTec2!H28 -> 0 | J54: =+MuestraTec1!I28+MuestraTec2!I28 -> 0
B55: =IF(D55<>0,TRUE,FALSE) -> FALSE | C55: Otras Ciudades | D55: =SUM(E55:J55) -> 0 | E55: =+MuestraTec1!D29+MuestraTec2!D29 -> 0 | F55: =+MuestraTec1!E29+MuestraTec2!E29 -> 0 | G55: =+MuestraTec1!F29+MuestraTec2!F29 -> 0 | H55: =+MuestraTec1!G29+MuestraTec2!G29 -> 0 | I55: =+MuestraTec1!H29+MuestraTec2!H29 -> 0 | J55: =+MuestraTec1!I29+MuestraTec2!I29 -> 0 | L55: =IF(D55>0,"Se debe dirigir al área de costos para contemplar las ciudades y sus costos reales",0) -> 0
C56: Valor del Reclutamiento en caso de requerirlo | D56: Ninguno | E56: =VLOOKUP(E44,Parametros!$A$42:$M$52,HLOOKUP($E$20,Parametros!$A$42:$M$52,2,0),0) -> 20000 | G56: =VLOOKUP(G44,Parametros!$A$42:$M$52,HLOOKUP($E$20,Parametros!$A$42:$M$52,2,0),0) -> 20000 | H56: =VLOOKUP(H44,Parametros!$A$42:$M$52,HLOOKUP($E$20,Parametros!$A$42:$M$52,2,0),0) -> 25000 | I56: =VLOOKUP(I44,Parametros!$A$42:$M$52,HLOOKUP($E$20,Parametros!$A$42:$M$52,2,0),0) -> 30000
C57: Valor del Obsequio en caso de requerirlo | D57: No | E57: =VLOOKUP(E58,Parametros!$A$42:$M$52,HLOOKUP($E$20,Parametros!$A$42:$M$52,2,0),0) -> 25000 | G57: =VLOOKUP(G58,Parametros!$A$42:$M$52,HLOOKUP($E$20,Parametros!$A$42:$M$52,2,0),0) -> 25000 | H57: =VLOOKUP(H58,Parametros!$A$42:$M$52,HLOOKUP($E$20,Parametros!$A$42:$M$52,2,0),0) -> 30000 | I57: =VLOOKUP(I58,Parametros!$A$42:$M$52,HLOOKUP($E$20,Parametros!$A$42:$M$52,2,0),0) -> 30000
A58: =VLOOKUP(D58,Parametros!B219:C220,2,0) -> 0 | C58: El estudio contempla Niños | D58: No | E58: 22 | G58: 21 | H58: 20 | I58: 19
C59: Taxi a participantes | D59: No | E59: =VLOOKUP($D$59,Parametros!$B$219:$C$220,2,0) -> 0
C60: Clase de Prueba | D60: Monádica sequencial | E60: =VLOOKUP(D60,Parametros!E208:F210,2,0) -> 2
C61: Requiere refrigeración anticipada | D61: No | E61: {=VLOOKUP(D61,+Parametros!$B$218:$C$220,2,0)} -> 0
C62: Valor de la compra del producto en caso de requerirlo | D62: 0
C63: Etiquetado, blind, o prueba a ciegas | D63: Blind, o prueba a ciegas
C64: Embalaje | D64: No
C65: # Producto a testear | D65: Si | E65: 2
C66: # Product por respondiente | D66: Si | E66: 2
C67: # Patinadores por ciudad | D67: Si | E67: =+'Costos Directos discriminados'!D49 -> 2
C68: Siembra y recolección | D68: No | E68: {=VLOOKUP(D68,+[3]Parametros!$B$68:$C$70,2,0)} -> 0
C69: Apoyo Reclutamiento en sitio | D69: Ninguno | E69: =VLOOKUP($D$69,Parametros!$B$214:$C$217,2,0) -> 0
D71: Mystery/Shopper Tipo Visita 1 | E71: Mystery/Shopper Tipo Visita 2 | F71: Mystery/Shopper Tipo Visita 3
C72: No. Olas | D72: 1 | E72: 1 | F72: 1
C73: Desplazamientos (viaticos) | D73: 0
C74: Otro tipo de desplazamiento - Tanqueos - consumos | D74: 0
C75: Alertas tempranas - Fotocopia a color | D75: 0 | E75: 1
C76: Edición videos - Apoyo Logístico | D76: 0
C77: Alquiler equipos y otros - Tablets - Plan de datos - Vr. Mensual (Act. Subcontratada) | D77: 0
C78: Compra de dispositivos de grabación | D78: Si | E78: No | F78: No
C79: # Horas capacitaciones / entrega (Coord campo) | D79: 4
C80: # Horas del PMO | D80: 36
C81: # Horas del Asist. Campo (Coord. Campo) | D81: 36
C82: Apoyo otra asistencia - Unificación videos | D82: Si | E82: No | F82: No
C83: Apoyo otra asistencia - RMC | D83: Si | E83: No | F83: No
C84: Solución a descargos | D84: Si | E84: No | F84: No
C86: Otros | D86: 0
C89: Metodologías VS Horas por cargo SL | D89: Horas Minimas | E89: Horas Presupuestadas | F89: Valor Total
C90: L3 | D90: 0 | F90: =+E90*Horas!J5 -> 0
C91: L4 | D91: =VLOOKUP($D$10&" | "&$C91&" | "&$D$11,Horas!A2:E260,5,0) -> 20 | F91: =+E91*Horas!J6 -> 0
C92: L5 | D92: =VLOOKUP($D$10&" | "&$C92&" | "&$D$11,Horas!A3:E261,5,0) -> 85 | F92: =+E92*Horas!J7 -> 0
C93: L6 | D93: =VLOOKUP($D$10&" | "&$C93&" | "&$D$11,Horas!A4:E262,5,0) -> 95 | F93: =+E93*Horas!J8 -> 0
C94: L7 | D94: =VLOOKUP($D$10&" | "&$C94&" | "&$D$11,Horas!A5:E263,5,0) -> 140 | F94: =+E94*Horas!J9 -> 0
C95: Total | D95: =SUM(D91:D94) -> 340 | E95: =SUM(E91:E94) -> 0 | F95: =SUM(F91:F94)/(1-26.84%) -> 0
D97: Valor Total
C98: Conversión/generación archivos ASCII y otros | D98: =+'Costos Directos discriminados'!D120 -> 0 | F98: Resumen de Costos Operativos
C99: Estadistica | D99: =(+'Tarifario Estadistica2'!$K$78+D34)*E33 -> 0 | E99: =IF(E33>0,"En caso de ser necesario verificar con Sandra Pastran",0) -> 0 | F99: Campo+Calidad+ Viáticos | G99: =+'Costos Directos discriminados'!E150 -> 19935082
C100: Scripting | D100: =+'Costos Directos discriminados'!D122+'Costos Directos discriminados'!D123 -> 1645392 | F100: TDD (Script+Code+Proc) | G100: =+'Costos Directos discriminados'!E151 -> 5066581.5
C101: Datacleaning | D101: =+'Costos Directos discriminados'!D124 -> 1389609 | F101: Incentivos | G101: =+'Costos Directos discriminados'!E152 -> 0
C102: TopLines | D102: =+'Costos Directos discriminados'!D125 -> 0 | F102: Estadistica | G102: =+'Costos Directos discriminados'!E153 -> 0
C103: Procesamiento | D103: =+'Costos Directos discriminados'!D126 -> 1068930 | F103: Total | G103: =+'Costos Directos discriminados'!E154 -> 25001663
C104: Harmoni | D104: =+'Costos Directos discriminados'!D127 -> 0
C105: Graficación | D105: =+'Costos Directos discriminados'!D128 -> 0
C106: Staff OPS | D106: =SUM(D98:D105) -> 4103931
C108: 0.2145
C109: 0.2145 | D109: 0.2145
...

Sheet Tarifario Estadistica
A1: No. | B1: Categoría de servicio | C1: Análisis/servicios | D1: Explicación del modelo o entregable | E1: Ejemplo de entregable | F1: Total de horas estimadas* | G1: Precio de referencia (2024) | H1: Factor para manejar economía de escala | I1: En cuánto tiempo aproximadamente se entrega uno de los procesos, previo agendamiento. | J1: Número de modelos a realizar (Se debe llenar) | K1: Precio de referencia por X modelos - Ahorro por economía de escala
A2: 1 | B2: Procesos Especiales | C2: Modelo de satisfacción (CX-variable respuesta en escala) | D2: Es un modelo (completo y el mejor modelo) que se entrega en una hoja excel, con una hoja inicial de guía para interpretación. La condición es que todas las variables deben venir en escala que miden el nivel de satisfacción. | F2: 2 | G2: 224910 | H2: 0.6 | I2: Dos días | J2: 0 | K2: =IF(J2=0,0,G2+(J2-1)*ROUND(G2*H2,0)) -> 0 | L2: =IF(J2=0,0,F2+(J2-1)*ROUND(F2*H2,0)) -> 0
A3: 2 | B3: Procesos Especiales | C3: Orden de atributos o Análisis de Drivers (variable respuesta en escala) | D3: Un modelo (completo y el mejor modelo) se entrega en una hoja excel, con una hoja inicial de guía para interpretación. La condición es que todas las variables deben venir en escala. | F3: 3 | G3: 286856 | H3: 0.3 | I3: Dos días | J3: 4 | K3: =IF(J3=0,0,G3+(J3-1)*ROUND(G3*H3,0)) -> 545027 | L3: =IF(J3=0,0,F3+(J3-1)*ROUND(F3*H3,0)) -> 6
A4: 3 | B4: Procesos Especiales | C4: Orden de atributos o Análisis de Drivers (variable respuesta dicotómica) | D4: Un modelo GLM o de machine learning (el mejor modelo), el cual se entrega en una hoja excel, con una hoja inicial de guía para interpretación. Esto ocurre cuando la variable respuesta (Y) es una variable que contiene ceros y unos. | F4: 4 | G4: 449820 | H4: 0.3 | I4: Dos días | J4: 0 | K4: =IF(J4=0,0,G4+(J4-1)*ROUND(G4*H4,0)) -> 0 | L4: =IF(J4=0,0,F4+(J4-1)*ROUND(F4*H4,0)) -> 0
A5: 4 | B5: Procesos Especiales | C5: Random Forest | D5: Es un modelo dentro de los modelos de machine learning, el cual se entrega en una hoja excel, con una hoja inicial de guía para interpretación. | F5: 3.5 | G5: 317829 | H5: 0.3 | I5: Dos días | J5: 0 | K5: =IF(J5=0,0,G5+(J5-1)*ROUND(G5*H5,0)) -> 0 | L5: =IF(J5=0,0,F5+(J5-1)*ROUND(F5*H5,0)) -> 0
A6: 5 | B6: Procesos Especiales | C6: Modelos GLM (variable con respuesta dicotómica) | D6: Un modelo GLM o de machine learning (el mejor modelo), el cual se entrega en una hoja excel, con una hoja inicial de guía para interpretación. Esto ocurre cuando la variable respuesta (Y) es una variable que contiene ceros y unos. | F6: 9 | G6: 759550 | H6: 0.3 | I6: Dos días | J6: 0 | K6: =IF(J6=0,0,G6+(J6-1)*ROUND(G6*H6,0)) -> 0 | L6: =IF(J6=0,0,F6+(J6-1)*ROUND(F6*H6,0)) -> 0
A7: 6 | B7: Procesos Especiales | C7: Modelos de machine learning | D7: Es un modelo de machine learning que aprende de la información existente y predice la información del indicador para los encuestado. Se entrega un documento del modelo y la BDD con la variable predicha. | F7: 30 | G7: 3878740 | H7: 0.3 | I7: Cuatro días | J7: 0 | K7: =IF(J7=0,0,G7+(J7-1)*ROUND(G7*H7,0)) -> 0 | L7: =IF(J7=0,0,F7+(J7-1)*ROUND(F7*H7,0)) -> 0
A8: 7 | B8: Procesos Especiales | C8: Modelos para tasa de no respuesta muy altas | D8: Es un modelo de machine learning que aprende de la información recolectada y predice, con información existente de los no-encuestado, la información faltante. Se entrega un documento del modelo y la BDD con la variable predicha. | F8: 10 | G8: 1023532 | H8: 0.5 | I8: Tres días | J8: 0 | K8: =IF(J8=0,0,G8+(J8-1)*ROUND(G8*H8,0)) -> 0 | L8: =IF(J8=0,0,F8+(J8-1)*ROUND(F8*H8,0)) -> 0
A9: 8 | B9: Procesos Especiales | C9: Modelo de anonimización | D9: Es un modelo de machine learning que anonimiza variables cualitativa o cuantitativas, para la no posible identificación del encuestado, sin afectar los resultados descriptivos. Se entrega un documento del modelo y la BDD con la variable anonimizada. | E9: Y BDD… | F9: 8 | G9: 899640 | H9: 0.5 | I9: Tres días | J9: 0 | K9: =IF(J9=0,0,G9+(J9-1)*ROUND(G9*H9,0)) -> 0 | L9: =IF(J9=0,0,F9+(J9-1)*ROUND(F9*H9,0)) -> 0
A10: 9 | B10: Procesos Especiales | C10: Graphical modelling (INNO-sin magnitud de la relación) | D10: Se entrega un grafo en archivo .html interactivo, que muestra relaciones entre atributos y una variable respuesta en escala o dicotómica. | F10: 2.5 | G10: 356901 | H10: 0.7 | I10: Dos días | J10: 0 | K10: =IF(J10=0,0,G10+(J10-1)*ROUND(G10*H10,0)) -> 0 | L10: =IF(J10=0,0,F10+(J10-1)*ROUND(F10*H10,0)) -> 0
A11: 10 | B11: Procesos Especiales | C11: Graphical modelling (con magnitud de la relación) | D11: Se entrega un grafo en archivo .html interactivo, que muestra relaciones entre atributos y una variable respuesta en escala o dicotómica, en donde se incluye la magnitud de la relación para cada enlace, que representa la fuerza de la relación existente entre los dos atributos. | F11: 3 | G11: 387874 | H11: 0.7 | I11: Dos días | J11: 0 | K11: =IF(J11=0,0,G11+(J11-1)*ROUND(G11*H11,0)) -> 0 | L11: =IF(J11=0,0,F11+(J11-1)*ROUND(F11*H11,0)) -> 0 | M11: 271512 | N11: =+K11-L11-M11 -> -271512 | O11: =+N11*2 -> -543024
A12: 11 | B12: Procesos Especiales | C12: Graphical modelling + Orden de atributos (variable respuesta en escala) | D12: Se entrega un grafo en archivo .html interactivo y un modelo de orden de atributos (la condición es que la variable respuesta debe ser en escala). | F12: 5 | G12: 511766 | H12: 0.7 | I12: Dos días | J12: 4 | K12: =IF(J12=0,0,G12+(J12-1)*ROUND(G12*H12,0)) -> 1586474 | L12: =IF(J12=0,0,F12+(J12-1)*ROUND(F12*H12,0)) -> 17
A13: 12 | B13: Procesos Especiales | C13: Graphical modelling + Orden de atributos (variable respuesta dicotómica) | D13: Se entrega un grafo en archivo .html interactivo y un modelo de orden de atributos (la condición es que la variable respuesta debe ser dicotómica). | F13: 5.5 | G13: 542739 | H13: 0.7 | I13: Dos días | J13: 0 | K13: =IF(J13=0,0,G13+(J13-1)*ROUND(G13*H13,0)) -> 0 | L13: =IF(J13=0,0,F13+(J13-1)*ROUND(F13*H13,0)) -> 0
A14: 13 | B14: Procesos Especiales | C14: Correlaciones/asociaciones | D14: Se entrega en archivo excel con la matrix correlaciones o asociaciones, con las variables señaladas sin apertura. | F14: 1 | G14: 162964 | H14: 0.7 | I14: Dos días | J14: 0 | K14: =IF(J14=0,0,G14+(J14-1)*ROUND(G14*H14,0)) -> 0 | L14: =IF(J14=0,0,F14+(J14-1)*ROUND(F14*H14,0)) -> 0
A15: 14 | B15: Procesos Especiales | C15: Inferencia Estadística (diferencias, pruebas de hipotesis, metas, análisis migratorio) | D15: Se entrega en archivo excel con el resultado de la prueba estadística o inferencia señalada sin apertura. | F15: 4 | G15: 449820 | H15: 0.7 | I15: Dos días | J15: 0 | K15: =IF(J15=0,0,G15+(J15-1)*ROUND(G15*H15,0)) -> 0 | L15: =IF(J15=0,0,F15+(J15-1)*ROUND(F15*H15,0)) -> 0
A16: 15 | B16: Procesos Especiales | C16: Text analytics (CREATIVE-De palabras) | D16: Se entrega dos grafos, uno el original y el otro con su debida partición, las métricas y la identificación de cada palabra con su grupo y número de menciones. | F16: 5 | G16: 511766 | H16: 0.75 | I16: Dos días | J16: 0 | K16: =IF(J16=0,0,G16+(J16-1)*ROUND(G16*H16,0)) -> 0 | L16: =IF(J16=0,0,F16+(J16-1)*ROUND(F16*H16,0)) -> 0
A17: 16 | B17: Procesos Especiales | C17: Text Analytics por LDA ( frases construidas) | D17: Se entrega una clasificación de verbatims, que ayuda a la construcción de frases que hace la SL, luego con las frases se hace un grafo, donde se precisan colores y edición corta de la frase, lo cual se entrega en un archivo .html. | F17: 13 | G17: 1209370 | I17: Una semana | J17: 0 | K17: =IF(J17=0,0,G17+(J17-1)*ROUND(G17*H17,0)) -> 0 | L17: =IF(J17=0,0,F17+(J17-1)*ROUND(F17*H17,0)) -> 0
A18: 17 | B18: Procesos Especiales | C18: Text analytics con segmentación y depurado de palabras | D18: Se entrega máximo tres grafos, el original con su debida partición y máximo dos depuraciones de palabras, las métricas y la identificación de cada palabra con su grupo y número de menciones. | F18: 8 | G18: 899640 | H18: 0.75 | I18: Tres días | J18: 0 | K18: =IF(J18=0,0,G18+(J18-1)*ROUND(G18*H18,0)) -> 0 | L18: =IF(J18=0,0,F18+(J18-1)*ROUND(F18*H18,0)) -> 0
A19: 18 | B19: Procesos Especiales | C19: Text analytics depurado de marcas | D19: Se entrega máximo tres grafos con máximo cuatro marcas, el original con su debida partición de marcas y máximo dos depuraciones de palabras de las marcas, las métricas y la identificación de cada palabra con su grupo y número de menciones. | F19: 11 | G19: 1085478 | H19: 0.75 | I19: Tres días | J19: 0 | K19: =IF(J19=0,0,G19+(J19-1)*ROUND(G19*H19,0)) -> 0 | L19: =IF(J19=0,0,F19+(J19-1)*ROUND(F19*H19,0)) -> 0
A20: 19 | B20: Procesos Especiales | C20: Text analytics con segmentación y asociando imágenes | D20: Es un archivo .html con un grafo, un archivo excel con identificación para cada registro el grupo al que pertenece y la identificación de las imágenes más frecuentes en cada grupo. | F20: 11 | G20: 1085478 | I20: Tres días | J20: 0 | K20: =IF(J20=0,0,G20+(J20-1)*ROUND(G20*H20,0)) -> 0 | L20: =IF(J20=0,0,F20+(J20-1)*ROUND(F20*H20,0)) -> 0
A21: 20 | B21: Procesos Especiales | C21: Penalty Analysis | D21: Se entregan dos archivos .html con las penalidades y otro con los porcentajes de cada grupo por atributos, estos mismos archivos se entregan en excel. | F21: 2 | G21: 224910 | H21: 0.5 | I21: Un día | J21: 0 | K21: =IF(J21=0,0,G21+(J21-1)*ROUND(G21*H21,0)) -> 0 | L21: =IF(J21=0,0,F21+(J21-1)*ROUND(F21*H21,0)) -> 0
A22: 21 | B22: Procesos Especiales | C22: Reglas de asociación | D22: Ante la pregunta de los productos que compró, se pueden identificar productos complementarios y sustitutos, los cuales son identificados en este análisis que se entrega en excel, con el calculo de lift. | F22: 3 | G22: 387874 | H22: 0.5 | I22: Dos días | J22: 0 | K22: =IF(J22=0,0,G22+(J22-1)*ROUND(G22*H22,0)) -> 0 | L22: =IF(J22=0,0,F22+(J22-1)*ROUND(F22*H22,0)) -> 0
A23: 22 | B23: Procesos Especiales | C23: Indicadores (ACP) | D23: El indicador se entrega en una hoja excel, con el peso de cada una de las variables involucradas en el análisis, su matrix de correlaciones, el calculo del indicador en una apertura requerida y el cálculo del indicador en cada uno de los registros del estudio. | F23: 4 | G23: 449820 | H23: 0.7 | I23: Dos días | J23: 0 | K23: =IF(J23=0,0,G23+(J23-1)*ROUND(G23*H23,0)) -> 0 | L23: =IF(J23=0,0,F23+(J23-1)*ROUND(F23*H23,0)) -> 0
A24: 23 | B24: Procesos Especiales | C24: Análisis factorial (redución o agrupamiento de variables) | D24: Se entrega el cluster del agrupamiento de variables, junto con la matrix de similitudes, el dendograma y el peso de cada variables a los factores creaados en excel. | F24: 5 | G24: 612784 | H24: 0.7 | I24: Tres días | J24: 0 | K24: =IF(J24=0,0,G24+(J24-1)*ROUND(G24*H24,0)) -> 0 | L24: =IF(J24=0,0,F24+(J24-1)*ROUND(F24*H24,0)) -> 0
A25: 24 | B25: Procesos Especiales | C25: Residuales ajustados | D25: Es una matrix de distancias estándarizadas de marcas vs atributos, donde se visualiza la asociaciones significativas tanto en la matrix cómo gráficamente, el archivo se entrega en excel. | F25: 3 | G25: 286856 | H25: 0.7 | I25: Dos días | J25: 0 | K25: =IF(J25=0,0,G25+(J25-1)*ROUND(G25*H25,0)) -> 0 | L25: =IF(J25=0,0,F25+(J25-1)*ROUND(F25*H25,0)) -> 0
A26: 25 | B26: Procesos Especiales | C26: Mapa de correspondencia | D26: Se entrega un mapa y dendograma en una hoja excel, con las coordenadas de cada punto, las proyecciones de los casos ilustrativos (cuando hay bases muy pequeñas) y las agrupaciones sombreadas a partir de los análisis de dendogramas. | F26: 4.5 | G26: 480793 | H26: 0.7 | I26: Dos días | J26: 0 | K26: =IF(J26=0,0,G26+(J26-1)*ROUND(G26*H26,0)) -> 0 | L26: =IF(J26=0,0,F26+(J26-1)*ROUND(F26*H26,0)) -> 0
A27: 26 | B27: Procesos Especiales | C27: Mapa de correspondencia+residuales | D27: Se entrega el mapa de correspondencia y la matrix de residuales, para evidenciar no solo las agrupaciones sombreadas sino las relaciones más significativas entre atributos y marcas. | F27: 5.5 | G27: 542739 | H27: 0.7 | I27: Tres días | J27: 0 | K27: =IF(J27=0,0,G27+(J27-1)*ROUND(G27*H27,0)) -> 0 | L27: =IF(J27=0,0,F27+(J27-1)*ROUND(F27*H27,0)) -> 0
A28: 27 | B28: Procesos Especiales | C28: Equity actitudinal con funnel | D28: Es un archivo excel con el cálculo del AE para cada registro y marca, además de otra hoja donde se encuentra el consolidado de los resutlados del equity por marca y la clasificación cualitativa de este. | F28: 3 | G28: 286856 | H28: 0.8 | I28: Dos días | J28: 0 | K28: =IF(J28=0,0,G28+(J28-1)*ROUND(G28*H28,0)) -> 0 | L28: =IF(J28=0,0,F28+(J28-1)*ROUND(F28*H28,0)) -> 0
A29: 28 | B29: Procesos Especiales | C29: Segmentación o perfilamiento (Análisis de Cluster) | D29: Tres opciones de perfiles con el cruce de cada una de las variables del perfilamiento y el peso de cada perfil, además de los residuales. | F29: 14 | G29: 1271316 | H29: 0.9 | I29: Tres días | J29: 0 | K29: =IF(J29=0,0,G29+(J29-1)*ROUND(G29*H29,0)) -> 0 | L29: =IF(J29=0,0,F29+(J29-1)*ROUND(F29*H29,0)) -> 0
A30: 29 | B30: Procesos Especiales | C30: Segmentación cruzada | D30: Se entregan dos segmentaciones una usualmente de la muestra de personas y la otra segmentación de ocasiones o necesidades, las cuales se cruzan para identificar los mejores segmentos. | F30: 28 | G30: 2542632 | I30: Siete días | J30: 0 | K30: =IF(J30=0,0,G30+(J30-1)*ROUND(G30*H30,0)) -> 0 | L30: =IF(J30=0,0,F30+(J30-1)*ROUND(F30*H30,0)) -> 0
A31: 30 | B31: Procesos Especiales | C31: Segmentación (Análisis de clúster) + Algoritmo (typing tool) | D31: Tres opciones de segmentación con el cruce de cada una de las variables de la segmentación, el peso de cada perfil y un algoritmo en excel o shiny para una clasificación a posteriori. | F31: 30 | G31: 2666524 | H31: 0.9 | I31: Dos semanas | J31: 0 | K31: =IF(J31=0,0,G31+(J31-1)*ROUND(G31*H31,0)) -> 0 | L31: =IF(J31=0,0,F31+(J31-1)*ROUND(F31*H31,0)) -> 0
A32: 31 | B32: Procesos Especiales | C32: Turf | D32: Se entrega un gráfico en excel, con el ordenamiento y contribución de cada medio, canal o ente de evaluación. | F32: 2.5 | G32: 255883 | H32: 0.4 | I32: Dos días | J32: 0 | K32: =IF(J32=0,0,G32+(J32-1)*ROUND(G32*H32,0)) -> 0 | L32: =IF(J32=0,0,F32+(J32-1)*ROUND(F32*H32,0)) -> 0
A33: 32 | B33: Procesos Especiales | C33: Odds ration | D33: Se entrega en una hoja excel las frecuencias, el odd para las variables señaladas, y un ejemplo de la interpretación. | F33: 2 | G33: 224910 | H33: 0.5 | I33: Dos días | J33: 0 | K33: =IF(J33=0,0,G33+(J33-1)*ROUND(G33*H33,0)) -> 0 | L33: =IF(J33=0,0,F33+(J33-1)*ROUND(F33*H33,0)) -> 0
A34: 33 | B34: Procesos Especiales | C34: Indicadores simples | D34: Se entrega una tabla en excel con el indicador calculado. | F34: 2.5 | G34: 255883 | H34: 0.9 | I34: Dos días | J34: 0 | K34: =IF(J34=0,0,G34+(J34-1)*ROUND(G34*H34,0)) -> 0 | L34: =IF(J34=0,0,F34+(J34-1)*ROUND(F34*H34,0)) -> 0
A35: 34 | B35: Procesos Especiales | C35: Penalty & Rewards | D35: Se entrega un archivo excel con los pesos de los factores y atributos, para un segmento, además de las penalidades y rewards. | F35: 5 | G35: 511766 | H35: 0.6 | I35: Dos días | J35: 0 | K35: =IF(J35=0,0,G35+(J35-1)*ROUND(G35*H35,0)) -> 0 | L35: =IF(J35=0,0,F35+(J35-1)*ROUND(F35*H35,0)) -> 0
A36: 35 | B36: Procesos Especiales | C36: Aporte entre marcas (similar a Brand Halo) | D36: Es un archivo en excel que muestra el aporte de cada atributo o submarca a una marca principal, junto con las diferencias significativas de los resultados. | F36: 4 | G36: 449820 | H36: 0.3 | I36: Dos días | J36: 0 | K36: =IF(J36=0,0,G36+(J36-1)*ROUND(G36*H36,0)) -> 0 | L36: =IF(J36=0,0,F36+(J36-1)*ROUND(F36*H36,0)) -> 0
A37: 36 | B37: Procesos Especiales | C37: Aplicación de algoritmo de segmentación | D37: Previo entrega de un algoritmo de segmentación, este se aplica a una nueva BDD y se entrega en excel el cluster de cada registro. | F37: 3 | G37: 286856 | H37: 0.75 | I37: Un día | J37: 0 | K37: =IF(J37=0,0,G37+(J37-1)*ROUND(G37*H37,0)) -> 0 | L37: =IF(J37=0,0,F37+(J37-1)*ROUND(F37*H37,0)) -> 0
A38: 37 | B38: Procesos Especiales | C38: Análisis chaid (Árboles de clasificación) | D38: Un árbol de clasificiación con su debida documentación que presenta el análisis e interpretación. | F38: 3.5 | G38: 418847 | H38: 0.75 | I38: Dos días | J38: 0 | K38: =IF(J38=0,0,G38+(J38-1)*ROUND(G38*H38,0)) -> 0 | L38: =IF(J38=0,0,F38+(J38-1)*ROUND(F38*H38,0)) -> 0
A39: 38 | B39: Procesos Especiales | C39: Análisis chaid (CX-Árboles de clasificación) | D39: Un árbol de clasificiación, para una variable categórica como NPS o Satisfacción con su debida interpretación, se entrega en un archivo excel. | F39: 2.5 | G39: 255883 | H39: 0.75 | I39: Dos días | J39: 0 | K39: =IF(J39=0,0,G39+(J39-1)*ROUND(G39*H39,0)) -> 0 | L39: =IF(J39=0,0,F39+(J39-1)*ROUND(F39*H39,0)) -> 0
A40: 39 | B40: Procesos Especiales | C40: Análisis de causalidad con redes bayesianas (similar a IBN) | D40: Se entrega un archivo .html con un grafo acíclico dirigido, basado en redes bayesinas que permiten encontrar la causalidad de la relación entre dos atributos (flechas). | F40: 13 | G40: 1209370 | H40: 0.5 | I40: Una semana | J40: 0 | K40: =IF(J40=0,0,G40+(J40-1)*ROUND(G40*H40,0)) -> 0 | L40: =IF(J40=0,0,F40+(J40-1)*ROUND(F40*H40,0)) -> 0
A41: 40 | B41: Procesos Especiales | C41: PSM | D41: Una hoja excel para un PSM con el gráfico que contiene la identificación de los puntos de intercepción y los tabulados de los precios asignados. | F41: 3.5 | G41: 317829 | H41: 0.6 | I41: Dos días | J41: 0 | K41: =IF(J41=0,0,G41+(J41-1)*ROUND(G41*H41,0)) -> 0 | L41: =IF(J41=0,0,F41+(J41-1)*ROUND(F41*H41,0)) -> 0
A42: 41 | B42: Procesos Especiales | C42: Árbol de decisión del Shopper | D42: Se entrega en un archivo excel el ranking, que describen el peso de los atributos a la escogencia. | F42: 5 | G42: 511766 | H42: 0.9 | I42: Tres días | J42: 0 | K42: =IF(J42=0,0,G42+(J42-1)*ROUND(G42*H42,0)) -> 0 | L42: =IF(J42=0,0,F42+(J42-1)*ROUND(F42*H42,0)) -> 0
... A45: 44 | B45: Procesos Especiales | C45: Elasticidad | D45: Se entrega un archivo excel con la tabla de precios con su respectiva participación y calculo de la elasticidad. | F45: 5 | G45: 511766 | H45: 0.8 | I45: Dos días | J45: 0 | K45: =IF(J45=0,0,G45+(J45-1)*ROUND(G45*H45,0)) -> 0 | L45: =IF(J45=0,0,F45+(J45-1)*ROUND(F45*H45,0)) -> 0
A46: 45 | B46: Procesos Especiales | C46: Elasticidad (similar a Gabor Granger) | D46: Se entrega un archivo excel con la curva de sensibilidad al precio, además de la tabla de precios con su respectiva participación y calculo de la elesticidad. | F46: 8 | G46: 697604 | I46: Tres días | J46: 0 | K46: =IF(J46=0,0,G46+(J46-1)*ROUND(G46*H46,0)) -> 0 | L46: =IF(J46=0,0,F46+(J46-1)*ROUND(F46*H46,0)) -> 0
A47: 46 | B47: Procesos Especiales | C47: Modelo de Atributos de Precio por Marca (similar a BIM) | D47: Es un agrupamiento de atributos de precios evaluados en diferentes marcas (cliente y competencia), se entrega en excel un análisis factorial con el agrupamiento de atributos, un modelo de machine learning que revela el peso de los factores y unos residuales ajustados complementado con mapa de correspondencia para evaluar el desempeño de la marca y su competencia. | F47: 16 | G47: 1395208 | I47: Una semana | J47: 0 | K47: =IF(J47=0,0,G47+(J47-1)*ROUND(G47*H47,0)) -> 0 | L47: =IF(J47=0,0,F47+(J47-1)*ROUND(F47*H47,0)) -> 0
A48: 47 | B48: Procesos Especiales | C48: SOVA | D48: Se entrega una tabla en excel para el producto de prueba con el resultado del source of volumen por cada producto y cada categoría. | F48: 5 | G48: 511766 | H48: 0.9 | I48: Dos días | J48: 0 | K48: =IF(J48=0,0,G48+(J48-1)*ROUND(G48*H48,0)) -> 0 | L48: =IF(J48=0,0,F48+(J48-1)*ROUND(F48*H48,0)) -> 0
A49: 48 | B49: Procesos Especiales | C49: Análisis de consistencia (Alpha cronbach) | D49: Se entrega en un excel el calculo e interpretación del coeficiente Alfa de Cronbach para la variable de interés, lo cuál muestra el nivel de confiabilidad interna de la pregunta, dentro del cuestionario, la consistencia de la escala y si es la misma variable medida en diferentes olas, muestra la consistencia en el tiempo, adicionando una prueba ANOVA. | F49: 5.5 | G49: 542739 | H49: 0.9 | I49: Dos días | J49: 0 | K49: =IF(J49=0,0,G49+(J49-1)*ROUND(G49*H49,0)) -> 0 | L49: =IF(J49=0,0,F49+(J49-1)*ROUND(F49*H49,0)) -> 0
A50: 49 | B50: Procesos Especiales | C50: Ecosystem Flow | D50: Es un grafo .html interactivo, con sus respectivas métricas de penetración y estadísticas de resúmen por apertura como franja horaria, de información suministrada de la interacción de la persona con la web, con entregable en power BI. | F50: 18 | G50: 1519100 | H50: 0.9 | I50: Cuatro días | J50: 0 | K50: =IF(J50=0,0,G50+(J50-1)*ROUND(G50*H50,0)) -> 0 | L50: =IF(J50=0,0,F50+(J50-1)*ROUND(F50*H50,0)) -> 0
A51: 50 | B51: Procesos Especiales | C51: Channel Vision | D51: Un AE, Turf no ponderado, turf ponderado por AE, indicador de afinidad y dos ordenes de atributos-incluye asesoria de movido de BDD. | F51: 18 | G51: 1519100 | H51: 0.75 | I51: Tres días | J51: 0 | K51: =IF(J51=0,0,G51+(J51-1)*ROUND(G51*H51,0)) -> 0 | L51: =IF(J51=0,0,F51+(J51-1)*ROUND(F51*H51,0)) -> 0
A52: 51 | B52: Procesos Especiales | C52: Potential modelling | D52: Se entregan un archivo .html con el resultado de la simulación para cada atributo y una tabla en excel con los valores de resúmen de la simulación. | F52: 4 | G52: 449820 | H52: 0.9 | I52: Dos días | J52: 0 | K52: =IF(J52=0,0,G52+(J52-1)*ROUND(G52*H52,0)) -> 0 | L52: =IF(J52=0,0,F52+(J52-1)*ROUND(F52*H52,0)) -> 0
A53: 52 | B53: Procesos Especiales | C53: t-plot | D53: Se entrega un gráfico en excel con la comparación estadística de dos grupos, con sus respectivas bandas. | F53: 4 | G53: 449820 | H53: 0.9 | I53: Dos días | J53: 0 | K53: =IF(J53=0,0,G53+(J53-1)*ROUND(G53*H53,0)) -> 0 | L53: =IF(J53=0,0,F53+(J53-1)*ROUND(F53*H53,0)) -> 0
A54: 53 | B54: Procesos Especiales | C54: Análisis Conjoint (CBC) | D54: Un archivo en excel que contiene la importancia y utilidades de los atributos y variables. | F54: 25 | G54: 2154758 | H54: 0.95 | I54: Tres días | J54: 0 | K54: =IF(J54=0,0,G54+(J54-1)*ROUND(G54*H54,0)) -> 0 | L54: =IF(J54=0,0,F54+(J54-1)*ROUND(F54*H54,0)) -> 0
A55: 54 | B55: Procesos Especiales | C55: Análisis Conjoint (CBC) con elasticidades | D55: Un archivo en excel que contiene la importancia y utilidades de los atributos y variables, además de las elesticidades marginales, cruzadas y la canibalización. | F55: 42 | G55: 3813948 | H55: 0.95 | I55: Una semana | J55: 0 | K55: =IF(J55=0,0,G55+(J55-1)*ROUND(G55*H55,0)) -> 0 | L55: =IF(J55=0,0,F55+(J55-1)*ROUND(F55*H55,0)) -> 0
A56: 55 | B56: Procesos Especiales | C56: Espacios de demanda (similar Demand Space) | D56: Se tienen dos entregas, la primera es un random Forest para precisar las variables que más pesan más sobre una variable de volumen o consumo y la segunda es la segmentación de personas o ocasiones o necesidades, todo se entrega en excel. | F56: 26 | G56: 3226884 | H56: 1 | I56: Siete días | J56: 0 | K56: =IF(J56=0,0,G56+(J56-1)*ROUND(G56*H56,0)) -> 0 | L56: =IF(J56=0,0,F56+(J56-1)*ROUND(F56*H56,0)) -> 0
A57: 56 | B57: Procesos Especiales | C57: Means - End Chain (Text Analytics de Atributos-Beneficios-Valores) | D57: Es un archivo en .html que muestra un grafo que proviene de una análisis por LDA de atributos, beneficios y valores, y un archivo excel con la frecuencias de cada atributo, beneficio y valor. | F57: 39 | G57: 3224038 | H57: 0.5 | I57: Dos semanas | J57: 0 | K57: =IF(J57=0,0,G57+(J57-1)*ROUND(G57*H57,0)) -> 0 | L57: =IF(J57=0,0,F57+(J57-1)*ROUND(F57*H57,0)) -> 0
A58: 57 | B58: Procesos Especiales | C58: Dendograma | D58: Es un gráfico descriptivo de la segmentación de atributos o personas | F58: 5 | G58: 511766 | H58: 1 | I58: Dos días | J58: 0 | K58: =IF(J58=0,0,G58+(J58-1)*ROUND(G58*H58,0)) -> 0 | L58: =IF(J58=0,0,F58+(J58-1)*ROUND(F58*H58,0)) -> 0
A59: 58 | B59: Ponderación | C59: Ponderación por una variable o dos variables cruzadas | D59: Se sube a matrix el archivo en excel de la base de datos muestrales con el ponderador para cada registro y se debe aprobar el pegue de este ponderador a la BDD final. | F59: 3 | G59: 255883 | H59: 1 | I59: Un día | J59: 0 | K59: =IF(J59=0,0,G59+(J59-1)*ROUND(G59*H59,0)) -> 0 | L59: =IF(J59=0,0,F59+(J59-1)*ROUND(F59*H59,0)) -> 0
A60: 59 | B60: Ponderación | C60: Ponderación dos variables (no cruzadas) | F60: 4.5 | G60: 480793 | H60: 1 | I60: Un día | J60: 0 | K60: =IF(J60=0,0,G60+(J60-1)*ROUND(G60*H60,0)) -> 0 | L60: =IF(J60=0,0,F60+(J60-1)*ROUND(F60*H60,0)) -> 0
A61: 60 | B61: Ponderación | C61: Ponderación tres o más variables no cruzadas | F61: 9 | G61: 759550 | H61: 1 | I61: Un día | J61: 0 | K61: =IF(J61=0,0,G61+(J61-1)*ROUND(G61*H61,0)) -> 0 | L61: =IF(J61=0,0,F61+(J61-1)*ROUND(F61*H61,0)) -> 0
A62: 61 | B62: Ponderación | C62: Ponderación por variable diferente a universo (ejemplo ventas) | F62: 14 | G62: 1271316 | H62: 1 | I62: Tres días | J62: 0 | K62: =IF(J62=0,0,G62+(J62-1)*ROUND(G62*H62,0)) -> 0 | L62: =IF(J62=0,0,F62+(J62-1)*ROUND(F62*H62,0)) -> 0
A63: 62 | B63: Ponderación | C63: Factor de Expansión | D63: Se deben incluir unas preguntas de validación en el cuestionario, según el diseño muestral y se requiere especificar en la metodología las variables a usar. El archivo se entrega en excel de la base de datos muestrales con el factor de expansión para cada registro y las tablas del universo representado por esta encuesta. | F63: 19 | G63: 1581046 | H63: 1 | I63: Tres días | J63: 0 | K63: =IF(J63=0,0,G63+(J63-1)*ROUND(G63*H63,0)) -> 0 | L63: =IF(J63=0,0,F63+(J63-1)*ROUND(F63*H63,0)) -> 0
A64: 63 | B64: Ponderación | C64: Factor de Expansión en muestreos no-probabilísticos (estimaciones doblemente robustas) | D64: Se deben incluir unas preguntas de validación en el cuestionario de un estuid probabilístico, según el diseño muestral y se requiere especificar en la metodología las variables a usar. El archivo se entrega en excel de la base de datos muestrales con el factor de expansión para cada registro y las tablas del universo representado por esta encuesta. | F64: 56 | G64: 5489336 | H64: 1 | I64: Una semana | J64: 0 | K64: =IF(J64=0,0,G64+(J64-1)*ROUND(G64*H64,0)) -> 0 | L64: =IF(J64=0,0,F64+(J64-1)*ROUND(F64*H64,0)) -> 0
A65: 64 | B65: Selección IDM | C65: Selección IDM por listado | D65: Se entrega el listado de los seleccionados con el 20% de sobremuestra. | F65: 5 | G65: 511766 | H65: 1 | I65: Dos días | J65: 0 | K65: =IF(J65=0,0,G65+(J65-1)*ROUND(G65*H65,0)) -> 0 | L65: =IF(J65=0,0,F65+(J65-1)*ROUND(F65*H65,0)) -> 0
A66: 65 | B66: Selección IDM | C66: Selección IDM de municipios menos de 5 municpios) | D66: Listado de IDM seleccionados por municipios y en muestreos no probabilísticos con el 50% de reemplazos y probabilísticos 20%. | F66: 4.5 | G66: 278757 | H66: 1 | I66: Dos días | J66: 0 | K66: =IF(J66=0,0,G66+(J66-1)*ROUND(G66*H66,0)) -> 0 | L66: =IF(J66=0,0,F66+(J66-1)*ROUND(F66*H66,0)) -> 0
A67: 66 | B67: Selección IDM | C67: Selección IDM entre 6 y 20 municipios | D67: Listado de IDM seleccionados por municipios y en muestreos no probabilísticos con el 50% de reemplazos y probabilísticos 20%. | F67: 7.5 | G67: 464595 | H67: 1 | I67: Dos días | J67: 0 | K67: =IF(J67=0,0,G67+(J67-1)*ROUND(G67*H67,0)) -> 0 | L67: =IF(J67=0,0,F67+(J67-1)*ROUND(F67*H67,0)) -> 0
A68: 67 | B68: Selección IDM | C68: Selección IDM más de 20 municipios | D68: Listado de IDM seleccionados por municipios y en muestreos no probabilísticos con el 50% de reemplazos y probabilísticos 20%. | F68: 11 | G68: 883442 | H68: 1 | I68: Tres días | J68: 0 | K68: =IF(J68=0,0,G68+(J68-1)*ROUND(G68*H68,0)) -> 0 | L68: =IF(J68=0,0,F68+(J68-1)*ROUND(F68*H68,0)) -> 0
A69: 68 | B69: Selección IDM | C69: Reemplazos de IDM | D69: Por cada pedido de reemplazos, se costea este tiempo. | F69: 2 | G69: 184502.8 | H69: 1 | I69: El mismo día (si se solicita antes del medio día) | J69: 0 | K69: =IF(J69=0,0,G69+(J69-1)*ROUND(G69*H69,0)) -> 0 | L69: =IF(J69=0,0,F69+(J69-1)*ROUND(F69*H69,0)) -> 0
A70: 69 | B70: Selección IDM | C70: Cartografía para un municipio nuevo en la selección de IDM | D70: Se cargan los mapas en pdf a la carpeta de campo. | F70: 3 | G70: 185838 | H70: 0.7 | I70: Un día | J70: 0 | K70: =IF(J70=0,0,G70+(J70-1)*ROUND(G70*H70,0)) -> 0 | L70: =IF(J70=0,0,F70+(J70-1)*ROUND(F70*H70,0)) -> 0
A71: 70 | B71: Metodologías | C71: Metodología (sin diseño muestral) | D71: Dadas las especificaciones técnicas se crea la metodología en word y en matrix. | F71: 2 | G71: 224910 | H71: 0.5 | I71: Un día | J71: 0 | K71: =IF(J71=0,0,G71+(J71-1)*ROUND(G71*H71,0)) -> 0 | L71: =IF(J71=0,0,F71+(J71-1)*ROUND(F71*H71,0)) -> 0
A72: 71 | B72: Metodologías | C72: Metodología (con diseño muestral) | D72: Dadas las especificaciones técnicas se crea la metodología en word y en matrix, previa verificación al diseño muestral propuesto. | F72: 5 | G72: 511766 | H72: 0.5 | I72: Un día | J72: 0 | K72: =IF(J72=0,0,G72+(J72-1)*ROUND(G72*H72,0)) -> 0 | L72: =IF(J72=0,0,F72+(J72-1)*ROUND(F72*H72,0)) -> 0
A73: 72 | B73: Metodologías | C73: Metodología (PA-con diseño muestral probabilístico) | D73: Dadas las especificaciones técnicas se crea la metodología en word y en matrix, previa verificación al diseño muestral probabilístico propuesto. | F73: 10 | G73: 1023532 | H73: 0.5 | I73: Dos días | J73: 0 | K73: =IF(J73=0,0,G73+(J73-1)*ROUND(G73*H73,0)) -> 0 | L73: =IF(J73=0,0,F73+(J73-1)*ROUND(F73*H73,0)) -> 0
A74: 73 | B74: Diseño Muestral | C74: Propuesta Diseño muestral básico | D74: Se entrega el documento en word del diseño, con la muestra propuesta y el universo encontrado. | F74: 7 | G74: 635658 | H74: 0.5 | I74: Dos días | J74: 0 | K74: =IF(J74=0,0,G74+(J74-1)*ROUND(G74*H74,0)) -> 0 | L74: =IF(J74=0,0,F74+(J74-1)*ROUND(F74*H74,0)) -> 0
A75: 74 | B75: Diseño Muestral | C75: Propuesta diseño muestral complejo | D75: Se entrega el documento en word del diseño, con toda la programación en R y marco muestral utilizado. | F75: 70 | G75: 8376940 | I75: A convenir | J75: 0 | K75: =IF(J75=0,0,G75+(J75-1)*ROUND(G75*H75,0)) -> 0 | L75: =IF(J75=0,0,F75+(J75-1)*ROUND(F75*H75,0)) -> 0
A76: 75 | B76: Diseño Muestral | C76: Actualización de diseño muestral complejo | D76: Se entrega el documento en word del diseño, con toda la programación en R y marco muestral final, adicional a todo el acompañamiento y clarificación de dudas. | F76: 120 | G76: 11474240 | I76: A convenir | J76: 0 | K76: =IF(J76=0,0,G76+(J76-1)*ROUND(G76*H76,0)) -> 0 | L76: =IF(J76=0,0,F76+(J76-1)*ROUND(F76*H76,0)) -> 0
A77: 76 | B77: Procesos Especiales | C77: Tabulados con error muestral o estimaciones asistidas por modelos | D77: Se entrega las tablas con las estimaciones de los indicadores y sus errores muestrales, además de la programación en R. | F77: 50 | G77: 5117660 | H77: 1 | I77: A convenir | J77: 0 | K77: =IF(J77=0,0,G77+(J77-1)*ROUND(G77*H77,0)) -> 0 | L77: =IF(J77=0,0,F77+(J77-1)*ROUND(F77*H77,0)) -> 0
A78: * Valores estimados por procesos, las asesorias adicionales o acompañamiento a cliente, serían horas adicionales. | J78: Total | K78: =SUM(K2:K77) -> 2131501
C80: text insight | F80: 4.5 | G80: 480793 | H80: 0.7 | J80: 4 | K80: =IF(J80=0,0,G80+(J80-1)*ROUND(G80*H80,0)) -> 1490458
K81: =+K73+K70+K63 -> 0
G82: =G80*H80 -> 336555.1 | K82: =K3/24*3 -> 68128.375
K84: =+K59+K12*2+K3*2 -> 4263002
D89: =4500000*0.7 -> 3150000
D90: =4500000+4*D89 -> 17100000

Sheet Tarifario Estadistica2
A1: No. | B1: Categoría de servicio | C1: Análisis/servicios | D1: Explicación del modelo o entregable | E1: Ejemplo de entregable | F1: Total de horas estimadas* | G1: Precio de referencia (2024) | H1: Factor para manejar economía de escala | I1: En cuánto tiempo aproximadamente se entrega uno de los procesos, previo agendamiento. | J1: Número de modelos a realizar (Se debe llenar) | K1: Precio de referencia por X modelos - Ahorro por economía de escala
A2: 1 | B2: Procesos Especiales | C2: Modelo de satisfacción (CX-variable respuesta en escala) | D2: Es un modelo (completo y el mejor modelo) que se entrega en una hoja excel, con una hoja inicial de guía para interpretación. La condición es que todas las variables deben venir en escala que miden el nivel de satisfacción. | F2: 2 | G2: 224910 | H2: 0.6 | I2: Dos días | J2: 0 | K2: =IF(J2=0,0,G2+(J2-1)*ROUND(G2*H2,0)) -> 0 | L2: =IF(J2=0,0,F2+(J2-1)*ROUND(F2*H2,0)) -> 0
A3: 2 | B3: Procesos Especiales | C3: Orden de atributos o Análisis de Drivers (variable respuesta en escala) | D3: Un modelo (completo y el mejor modelo) se entrega en una hoja excel, con una hoja inicial de guía para interpretación. La condición es que todas las variables deben venir en escala. | F3: 3 | G3: 286856 | H3: 0.3 | I3: Dos días | J3: 0 | K3: =IF(J3=0,0,G3+(J3-1)*ROUND(G3*H3,0)) -> 0 | L3: =IF(J3=0,0,F3+(J3-1)*ROUND(F3*H3,0)) -> 0
A4: 3 | B4: Procesos Especiales | C4: Orden de atributos o Análisis de Drivers (variable respuesta dicotómica) | D4: Un modelo GLM o de machine learning (el mejor modelo), el cual se entrega en una hoja excel, con una hoja inicial de guía para interpretación. Esto ocurre cuando la variable respuesta (Y) es una variable que contiene ceros y unos. | F4: 4 | G4: 449820 | H4: 0.3 | I4: Dos días | J4: 0 | K4: =IF(J4=0,0,G4+(J4-1)*ROUND(G4*H4,0)) -> 0 | L4: =IF(J4=0,0,F4+(J4-1)*ROUND(F4*H4,0)) -> 0
A5: 4 | B5: Procesos Especiales | C5: Random Forest | D5: Es un modelo dentro de los modelos de machine learning, el cual se entrega en una hoja excel, con una hoja inicial de guía para interpretación. | F5: 3.5 | G5: 317829 | H5: 0.3 | I5: Dos días | J5: 0 | K5: =IF(J5=0,0,G5+(J5-1)*ROUND(G5*H5,0)) -> 0 | L5: =IF(J5=0,0,F5+(J5-1)*ROUND(F5*H5,0)) -> 0
A6: 5 | B6: Procesos Especiales | C6: Modelos GLM (variable con respuesta dicotómica) | D6: Un modelo GLM o de machine learning (el mejor modelo), el cual se entrega en una hoja excel, con una hoja inicial de guía para interpretación. Esto ocurre cuando la variable respuesta (Y) es una variable que contiene ceros y unos. | F6: 9 | G6: 759550 | H6: 0.3 | I6: Dos días | J6: 0 | K6: =IF(J6=0,0,G6+(J6-1)*ROUND(G6*H6,0)) -> 0 | L6: =IF(J6=0,0,F6+(J6-1)*ROUND(F6*H6,0)) -> 0
A7: 6 | B7: Procesos Especiales | C7: Modelos de machine learning | D7: Es un modelo de machine learning que aprende de la información existente y predice la información del indicador para los encuestado. Se entrega un documento del modelo y la BDD con la variable predicha. | F7: 30 | G7: 3878740 | H7: 0.3 | I7: Cuatro días | J7: 0 | K7: =IF(J7=0,0,G7+(J7-1)*ROUND(G7*H7,0)) -> 0 | L7: =IF(J7=0,0,F7+(J7-1)*ROUND(F7*H7,0)) -> 0
A8: 7 | B8: Procesos Especiales | C8: Modelos para tasa de no respuesta muy altas | D8: Es un modelo de machine learning que aprende de la información recolectada y predice, con información existente de los no-encuestado, la información faltante. Se entrega un documento del modelo y la BDD con la variable predicha. | F8: 10 | G8: 1023532 | H8: 0.5 | I8: Tres días | J8: 0 | K8: =IF(J8=0,0,G8+(J8-1)*ROUND(G8*H8,0)) -> 0 | L8: =IF(J8=0,0,F8+(J8-1)*ROUND(F8*H8,0)) -> 0
A9: 8 | B9: Procesos Especiales | C9: Modelo de anonimización | D9: Es un modelo de machine learning que anonimiza variables cualitativa o cuantitativas, para la no posible identificación del encuestado, sin afectar los resultados descriptivos. Se entrega un documento del modelo y la BDD con la variable anonimizada. | E9: Y BDD… | F9: 8 | G9: 899640 | H9: 0.5 | I9: Tres días | J9: 0 | K9: =IF(J9=0,0,G9+(J9-1)*ROUND(G9*H9,0)) -> 0 | L9: =IF(J9=0,0,F9+(J9-1)*ROUND(F9*H9,0)) -> 0
A10: 9 | B10: Procesos Especiales | C10: Graphical modelling (INNO-sin magnitud de la relación) | D10: Se entrega un grafo en archivo .html interactivo, que muestra relaciones entre atributos y una variable respuesta en escala o dicotómica. | F10: 2.5 | G10: 356901 | H10: 0.7 | I10: Dos días | J10: 0 | K10: =IF(J10=0,0,G10+(J10-1)*ROUND(G10*H10,0)) -> 0 | L10: =IF(J10=0,0,F10+(J10-1)*ROUND(F10*H10,0)) -> 0
A11: 10 | B11: Procesos Especiales | C11: Graphical modelling (con magnitud de la relación) | D11: Se entrega un grafo en archivo .html interactivo, que muestra relaciones entre atributos y una variable respuesta en escala o dicotómica, en donde se incluye la magnitud de la relación para cada enlace, que representa la fuerza de la relación existente entre los dos atributos. | F11: 3 | G11: 387874 | H11: 0.7 | I11: Dos días | J11: 0 | K11: =IF(J11=0,0,G11+(J11-1)*ROUND(G11*H11,0)) -> 0 | L11: =IF(J11=0,0,F11+(J11-1)*ROUND(F11*H11,0)) -> 0 | M11: 271512 | N11: =+K11-L11-M11 -> -271512 | O11: =+N11*2 -> -543024
A12: 11 | B12: Procesos Especiales | C12: Graphical modelling + Orden de atributos (variable respuesta en escala) | D12: Se entrega un grafo en archivo .html interactivo y un modelo de orden de atributos (la condición es que la variable respuesta debe ser en escala). | F12: 5 | G12: 511766 | H12: 0.7 | I12: Dos días | J12: 0 | K12: =IF(J12=0,0,G12+(J12-1)*ROUND(G12*H12,0)) -> 0 | L12: =IF(J12=0,0,F12+(J12-1)*ROUND(F12*H12,0)) -> 0
A13: 12 | B13: Procesos Especiales | C13: Graphical modelling + Orden de atributos (variable respuesta dicotómica) | D13: Se entrega un grafo en archivo .html interactivo y un modelo de orden de atributos (la condición es que la variable respuesta debe ser dicotómica). | F13: 5.5 | G13: 542739 | H13: 0.7 | I13: Dos días | J13: 0 | K13: =IF(J13=0,0,G13+(J13-1)*ROUND(G13*H13,0)) -> 0 | L13: =IF(J13=0,0,F13+(J13-1)*ROUND(F13*H13,0)) -> 0
A14: 13 | B14: Procesos Especiales | C14: Correlaciones/asociaciones | D14: Se entrega en archivo excel con la matrix correlaciones o asociaciones, con las variables señaladas sin apertura. | F14: 1 | G14: 162964 | H14: 0.7 | I14: Dos días | J14: 0 | K14: =IF(J14=0,0,G14+(J14-1)*ROUND(G14*H14,0)) -> 0 | L14: =IF(J14=0,0,F14+(J14-1)*ROUND(F14*H14,0)) -> 0
A15: 14 | B15: Procesos Especiales | C15: Inferencia Estadística (diferencias, pruebas de hipotesis, metas, análisis migratorio) | D15: Se entrega en archivo excel con el resultado de la prueba estadística o inferencia señalada sin apertura. | F15: 4 | G15: 449820 | H15: 0.7 | I15: Dos días | J15: 0 | K15: =IF(J15=0,0,G15+(J15-1)*ROUND(G15*H15,0)) -> 0 | L15: =IF(J15=0,0,F15+(J15-1)*ROUND(F15*H15,0)) -> 0
A16: 15 | B16: Procesos Especiales | C16: Text analytics (CREATIVE-De palabras) | D16: Se entrega dos grafos, uno el original y el otro con su debida partición, las métricas y la identificación de cada palabra con su grupo y número de menciones. | F16: 5 | G16: 511766 | H16: 0.75 | I16: Dos días | J16: 0 | K16: =IF(J16=0,0,G16+(J16-1)*ROUND(G16*H16,0)) -> 0 | L16: =IF(J16=0,0,F16+(J16-1)*ROUND(F16*H16,0)) -> 0
A17: 16 | B17: Procesos Especiales | C17: Text Analytics por LDA ( frases construidas) | D17: Se entrega una clasificación de verbatims, que ayuda a la construcción de frases que hace la SL, luego con las frases se hace un grafo, donde se precisan colores y edición corta de la frase, lo cual se entrega en un archivo .html. | F17: 13 | G17: 1209370 | I17: Una semana | J17: 0 | K17: =IF(J17=0,0,G17+(J17-1)*ROUND(G17*H17,0)) -> 0 | L17: =IF(J17=0,0,F17+(J17-1)*ROUND(F17*H17,0)) -> 0
A18: 17 | B18: Procesos Especiales | C18: Text analytics con segmentación y depurado de palabras | D18: Se entrega máximo tres grafos, el original con su debida partición y máximo dos depuraciones de palabras, las métricas y la identificación de cada palabra con su grupo y número de menciones. | F18: 8 | G18: 899640 | H18: 0.75 | I18: Tres días | J18: 0 | K18: =IF(J18=0,0,G18+(J18-1)*ROUND(G18*H18,0)) -> 0 | L18: =IF(J18=0,0,F18+(J18-1)*ROUND(F18*H18,0)) -> 0
A19: 18 | B19: Procesos Especiales | C19: Text analytics depurado de marcas | D19: Se entrega máximo tres grafos con máximo cuatro marcas, el original con su debida partición de marcas y máximo dos depuraciones de palabras de las marcas, las métricas y la identificación de cada palabra con su grupo y número de menciones. | F19: 11 | G19: 1085478 | H19: 0.75 | I19: Tres días | J19: 0 | K19: =IF(J19=0,0,G19+(J19-1)*ROUND(G19*H19,0)) -> 0 | L19: =IF(J19=0,0,F19+(J19-1)*ROUND(F19*H19,0)) -> 0
A20: 19 | B20: Procesos Especiales | C20: Text analytics con segmentación y asociando imágenes | D20: Es un archivo .html con un grafo, un archivo excel con identificación para cada registro el grupo al que pertenece y la identificación de las imágenes más frecuentes en cada grupo. | F20: 11 | G20: 1085478 | I20: Tres días | J20: 0 | K20: =IF(J20=0,0,G20+(J20-1)*ROUND(G20*H20,0)) -> 0 | L20: =IF(J20=0,0,F20+(J20-1)*ROUND(F20*H20,0)) -> 0
A21: 20 | B21: Procesos Especiales | C21: Penalty Analysis | D21: Se entregan dos archivos .html con las penalidades y otro con los porcentajes de cada grupo por atributos, estos mismos archivos se entregan en excel. | F21: 2 | G21: 224910 | H21: 0.5 | I21: Un día | J21: 0 | K21: =IF(J21=0,0,G21+(J21-1)*ROUND(G21*H21,0)) -> 0 | L21: =IF(J21=0,0,F21+(J21-1)*ROUND(F21*H21,0)) -> 0
A22: 21 | B22: Procesos Especiales | C22: Reglas de asociación | D22: Ante la pregunta de los productos que compró, se pueden identificar productos complementarios y sustitutos, los cuales son identificados en este análisis que se entrega en excel, con el calculo de lift. | F22: 3 | G22: 387874 | H22: 0.5 | I22: Dos días | J22: 0 | K22: =IF(J22=0,0,G22+(J22-1)*ROUND(G22*H22,0)) -> 0 | L22: =IF(J22=0,0,F22+(J22-1)*ROUND(F22*H22,0)) -> 0
A23: 22 | B23: Procesos Especiales | C23: Indicadores (ACP) | D23: El indicador se entrega en una hoja excel, con el peso de cada una de las variables involucradas en el análisis, su matrix de correlaciones, el calculo del indicador en una apertura requerida y el cálculo del indicador en cada uno de los registros del estudio. | F23: 4 | G23: 449820 | H23: 0.7 | I23: Dos días | J23: 0 | K23: =IF(J23=0,0,G23+(J23-1)*ROUND(G23*H23,0)) -> 0 | L23: =IF(J23=0,0,F23+(J23-1)*ROUND(F23*H23,0)) -> 0
A24: 23 | B24: Procesos Especiales | C24: Análisis factorial (redución o agrupamiento de variables) | D24: Se entrega el cluster del agrupamiento de variables, junto con la matrix de similitudes, el dendograma y el peso de cada variables a los factores creaados en excel. | F24: 5 | G24: 612784 | H24: 0.7 | I24: Tres días | J24: 0 | K24: =IF(J24=0,0,G24+(J24-1)*ROUND(G24*H24,0)) -> 0 | L24: =IF(J24=0,0,F24+(J24-1)*ROUND(F24*H24,0)) -> 0
A25: 24 | B25: Procesos Especiales | C25: Residuales ajustados | D25: Es una matrix de distancias estándarizadas de marcas vs atributos, donde se visualiza la asociaciones significativas tanto en la matrix cómo gráficamente, el archivo se entrega en excel. | F25: 3 | G25: 286856 | H25: 0.7 | I25: Dos días | J25: 0 | K25: =IF(J25=0,0,G25+(J25-1)*ROUND(G25*H25,0)) -> 0 | L25: =IF(J25=0,0,F25+(J25-1)*ROUND(F25*H25,0)) -> 0
A26: 25 | B26: Procesos Especiales | C26: Mapa de correspondencia | D26: Se entrega un mapa y dendograma en una hoja excel, con las coordenadas de cada punto, las proyecciones de los casos ilustrativos (cuando hay bases muy pequeñas) y las agrupaciones sombreadas a partir de los análisis de dendogramas. | F26: 4.5 | G26: 480793 | H26: 0.7 | I26: Dos días | J26: 0 | K26: =IF(J26=0,0,G26+(J26-1)*ROUND(G26*H26,0)) -> 0 | L26: =IF(J26=0,0,F26+(J26-1)*ROUND(F26*H26,0)) -> 0
A27: 26 | B27: Procesos Especiales | C27: Mapa de correspondencia+residuales | D27: Se entrega el mapa de correspondencia y la matrix de residuales, para evidenciar no solo las agrupaciones sombreadas sino las relaciones más significativas entre atributos y marcas. | F27: 5.5 | G27: 542739 | H27: 0.7 | I27: Tres días | J27: 0 | K27: =IF(J27=0,0,G27+(J27-1)*ROUND(G27*H27,0)) -> 0 | L27: =IF(J27=0,0,F27+(J27-1)*ROUND(F27*H27,0)) -> 0
A28: 27 | B28: Procesos Especiales | C28: Equity actitudinal con funnel | D28: Es un archivo excel con el cálculo del AE para cada registro y marca, además de otra hoja donde se encuentra el consolidado de los resutlados del equity por marca y la clasificación cualitativa de este. | F28: 3 | G28: 286856 | H28: 0.8 | I28: Dos días | J28: 0 | K28: =IF(J28=0,0,G28+(J28-1)*ROUND(G28*H28,0)) -> 0 | L28: =IF(J28=0,0,F28+(J28-1)*ROUND(F28*H28,0)) -> 0
A29: 28 | B29: Procesos Especiales | C29: Segmentación o perfilamiento (Análisis de Cluster) | D29: Tres opciones de perfiles con el cruce de cada una de las variables del perfilamiento y el peso de cada perfil, además de los residuales. | F29: 14 | G29: 1271316 | H29: 0.9 | I29: Tres días | J29: 0 | K29: =IF(J29=0,0,G29+(J29-1)*ROUND(G29*H29,0)) -> 0 | L29: =IF(J29=0,0,F29+(J29-1)*ROUND(F29*H29,0)) -> 0
A30: 29 | B30: Procesos Especiales | C30: Segmentación cruzada | D30: Se entregan dos segmentaciones una usualmente de la muestra de personas y la otra segmentación de ocasiones o necesidades, las cuales se cruzan para identificar los mejores segmentos. | F30: 28 | G30: 2542632 | I30: Siete días | J30: 0 | K30: =IF(J30=0,0,G30+(J30-1)*ROUND(G30*H30,0)) -> 0 | L30: =IF(J30=0,0,F30+(J30-1)*ROUND(F30*H30,0)) -> 0
A31: 30 | B31: Procesos Especiales | C31: Segmentación (Análisis de clúster) + Algoritmo (typing tool) | D31: Tres opciones de segmentación con el cruce de cada una de las variables de la segmentación, el peso de cada perfil y un algoritmo en excel o shiny para una clasificación a posteriori. | F31: 30 | G31: 2666524 | H31: 0.9 | I31: Dos semanas | J31: 0 | K31: =IF(J31=0,0,G31+(J31-1)*ROUND(G31*H31,0)) -> 0 | L31: =IF(J31=0,0,F31+(J31-1)*ROUND(F31*H31,0)) -> 0
A32: 31 | B32: Procesos Especiales | C32: Turf | D32: Se entrega un gráfico en excel, con el ordenamiento y contribución de cada medio, canal o ente de evaluación. | F32: 2.5 | G32: 255883 | H32: 0.4 | I32: Dos días | J32: 0 | K32: =IF(J32=0,0,G32+(J32-1)*ROUND(G32*H32,0)) -> 0 | L32: =IF(J32=0,0,F32+(J32-1)*ROUND(F32*H32,0)) -> 0
A33: 32 | B33: Procesos Especiales | C33: Odds ration | D33: Se entrega en una hoja excel las frecuencias, el odd para las variables señaladas, y un ejemplo de la interpretación. | F33: 2 | G33: 224910 | H33: 0.5 | I33: Dos días | J33: 0 | K33: =IF(J33=0,0,G33+(J33-1)*ROUND(G33*H33,0)) -> 0 | L33: =IF(J33=0,0,F33+(J33-1)*ROUND(F33*H33,0)) -> 0
A34: 33 | B34: Procesos Especiales | C34: Indicadores simples | D34: Se entrega una tabla en excel con el indicador calculado. | F34: 2.5 | G34: 255883 | H34: 0.9 | I34: Dos días | J34: 0 | K34: =IF(J34=0,0,G34+(J34-1)*ROUND(G34*H34,0)) -> 0 | L34: =IF(J34=0,0,F34+(J34-1)*ROUND(F34*H34,0)) -> 0
A35: 34 | B35: Procesos Especiales | C35: Penalty & Rewards | D35: Se entrega un archivo excel con los pesos de los factores y atributos, para un segmento, además de las penalidades y rewards. | F35: 5 | G35: 511766 | H35: 0.6 | I35: Dos días | J35: 0 | K35: =IF(J35=0,0,G35+(J35-1)*ROUND(G35*H35,0)) -> 0 | L35: =IF(J35=0,0,F35+(J35-1)*ROUND(F35*H35,0)) -> 0
A36: 35 | B36: Procesos Especiales | C36: Aporte entre marcas (similar a Brand Halo) | D36: Es un archivo en excel que muestra el aporte de cada atributo o submarca a una marca principal, junto con las diferencias significativas de los resultados. | F36: 4 | G36: 449820 | H36: 0.3 | I36: Dos días | J36: 0 | K36: =IF(J36=0,0,G36+(J36-1)*ROUND(G36*H36,0)) -> 0 | L36: =IF(J36=0,0,F36+(J36-1)*ROUND(F36*H36,0)) -> 0
A37: 36 | B37: Procesos Especiales | C37: Aplicación de algoritmo de segmentación | D37: Previo entrega de un algoritmo de segmentación, este se aplica a una nueva BDD y se entrega en excel el cluster de cada registro. | F37: 3 | G37: 286856 | H37: 0.75 | I37: Un día | J37: 0 | K37: =IF(J37=0,0,G37+(J37-1)*ROUND(G37*H37,0)) -> 0 | L37: =IF(J37=0,0,F37+(J37-1)*ROUND(F37*H37,0)) -> 0
A38: 37 | B38: Procesos Especiales | C38: Análisis chaid (Árboles de clasificación) | D38: Un árbol de clasificiación con su debida documentación que presenta el análisis e interpretación. | F38: 3.5 | G38: 418847 | H38: 0.75 | I38: Dos días | J38: 0 | K38: =IF(J38=0,0,G38+(J38-1)*ROUND(G38*H38,0)) -> 0 | L38: =IF(J38=0,0,F38+(J38-1)*ROUND(F38*H38,0)) -> 0
A39: 38 | B39: Procesos Especiales | C39: Análisis chaid (CX-Árboles de clasificación) | D39: Un árbol de clasificiación, para una variable categórica como NPS o Satisfacción con su debida interpretación, se entrega en un archivo excel. | F39: 2.5 | G39: 255883 | H39: 0.75 | I39: Dos días | J39: 0 | K39: =IF(J39=0,0,G39+(J39-1)*ROUND(G39*H39,0)) -> 0 | L39: =IF(J39=0,0,F39+(J39-1)*ROUND(F39*H39,0)) -> 0
A40: 39 | B40: Procesos Especiales | C40: Análisis de causalidad con redes bayesianas (similar a IBN) | D40: Se entrega un archivo .html con un grafo acíclico dirigido, basado en redes bayesinas que permiten encontrar la causalidad de la relación entre dos atributos (flechas). | F40: 13 | G40: 1209370 | H40: 0.5 | I40: Una semana | J40: 0 | K40: =IF(J40=0,0,G40+(J40-1)*ROUND(G40*H40,0)) -> 0 | L40: =IF(J40=0,0,F40+(J40-1)*ROUND(F40*H40,0)) -> 0
A41: 40 | B41: Procesos Especiales | C41: PSM | D41: Una hoja excel para un PSM con el gráfico que contiene la identificación de los puntos de intercepción y los tabulados de los precios asignados. | F41: 3.5 | G41: 317829 | H41: 0.6 | I41: Dos días | J41: 0 | K41: =IF(J41=0,0,G41+(J41-1)*ROUND(G41*H41,0)) -> 0 | L41: =IF(J41=0,0,F41+(J41-1)*ROUND(F41*H41,0)) -> 0
A42: 41 | B42: Procesos Especiales | C42: Árbol de decisión del Shopper | D42: Se entrega en un archivo excel el ranking, que describen el peso de los atributos a la escogencia. | F42: 5 | G42: 511766 | H42: 0.9 | I42: Tres días | J42: 0 | K42: =IF(J42=0,0,G42+(J42-1)*ROUND(G42*H42,0)) -> 0 | L42: =IF(J42=0,0,F42+(J42-1)*ROUND(F42*H42,0)) -> 0
... A45: 44 | B45: Procesos Especiales | C45: Elasticidad | D45: Se entrega un archivo excel con la tabla de precios con su respectiva participación y calculo de la elasticidad. | F45: 5 | G45: 511766 | H45: 0.8 | I45: Dos días | J45: 0 | K45: =IF(J45=0,0,G45+(J45-1)*ROUND(G45*H45,0)) -> 0 | L45: =IF(J45=0,0,F45+(J45-1)*ROUND(F45*H45,0)) -> 0
A46: 45 | B46: Procesos Especiales | C46: Elasticidad (similar a Gabor Granger) | D46: Se entrega un archivo excel con la curva de sensibilidad al precio, además de la tabla de precios con su respectiva participación y calculo de la elesticidad. | F46: 8 | G46: 697604 | I46: Tres días | J46: 0 | K46: =IF(J46=0,0,G46+(J46-1)*ROUND(G46*H46,0)) -> 0 | L46: =IF(J46=0,0,F46+(J46-1)*ROUND(F46*H46,0)) -> 0
A47: 46 | B47: Procesos Especiales | C47: Modelo de Atributos de Precio por Marca (similar a BIM) | D47: Es un agrupamiento de atributos de precios evaluados en diferentes marcas (cliente y competencia), se entrega en excel un análisis factorial con el agrupamiento de atributos, un modelo de machine learning que revela el peso de los factores y unos residuales ajustados complementado con mapa de correspondencia para evaluar el desempeño de la marca y su competencia. | F47: 16 | G47: 1395208 | I47: Una semana | J47: 0 | K47: =IF(J47=0,0,G47+(J47-1)*ROUND(G47*H47,0)) -> 0 | L47: =IF(J47=0,0,F47+(J47-1)*ROUND(F47*H47,0)) -> 0
A48: 47 | B48: Procesos Especiales | C48: SOVA | D48: Se entrega una tabla en excel para el producto de prueba con el resultado del source of volumen por cada producto y cada categoría. | F48: 5 | G48: 511766 | H48: 0.9 | I48: Dos días | J48: 0 | K48: =IF(J48=0,0,G48+(J48-1)*ROUND(G48*H48,0)) -> 0 | L48: =IF(J48=0,0,F48+(J48-1)*ROUND(F48*H48,0)) -> 0
A49: 48 | B49: Procesos Especiales | C49: Análisis de consistencia (Alpha cronbach) | D49: Se entrega en un excel el calculo e interpretación del coeficiente Alfa de Cronbach para la variable de interés, lo cuál muestra el nivel de confiabilidad interna de la pregunta, dentro del cuestionario, la consistencia de la escala y si es la misma variable medida en diferentes olas, muestra la consistencia en el tiempo, adicionando una prueba ANOVA. | F49: 5.5 | G49: 542739 | H49: 0.9 | I49: Dos días | J49: 0 | K49: =IF(J49=0,0,G49+(J49-1)*ROUND(G49*H49,0)) -> 0 | L49: =IF(J49=0,0,F49+(J49-1)*ROUND(F49*H49,0)) -> 0
A50: 49 | B50: Procesos Especiales | C50: Ecosystem Flow | D50: Es un grafo .html interactivo, con sus respectivas métricas de penetración y estadísticas de resúmen por apertura como franja horaria, de información suministrada de la interacción de la persona con la web, con entregable en power BI. | F50: 18 | G50: 1519100 | H50: 0.9 | I50: Cuatro días | J50: 0 | K50: =IF(J50=0,0,G50+(J50-1)*ROUND(G50*H50,0)) -> 0 | L50: =IF(J50=0,0,F50+(J50-1)*ROUND(F50*H50,0)) -> 0
A51: 50 | B51: Procesos Especiales | C51: Channel Vision | D51: Un AE, Turf no ponderado, turf ponderado por AE, indicador de afinidad y dos ordenes de atributos-incluye asesoria de movido de BDD. | F51: 18 | G51: 1519100 | H51: 0.75 | I51: Tres días | J51: 0 | K51: =IF(J51=0,0,G51+(J51-1)*ROUND(G51*H51,0)) -> 0 | L51: =IF(J51=0,0,F51+(J51-1)*ROUND(F51*H51,0)) -> 0
A52: 51 | B52: Procesos Especiales | C52: Potential modelling | D52: Se entregan un archivo .html con el resultado de la simulación para cada atributo y una tabla en excel con los valores de resúmen de la simulación. | F52: 4 | G52: 449820 | H52: 0.9 | I52: Dos días | J52: 0 | K52: =IF(J52=0,0,G52+(J52-1)*ROUND(G52*H52,0)) -> 0 | L52: =IF(J52=0,0,F52+(J52-1)*ROUND(F52*H52,0)) -> 0
A53: 52 | B53: Procesos Especiales | C53: t-plot | D53: Se entrega un gráfico en excel con la comparación estadística de dos grupos, con sus respectivas bandas. | F53: 4 | G53: 449820 | H53: 0.9 | I53: Dos días | J53: 0 | K53: =IF(J53=0,0,G53+(J53-1)*ROUND(G53*H53,0)) -> 0 | L53: =IF(J53=0,0,F53+(J53-1)*ROUND(F53*H53,0)) -> 0
A54: 53 | B54: Procesos Especiales | C54: Análisis Conjoint (CBC) | D54: Un archivo en excel que contiene la importancia y utilidades de los atributos y variables. | F54: 25 | G54: 2154758 | H54: 0.95 | I54: Tres días | J54: 0 | K54: =IF(J54=0,0,G54+(J54-1)*ROUND(G54*H54,0)) -> 0 | L54: =IF(J54=0,0,F54+(J54-1)*ROUND(F54*H54,0)) -> 0
A55: 54 | B55: Procesos Especiales | C55: Análisis Conjoint (CBC) con elasticidades | D55: Un archivo en excel que contiene la importancia y utilidades de los atributos y variables, además de las elesticidades marginales, cruzadas y la canibalización. | F55: 42 | G55: 3813948 | H55: 0.95 | I55: Una semana | J55: 0 | K55: =IF(J55=0,0,G55+(J55-1)*ROUND(G55*H55,0)) -> 0 | L55: =IF(J55=0,0,F55+(J55-1)*ROUND(F55*H55,0)) -> 0
A56: 55 | B56: Procesos Especiales | C56: Espacios de demanda (similar Demand Space) | D56: Se tienen dos entregas, la primera es un random Forest para precisar las variables que más pesan más sobre una variable de volumen o consumo y la segunda es la segmentación de personas o ocasiones o necesidades, todo se entrega en excel. | F56: 26 | G56: 3226884 | H56: 1 | I56: Siete días | J56: 0 | K56: =IF(J56=0,0,G56+(J56-1)*ROUND(G56*H56,0)) -> 0 | L56: =IF(J56=0,0,F56+(J56-1)*ROUND(F56*H56,0)) -> 0
A57: 56 | B57: Procesos Especiales | C57: Means - End Chain (Text Analytics de Atributos-Beneficios-Valores) | D57: Es un archivo en .html que muestra un grafo que proviene de una análisis por LDA de atributos, beneficios y valores, y un archivo excel con la frecuencias de cada atributo, beneficio y valor. | F57: 39 | G57: 3224038 | H57: 0.5 | I57: Dos semanas | J57: 0 | K57: =IF(J57=0,0,G57+(J57-1)*ROUND(G57*H57,0)) -> 0 | L57: =IF(J57=0,0,F57+(J57-1)*ROUND(F57*H57,0)) -> 0
A58: 57 | B58: Procesos Especiales | C58: Dendograma | D58: Es un gráfico descriptivo de la segmentación de atributos o personas | F58: 5 | G58: 511766 | H58: 1 | I58: Dos días | J58: 0 | K58: =IF(J58=0,0,G58+(J58-1)*ROUND(G58*H58,0)) -> 0 | L58: =IF(J58=0,0,F58+(J58-1)*ROUND(F58*H58,0)) -> 0
A59: 58 | B59: Ponderación | C59: Ponderación por una variable o dos variables cruzadas | D59: Se sube a matrix el archivo en excel de la base de datos muestrales con el ponderador para cada registro y se debe aprobar el pegue de este ponderador a la BDD final. | F59: 3 | G59: 255883 | H59: 1 | I59: Un día | J59: 0 | K59: =IF(J59=0,0,G59+(J59-1)*ROUND(G59*H59,0)) -> 0 | L59: =IF(J59=0,0,F59+(J59-1)*ROUND(F59*H59,0)) -> 0
A60: 59 | B60: Ponderación | C60: Ponderación dos variables (no cruzadas) | F60: 4.5 | G60: 480793 | H60: 1 | I60: Un día | J60: 0 | K60: =IF(J60=0,0,G60+(J60-1)*ROUND(G60*H60,0)) -> 0 | L60: =IF(J60=0,0,F60+(J60-1)*ROUND(F60*H60,0)) -> 0
A61: 60 | B61: Ponderación | C61: Ponderación tres o más variables no cruzadas | F61: 9 | G61: 759550 | H61: 1 | I61: Un día | J61: 0 | K61: =IF(J61=0,0,G61+(J61-1)*ROUND(G61*H61,0)) -> 0 | L61: =IF(J61=0,0,F61+(J61-1)*ROUND(F61*H61,0)) -> 0
A62: 61 | B62: Ponderación | C62: Ponderación por variable diferente a universo (ejemplo ventas) | F62: 14 | G62: 1271316 | H62: 1 | I62: Tres días | J62: 0 | K62: =IF(J62=0,0,G62+(J62-1)*ROUND(G62*H62,0)) -> 0 | L62: =IF(J62=0,0,F62+(J62-1)*ROUND(F62*H62,0)) -> 0
A63: 62 | B63: Ponderación | C63: Factor de Expansión | D63: Se deben incluir unas preguntas de validación en el cuestionario, según el diseño muestral y se requiere especificar en la metodología las variables a usar. El archivo se entrega en excel de la base de datos muestrales con el factor de expansión para cada registro y las tablas del universo representado por esta encuesta. | F63: 19 | G63: 1581046 | H63: 1 | I63: Tres días | J63: 0 | K63: =IF(J63=0,0,G63+(J63-1)*ROUND(G63*H63,0)) -> 0 | L63: =IF(J63=0,0,F63+(J63-1)*ROUND(F63*H63,0)) -> 0
A64: 63 | B64: Ponderación | C64: Factor de Expansión en muestreos no-probabilísticos (estimaciones doblemente robustas) | D64: Se deben incluir unas preguntas de validación en el cuestionario de un estuid probabilístico, según el diseño muestral y se requiere especificar en la metodología las variables a usar. El archivo se entrega en excel de la base de datos muestrales con el factor de expansión para cada registro y las tablas del universo representado por esta encuesta. | F64: 56 | G64: 5489336 | H64: 1 | I64: Una semana | J64: 0 | K64: =IF(J64=0,0,G64+(J64-1)*ROUND(G64*H64,0)) -> 0 | L64: =IF(J64=0,0,F64+(J64-1)*ROUND(F64*H64,0)) -> 0
A65: 64 | B65: Selección IDM | C65: Selección IDM por listado | D65: Se entrega el listado de los seleccionados con el 20% de sobremuestra. | F65: 5 | G65: 511766 | H65: 1 | I65: Dos días | J65: 0 | K65: =IF(J65=0,0,G65+(J65-1)*ROUND(G65*H65,0)) -> 0 | L65: =IF(J65=0,0,F65+(J65-1)*ROUND(F65*H65,0)) -> 0
A66: 65 | B66: Selección IDM | C66: Selección IDM de municipios menos de 5 municpios) | D66: Listado de IDM seleccionados por municipios y en muestreos no probabilísticos con el 50% de reemplazos y probabilísticos 20%. | F66: 4.5 | G66: 278757 | H66: 1 | I66: Dos días | J66: 0 | K66: =IF(J66=0,0,G66+(J66-1)*ROUND(G66*H66,0)) -> 0 | L66: =IF(J66=0,0,F66+(J66-1)*ROUND(F66*H66,0)) -> 0
A67: 66 | B67: Selección IDM | C67: Selección IDM entre 6 y 20 municipios | D67: Listado de IDM seleccionados por municipios y en muestreos no probabilísticos con el 50% de reemplazos y probabilísticos 20%. | F67: 7.5 | G67: 464595 | H67: 1 | I67: Dos días | J67: 0 | K67: =IF(J67=0,0,G67+(J67-1)*ROUND(G67*H67,0)) -> 0 | L67: =IF(J67=0,0,F67+(J67-1)*ROUND(F67*H67,0)) -> 0
A68: 67 | B68: Selección IDM | C68: Selección IDM más de 20 municipios | D68: Listado de IDM seleccionados por municipios y en muestreos no probabilísticos con el 50% de reemplazos y probabilísticos 20%. | F68: 11 | G68: 883442 | H68: 1 | I68: Tres días | J68: 0 | K68: =IF(J68=0,0,G68+(J68-1)*ROUND(G68*H68,0)) -> 0 | L68: =IF(J68=0,0,F68+(J68-1)*ROUND(F68*H68,0)) -> 0
A69: 68 | B69: Selección IDM | C69: Reemplazos de IDM | D69: Por cada pedido de reemplazos, se costea este tiempo. | F69: 2 | G69: 184502.8 | H69: 1 | I69: El mismo día (si se solicita antes del medio día) | J69: 0 | K69: =IF(J69=0,0,G69+(J69-1)*ROUND(G69*H69,0)) -> 0 | L69: =IF(J69=0,0,F69+(J69-1)*ROUND(F69*H69,0)) -> 0
A70: 69 | B70: Selección IDM | C70: Cartografía para un municipio nuevo en la selección de IDM | D70: Se cargan los mapas en pdf a la carpeta de campo. | F70: 3 | G70: 185838 | H70: 0.7 | I70: Un día | J70: 0 | K70: =IF(J70=0,0,G70+(J70-1)*ROUND(G70*H70,0)) -> 0 | L70: =IF(J70=0,0,F70+(J70-1)*ROUND(F70*H70,0)) -> 0
A71: 70 | B71: Metodologías | C71: Metodología (sin diseño muestral) | D71: Dadas las especificaciones técnicas se crea la metodología en word y en matrix. | F71: 2 | G71: 224910 | H71: 0.5 | I71: Un día | J71: 0 | K71: =IF(J71=0,0,G71+(J71-1)*ROUND(G71*H71,0)) -> 0 | L71: =IF(J71=0,0,F71+(J71-1)*ROUND(F71*H71,0)) -> 0
A72: 71 | B72: Metodologías | C72: Metodología (con diseño muestral) | D72: Dadas las especificaciones técnicas se crea la metodología en word y en matrix, previa verificación al diseño muestral propuesto. | F72: 5 | G72: 511766 | H72: 0.5 | I72: Un día | J72: 0 | K72: =IF(J72=0,0,G72+(J72-1)*ROUND(G72*H72,0)) -> 0 | L72: =IF(J72=0,0,F72+(J72-1)*ROUND(F72*H72,0)) -> 0
A73: 72 | B73: Metodologías | C73: Metodología (PA-con diseño muestral probabilístico) | D73: Dadas las especificaciones técnicas se crea la metodología en word y en matrix, previa verificación al diseño muestral probabilístico propuesto. | F73: 10 | G73: 1023532 | H73: 0.5 | I73: Dos días | J73: 0 | K73: =IF(J73=0,0,G73+(J73-1)*ROUND(G73*H73,0)) -> 0 | L73: =IF(J73=0,0,F73+(J73-1)*ROUND(F73*H73,0)) -> 0
A74: 73 | B74: Diseño Muestral | C74: Propuesta Diseño muestral básico | D74: Se entrega el documento en word del diseño, con la muestra propuesta y el universo encontrado. | F74: 7 | G74: 635658 | H74: 0.5 | I74: Dos días | J74: 0 | K74: =IF(J74=0,0,G74+(J74-1)*ROUND(G74*H74,0)) -> 0 | L74: =IF(J74=0,0,F74+(J74-1)*ROUND(F74*H74,0)) -> 0
A75: 74 | B75: Diseño Muestral | C75: Propuesta diseño muestral complejo | D75: Se entrega el documento en word del diseño, con toda la programación en R y marco muestral utilizado. | F75: 70 | G75: 8376940 | I75: A convenir | J75: 0 | K75: =IF(J75=0,0,G75+(J75-1)*ROUND(G75*H75,0)) -> 0 | L75: =IF(J75=0,0,F75+(J75-1)*ROUND(F75*H75,0)) -> 0
A76: 75 | B76: Diseño Muestral | C76: Actualización de diseño muestral complejo | D76: Se entrega el documento en word del diseño, con toda la programación en R y marco muestral final, adicional a todo el acompañamiento y clarificación de dudas. | F76: 120 | G76: 11474240 | I76: A convenir | J76: 0 | K76: =IF(J76=0,0,G76+(J76-1)*ROUND(G76*H76,0)) -> 0 | L76: =IF(J76=0,0,F76+(J76-1)*ROUND(F76*H76,0)) -> 0
A77: 76 | B77: Procesos Especiales | C77: Tabulados con error muestral o estimaciones asistidas por modelos | D77: Se entrega las tablas con las estimaciones de los indicadores y sus errores muestrales, además de la programación en R. | F77: 50 | G77: 5117660 | H77: 1 | I77: A convenir | J77: 0 | K77: =IF(J77=0,0,G77+(J77-1)*ROUND(G77*H77,0)) -> 0 | L77: =IF(J77=0,0,F77+(J77-1)*ROUND(F77*H77,0)) -> 0
A78: * Valores estimados por procesos, las asesorias adicionales o acompañamiento a cliente, serían horas adicionales. | J78: Total | K78: =SUM(K2:K77) -> 0
C80: text insight | F80: 4.5 | G80: 480793 | H80: 0.7 | J80: 4 | K80: =IF(J80=0,0,G80+(J80-1)*ROUND(G80*H80,0)) -> 1490458
K81: =+K73+K70+K63 -> 0
G82: =G80*H80 -> 336555.1 | K82: =K3/24*3 -> 0
K84: =+K59+K12*2+K3*2 -> 0
D89: =4500000*0.7 -> 3150000
D90: =4500000+4*D89 -> 17100000

Sheet MuestraTec1
C2: NSE 1 | D2: NSE 2 | E2: NSE 3 | F2: NSE 4 | G2: NSE 5 | H2: NSE 6 | I2: Total
B3: Bogotá | C3: 175822 | D3: 772989 | E3: 808409 | F3: 325667 | G3: 106394 | H3: 83335 | I3: =SUM(C3:H3) -> 2272616
B4: Barranquilla | C4: 120736 | D4: 72430 | E4: 82028 | F4: 48172 | G4: 17448 | H4: 13225 | I4: =SUM(C4:H4) -> 354039
B5: Medellín | C5: 135532 | D5: 319438 | E5: 265934 | F5: 105602 | G5: 77322 | H5: 40911 | I5: =SUM(C5:H5) -> 944739
B6: Cali | C6: 120201 | D6: 168508 | E6: 195620 | F6: 98481 | G6: 62130 | H6: 23429 | I6: =SUM(C6:H6) -> 668369
B7: B/manga | C7: 38127 | D7: 33305 | E7: 45924 | F7: 61562 | G7: 6002 | H7: 10180 | I7: =SUM(C7:H7) -> 195100
B8: C/gena | C8: 117585 | D8: 83838 | E8: 57300 | F8: 20294 | G8: 12086 | H8: 13328 | I8: =SUM(C8:H8) -> 304431
B9: Otras Ciudades | C9: 755665 | D9: 737405 | E9: 504312 | F9: 200497 | G9: 79576 | H9: 45633 | I9: =SUM(C9:H9) -> 2323088
B11: Bogotá | C11: =+C3/$I$3 -> 0.077365468 | D11: =+D3/$I$3 -> 0.34013181 | E11: =+E3/$I$3 -> 0.35571738 | F11: =+F3/$I$3 -> 0.1433005 | G11: =+G3/$I$3 -> 0.046815652 | H11: =+H3/$I$3 -> 0.036669195 | I11: =SUM(C11:H11) -> 1 | K11: Por favor consultar con estadistica Incorporación de ciudades o más regiones fuera de las 6 principales para un aterrizaje más detallado de costos
B12: Barranquilla | C12: =+C4/$I$4 -> 0.34102458 | D12: =+D4/$I$4 -> 0.20458198 | E12: =+E4/$I$4 -> 0.23169199 | F12: =+F4/$I$4 -> 0.13606411 | G12: =+G4/$I$4 -> 0.049282706 | H12: =+H4/$I$4 -> 0.037354642 | I12: =SUM(C12:H12) -> 1
B13: Medellín | C13: =+C5/$I$5 -> 0.14345973 | D13: =+D5/$I$5 -> 0.33812302 | E13: =+E5/$I$5 -> 0.28148938 | F13: =+F5/$I$5 -> 0.11177902 | G13: =+G5/$I$5 -> 0.081844827 | H13: =+H5/$I$5 -> 0.043304024 | I13: =SUM(C13:H13) -> 1
B14: Cali | C14: =+C6/$I$6 -> 0.17984227 | D14: =+D6/$I$6 -> 0.25211822 | E14: =+E6/$I$6 -> 0.29268263 | F14: =+F6/$I$6 -> 0.14734525 | G14: =+G6/$I$6 -> 0.092957633 | H14: =+H6/$I$6 -> 0.03505399 | I14: =SUM(C14:H14) -> 1
B15: B/manga | C15: =+C7/$I$7 -> 0.19542286 | D15: =+D7/$I$7 -> 0.17070733 | E15: =+E7/$I$7 -> 0.23538698 | F15: =+F7/$I$7 -> 0.31554075 | G15: =+G7/$I$7 -> 0.030763711 | H15: =+H7/$I$7 -> 0.05217837 | I15: =SUM(C15:H15) -> 1
B16: C/gena | C16: =+C8/$I$8 -> 0.38624516 | D16: =+D8/$I$8 -> 0.27539245 | E16: =+E8/$I$8 -> 0.18821999 | F16: =+F8/$I$8 -> 0.066662068 | G16: =+G8/$I$8 -> 0.039700293 | H16: =+H8/$I$8 -> 0.043780036 | I16: =SUM(C16:H16) -> 1
B17: Otras Ciudades Principales | C17: =+C9/$I$9 -> 0.32528471 | D17: =+D9/$I$9 -> 0.31742448 | E17: =+E9/$I$9 -> 0.21708691 | F17: =+F9/$I$9 -> 0.086306244 | G17: =+G9/$I$9 -> 0.034254406 | H17: =+H9/$I$9 -> 0.019643251 | I17: =SUM(C17:H17) -> 1
B20: Muestra Técnica de Recolección #1
B21: Ciudades | C21: =COUNTIF(A23:A29,"VERDADERO") -> 0 | D21: =SUM(D23:D29) -> 30.946187 | E21: =SUM(E23:E29) -> 136.05273 | F21: =SUM(F23:F29) -> 142.28695 | G21: =SUM(G23:G29) -> 57.320198 | H21: =SUM(H23:H29) -> 18.726261 | I21: =SUM(I23:I29) -> 14.667678 | J21: Muestra total
B22: Muestra | C22: =SUM(C23:C29) -> 400 | D22: NSE 1 | E22: NSE 2 | F22: NSE 3 | G22: NSE 4 | H22: NSE 5 | I22: NSE 6 | J22: =SUM(J23:J29) -> 400 | K22: Volver al Home
B23: Bogota | C23: =SUM(D23:I23) -> 400 | D23: =+$J$23*C11 -> 30.946187 | E23: =+$J$23*D11 -> 136.05273 | F23: =+$J$23*E11 -> 142.28695 | G23: =+$J$23*F11 -> 57.320198 | H23: =+$J$23*G11 -> 18.726261 | I23: =+$J$23*H11 -> 14.667678 | J23: 400
B24: B/quilla | C24: =SUM(D24:I24) -> 0 | D24: =+$J$24*C12 -> 0 | E24: =+$J$24*D12 -> 0 | F24: =+$J$24*E12 -> 0 | G24: =+$J$24*F12 -> 0 | H24: =+$J$24*G12 -> 0 | I24: =+$J$24*H12 -> 0
B25: M/llin | C25: =SUM(D25:I25) -> 0 | D25: =+$J$25*C13 -> 0 | E25: =+$J$25*D13 -> 0 | F25: =+$J$25*E13 -> 0 | G25: =+$J$25*F13 -> 0 | H25: =+$J$25*G13 -> 0 | I25: =+$J$25*H13 -> 0
B26: Cali | C26: =SUM(D26:I26) -> 0 | D26: =+$J$26*C14 -> 0 | E26: =+$J$26*D14 -> 0 | F26: =+$J$26*E14 -> 0 | G26: =+$J$26*F14 -> 0 | H26: =+$J$26*G14 -> 0 | I26: =+$J$26*H14 -> 0
B27: B/manga | C27: =SUM(D27:I27) -> 0 | D27: =+$J$27*C15 -> 0 | E27: =+$J$27*D15 -> 0 | F27: =+$J$27*E15 -> 0 | G27: =+$J$27*F15 -> 0 | H27: =+$J$27*G15 -> 0 | I27: =+$J$27*H15 -> 0
B28: C/gena | C28: =SUM(D28:I28) -> 0 | D28: =+$J$28*C16 -> 0 | E28: =+$J$28*D16 -> 0 | F28: =+$J$28*E16 -> 0 | G28: =+$J$28*F16 -> 0 | H28: =+$J$28*G16 -> 0 | I28: =+$J$28*H16 -> 0
B29: Otras Ciudades | C29: =SUM(D29:I29) -> 0 | D29: =+$J$29*C17 -> 0 | E29: =+$J$29*D17 -> 0 | F29: =+$J$29*E17 -> 0 | G29: =+$J$29*F17 -> 0 | H29: =+$J$29*G17 -> 0 | I29: =+$J$29*H17 -> 0 | K29: No Ciudades para otras ciudades | L29: 2
K30: No Encuestadores para otras ciudades | L30: 6
B33: Productividad | C33: 4 | F33: 4 | J33: 5 | N33: 5
B34: No Dias | C34: 3 | F34: 3 | J34: 2 | N34: 2
B35: Principal | C35: Muestra | D35: Encuestadores | E35: Costos | F35: Ciudad 1 | G35: Muestra | H35: Encuestadores | I35: Costos | J35: Ciudad 2 | K35: Muestra | L35: Encuestadores | M35: Costos | N35: Ciudad 3 | O35: Muestra | P35: Encuestadores | Q35: Costos
B36: Cúcuta | C36: 100 | D36: 10 | E36: =+((E70*D36)+(F70*D36*C34)) -> 550000 | F36: Valledupar | G36: 50 | H36: 8 | I36: =+((H36*E84)+(F84*H36*F34)) -> 1240000 | J36: Girardot | K36: 150 | O36: Armenia | P36: 50
B37: Cartagena de Indias | C37: 100 | D37: 5 | E37: =+(+E80*D37)+(D37*C34*F80) -> 835000 | F37: Montería | G37: 50 | H37: 6 | I37: =+((H37*F34)*(E71+F71)) -> 1602000 | J37: Neiva | K37: 50 | O37: Pereira | P37: 100
B38: Tunja | C38: 100 | D38: 5 | E38: =+((D38*E81)+(F81*D38*C34)) -> 1510000 | F38: Cajicá | G38: 50 | H38: 3 | I38: =16000*3*H38*2 -> 288000 | J38: Santa Marta | K38: 50 | O38: Ibagué | P38: 100
B39: Manizales | C39: 100 | D39: 8 | E39: =+((D39*E82)+(F82*D39*C34)) -> 1160000 | F39: Chía | G39: 50 | H39: 3 | I39: =28000*3*H39*2 -> 504000 | J39: Villavicencio | K39: 50
B40: Popayán | C40: 50 | D40: 5 | E40: =+((D40*E83)+(F83*D40*C34)) -> 685000 | F40: Mosquera | G40: 50 | I40: =+I38+I39 -> 792000 | J40: Pasto | K40: 50
B41: Total | C41: =SUM(C36:C40) -> 450 | D41: =SUM(D36:D40) -> 33 | E41: =SUM(E36:E40) -> 4740000 | G41: =SUM(G36:G40) -> 250 | H41: =SUM(H36:H40) -> 20 | I41: =SUM(I36:I40) -> 4426000 | K41: =SUM(K36:K40) -> 350 | L41: =SUM(L36:L40) -> 0 | M41: =SUM(M36:M40) -> 0 | O41: =SUM(O36:O40) -> 0 | P41: =SUM(P36:P40) -> 250 | Q41: =SUM(Q36:Q40) -> 0 | R41: =+O41+K41+G41+C41 -> 1050
L42: =+L36*J33*J34 -> 0 | P42: =+P36*N33*N34 -> 500
O43: Total Transp | Q43: =+Q41+M41+I41+E41 -> 9166000
K47: 60800 | L47: 42000
K48: Hotel | L48: Alimentación
K49: =+$K$47*D36*$C$34 -> 1824000 | L49: =+$L$47*$C$34*D36 -> 1260000
K50: =+$K$47*D37*$C$34 -> 912000 | L50: =+$L$47*$C$34*D37 -> 630000
K51: =+$K$47*D38*$C$34 -> 912000 | L51: =+$L$47*$C$34*D38 -> 630000
K52: =+$K$47*D39*$C$34 -> 1459200 | L52: =+$L$47*$C$34*D39 -> 1008000
K53: =+$K$47*D40*$C$34 -> 912000 | L53: =+$L$47*$C$34*D40 -> 630000
K54: =+K47*H36*F34 -> 1459200 | L54: =+L47*F34*H36 -> 1008000
K57: =SUM(K49:K56) -> 7478400 | L57: =SUM(L49:L56) -> 5166000 | M57: Total Hotel + Alim | N57: =+K57+L57 -> 12644400
M58: Total Viáticos | N58: =+N57+Q43 -> 21810400
A61: Departamento | B61: Ciudad | C61: Pasaje Ida y regreso | D61: Teminales | E61: Total | F61: En ciudad | G61: Rural
A62: Amazonas | B62: Leticia | C62: 250000 | D62: 26000 | E62: =SUM(C62:D62) -> 276000 | F62: 13000 | G62: 40000
A63: Antioquia | B63: Sabaneta | C63: 20000 | D63: 8000 | E63: =+C63+D63 -> 28000 | F63: 8000 | G63: 40000
A64: Antioquia | B64: Abejorral | C64: 80000 | D64: 26000 | E64: =SUM(C64:D64) -> 106000 | F64: 13000 | G64: 40000
A65: Antioquia | B65: Bello | C65: 8000 | D65: 8000 | E65: =SUM(C65:D65) -> 16000 | F65: 13000 | G65: 40000
A66: Antioquia | B66: Rionegro | C66: 30000 | D66: 8000 | E66: =SUM(C66:D66) -> 38000 | F66: 13000 | G66: 40000
A67: Antioquia | B67: Salgar | C67: 80000 | D67: 26000 | E67: =SUM(C67:D67) -> 106000 | F67: 13000 | G67: 40000
A68: Antioquia | B68: Envigado | C68: 8000 | D68: 8000 | E68: =SUM(C68:D68) -> 16000 | F68: 13000 | G68: 40000
A69: Antioquia | B69: Itagüí | C69: 8000 | D69: 26000 | E69: =SUM(C69:D69) -> 34000 | F69: 13000 | G69: 40000
A70: Antioquia | B70: Girardota | C70: 8000 | D70: 8000 | E70: =SUM(C70:D70) -> 16000 | F70: 13000 | G70: 40000
A71: Antioquia | B71: Barbosa | C71: 50000 | D71: 26000 | E71: =SUM(C71:D71) -> 76000 | F71: 13000 | G71: 40000
A72: Antioquia | B72: Anorí | C72: 100000 | D72: 26000 | E72: =SUM(C72:D72) -> 126000 | F72: 13000 | G72: 40000
A73: Antioquia | B73: Amalfi | C73: 90000 | D73: 26000 | E73: =SUM(C73:D73) -> 116000 | F73: 13000 | G73: 40000
A74: Antioquia | B74: Cocorná | C74: 80000 | D74: 26000 | E74: =SUM(C74:D74) -> 106000 | F74: 13000 | G74: 40000
A75: Arauca | B75: Arauca | C75: 230000 | D75: 26000 | E75: =SUM(C75:D75) -> 256000 | F75: 13000 | G75: 40000
A76: Arauca | B76: Tame | C76: 230000 | D76: 26000 | E76: =SUM(C76:D76) -> 256000 | F76: 13000 | G76: 40000
A77: Atlantico | B77: Malambo | C77: 24000 | D77: 8000 | E77: =+C77+D77 -> 32000 | F77: 13000 | G77: 40000
A78: Atlántico | B78: Soledad | C78: 34000 | D78: 8000 | E78: =SUM(C78:D78) -> 42000 | F78: 13000 | G78: 40000
A79: Atlántico | B79: Sabanalarga | C79: 40000 | D79: 8000 | E79: =SUM(C79:D79) -> 48000 | F79: 13000 | G79: 40000
A80: Bolívar | B80: Cartagena de Indias | C80: 102000 | D80: 26000 | E80: =SUM(C80:D80) -> 128000 | F80: 13000 | G80: 40000
A81: Bolívar | B81: Arjona | C81: =212000+25000 -> 237000 | D81: 26000 | E81: =SUM(C81:D81) -> 263000 | F81: 13000 | G81: 40000
A82: Bolívar | B82: El Carmen de Bolívar | C82: 80000 | D82: 26000 | E82: =SUM(C82:D82) -> 106000 | F82: 13000 | G82: 40000
A83: Boyacá | B83: Tunja | C83: =36000*2 -> 72000 | D83: 26000 | E83: =SUM(C83:D83) -> 98000 | F83: 13000 | G83: 40000
A84: Boyacá | B84: Duitama | C84: =45000*2 -> 90000 | D84: 26000 | E84: =SUM(C84:D84) -> 116000 | F84: 13000 | G84: 40000
A85: Boyacá | B85: Sogamoso | C85: =45000*2 -> 90000 | D85: 26000 | E85: =SUM(C85:D85) -> 116000 | F85: 13000 | G85: 40000
A86: Boyacá | B86: Tunja | C86: 98000 | D86: 26000 | E86: =SUM(C86:D86) -> 124000 | F86: 13000 | G86: 40000
A87: Boyacá | B87: Duitama | C87: 116000 | D87: 26000 | E87: =SUM(C87:D87) -> 142000 | F87: 13000 | G87: 40000
A88: Caldas | B88: Manizales | C88: 166000 | D88: 26000 | E88: =SUM(C88:D88) -> 192000 | F88: 13000 | G88: 40000
A89: Caldas | B89: Chinchiná | C89: 160000 | D89: 26000 | E89: =SUM(C89:D89) -> 186000 | F89: 13000 | G89: 40000
A90: Caldas | B90: Pácora | C90: 140000 | D90: 26000 | E90: =SUM(C90:D90) -> 166000 | F90: 13000 | G90: 40000
A91: Caldas | B91: Riosucio | C91: 140000 | D91: 26000 | E91: =SUM(C91:D91) -> 166000 | F91: 13000 | G91: 40000
A92: Caquetá | B92: Florencia | C92: 246000 | D92: 26000 | E92: =SUM(C92:D92) -> 272000 | F92: 13000 | G92: 40000
A93: Caquetá | B93: Cartagena del Chairá | C93: =160000*2 -> 320000 | D93: 26000 | E93: =SUM(C93:D93) -> 346000 | F93: 13000 | G93: 40000
A94: Caquetá | B94: Támara | C94: 100000 | D94: 26000 | E94: =SUM(C94:D94) -> 126000 | F94: 13000 | G94: 40000
A95: Casanare | B95: Yopal | C95: 186000 | D95: 26000 | E95: =SUM(C95:D95) -> 212000 | F95: 13000 | G95: 40000
A96: Casanare | B96: Paz de Ariporo | C96: 179000 | D96: 26000 | E96: =SUM(C96:D96) -> 205000 | F96: 13000 | G96: 40000
A97: Cauca | B97: Páez | C97: =81000*2 -> 162000 | D97: 26000 | E97: =SUM(C97:D97) -> 188000 | F97: 13000 | G97: 40000
A98: Cauca | B98: Popayán | C98: 106000 | D98: 26000 | E98: =SUM(C98:D98) -> 132000 | F98: 13000 | G98: 40000
A99: Cauca | B99: Balboa | C99: =166000*2 -> 332000 | D99: 26000 | E99: =SUM(C99:D99) -> 358000 | F99: 13000 | G99: 40000
A100: Cesar | B100: Valledupar | C100: =60000*2 -> 120000 | D100: 26000 | E100: =SUM(C100:D100) -> 146000 | F100: 13000 | G100: 40000
A101: Cesar | B101: Valledupar | C101: 146000 | D101: 26000 | E101: =SUM(C101:D101) -> 172000 | F101: 13000 | G101: 40000
A102: Cesar | B102: Pueblo Bello | C102: =40000+20000 -> 60000 | D102: 26000 | E102: =SUM(C102:D102) -> 86000 | F102: 13000 | G102: 40000
A103: Chocó | B103: Bagadó | C103: 246000 | D103: 26000 | E103: =SUM(C103:D103) -> 272000 | F103: 13000 | G103: 40000
A104: Chocó | B104: Carmen del Darién | C104: 292000 | D104: 26000 | E104: =SUM(C104:D104) -> 318000 | F104: 13000 | G104: 40000
A105: Chocó | B105: Bojayá ( se viaja en avión y Ferri) | C105: 1600000 | D105: 26000 | E105: =SUM(C105:D105) -> 1626000 | F105: 13000 | G105: 40000
A106: Chocó | B106: Istmina | C106: =120000*2 -> 240000 | D106: 26000 | E106: =SUM(C106:D106) -> 266000 | F106: 13000 | G106: 40000
A107: Chocó | B107: Quibdó | C107: 260000 | D107: 26000 | E107: =SUM(C107:D107) -> 286000 | F107: 13000 | G107: 40000
A108: Córdoba | B108: Montería | C108: 164000 | D108: 26000 | E108: =SUM(C108:D108) -> 190000 | F108: 13000 | G108: 40000
A109: Córdoba | B109: San andres de Sotavento | C109: 120000 | D109: 26000 | E109: =SUM(C109:D109) -> 146000 | F109: 13000 | G109: 40000
A110: Córdoba | B110: Lorica | C110: 55000 | D110: 26000 | E110: =SUM(C110:D110) -> 81000 | F110: 13000 | G110: 40000
A111: Córdoba | B111: Tierralta | C111: 180000 | D111: 26000 | E111: =SUM(C111:D111) -> 206000 | F111: 13000 | G111: 40000
A112: Cundinamarca | B112: Barandillas | C112: =10200*2 -> 20400 | D112: 16001 | E112: =+C112+D112 -> 36401 | F112: 13000 | G112: 400000
A113: Cundinamarca | B113: Briceño | C113: =7500*2 -> 15000 | D113: 16006 | E113: =+C113+D113 -> 31006 | F113: 13000 | G113: 400000
...

Sheet MuestraTec2
C2: NSE 1 | D2: NSE 2 | E2: NSE 3 | F2: NSE 4 | G2: NSE 5 | H2: NSE 6 | I2: Total
B3: Bogotá | C3: 175822 | D3: 772989 | E3: 808409 | F3: 325667 | G3: 106394 | H3: 83335 | I3: =SUM(C3:H3) -> 2272616
B4: Barranquilla | C4: 120736 | D4: 72430 | E4: 82028 | F4: 48172 | G4: 17448 | H4: 13225 | I4: =SUM(C4:H4) -> 354039
B5: Medellín | C5: 135532 | D5: 319438 | E5: 265934 | F5: 105602 | G5: 77322 | H5: 40911 | I5: =SUM(C5:H5) -> 944739
B6: Cali | C6: 120201 | D6: 168508 | E6: 195620 | F6: 98481 | G6: 62130 | H6: 23429 | I6: =SUM(C6:H6) -> 668369
B7: B/manga | C7: 38127 | D7: 33305 | E7: 45924 | F7: 61562 | G7: 6002 | H7: 10180 | I7: =SUM(C7:H7) -> 195100
B8: C/gena | C8: 117585 | D8: 83838 | E8: 57300 | F8: 20294 | G8: 12086 | H8: 13328 | I8: =SUM(C8:H8) -> 304431
B9: Otras Ciudades | C9: 755665 | D9: 737405 | E9: 504312 | F9: 200497 | G9: 79576 | H9: 45633 | I9: =SUM(C9:H9) -> 2323088
B11: Bogotá | C11: =+C3/$I$3 -> 0.077365468 | D11: =+D3/$I$3 -> 0.34013181 | E11: =+E3/$I$3 -> 0.35571738 | F11: =+F3/$I$3 -> 0.1433005 | G11: =+G3/$I$3 -> 0.046815652 | H11: =+H3/$I$3 -> 0.036669195 | I11: =SUM(C11:H11) -> 1 | K11: Por favor consultar con estadistica Incorporación de ciudades o más regiones fuera de las 6 principales para un aterrizaje más detallado de costos
B12: Barranquilla | C12: =+C4/$I$4 -> 0.34102458 | D12: =+D4/$I$4 -> 0.20458198 | E12: =+E4/$I$4 -> 0.23169199 | F12: =+F4/$I$4 -> 0.13606411 | G12: =+G4/$I$4 -> 0.049282706 | H12: =+H4/$I$4 -> 0.037354642 | I12: =SUM(C12:H12) -> 1
B13: Medellín | C13: =+C5/$I$5 -> 0.14345973 | D13: =+D5/$I$5 -> 0.33812302 | E13: =+E5/$I$5 -> 0.28148938 | F13: =+F5/$I$5 -> 0.11177902 | G13: =+G5/$I$5 -> 0.081844827 | H13: =+H5/$I$5 -> 0.043304024 | I13: =SUM(C13:H13) -> 1
B14: Cali | C14: =+C6/$I$6 -> 0.17984227 | D14: =+D6/$I$6 -> 0.25211822 | E14: =+E6/$I$6 -> 0.29268263 | F14: =+F6/$I$6 -> 0.14734525 | G14: =+G6/$I$6 -> 0.092957633 | H14: =+H6/$I$6 -> 0.03505399 | I14: =SUM(C14:H14) -> 1
B15: B/manga | C15: =+C7/$I$7 -> 0.19542286 | D15: =+D7/$I$7 -> 0.17070733 | E15: =+E7/$I$7 -> 0.23538698 | F15: =+F7/$I$7 -> 0.31554075 | G15: =+G7/$I$7 -> 0.030763711 | H15: =+H7/$I$7 -> 0.05217837 | I15: =SUM(C15:H15) -> 1
B16: C/gena | C16: =+C8/$I$8 -> 0.38624516 | D16: =+D8/$I$8 -> 0.27539245 | E16: =+E8/$I$8 -> 0.18821999 | F16: =+F8/$I$8 -> 0.066662068 | G16: =+G8/$I$8 -> 0.039700293 | H16: =+H8/$I$8 -> 0.043780036 | I16: =SUM(C16:H16) -> 1
B17: Otras Ciudades Principales | C17: =+C9/$I$9 -> 0.32528471 | D17: =+D9/$I$9 -> 0.31742448 | E17: =+E9/$I$9 -> 0.21708691 | F17: =+F9/$I$9 -> 0.086306244 | G17: =+G9/$I$9 -> 0.034254406 | H17: =+H9/$I$9 -> 0.019643251 | I17: =SUM(C17:H17) -> 1
B20: Muestra Técnica de Recolección #2
B21: Ciudades | C21: =COUNTIF(A23:A29,"VERDADERO") -> 0 | D21: =SUM(D23:D29) -> 0 | E21: =SUM(E23:E29) -> 0 | F21: =SUM(F23:F29) -> 0 | G21: =SUM(G23:G29) -> 0 | H21: =SUM(H23:H29) -> 0 | I21: =SUM(I23:I29) -> 0 | J21: Muestra total
B22: Muestra | C22: =SUM(C23:C29) -> 0 | D22: NSE 1 | E22: NSE 2 | F22: NSE 3 | G22: NSE 4 | H22: NSE 5 | I22: NSE 6 | J22: =SUM(J23:J29) -> 0 | K22: Volver al Home
B23: Bogota | C23: =SUM(D23:I23) -> 0 | D23: =+$J$23*C11 -> 0 | E23: =+$J$23*D11 -> 0 | F23: =+$J$23*E11 -> 0 | G23: =+$J$23*F11 -> 0 | H23: =+$J$23*G11 -> 0 | I23: =+$J$23*H11 -> 0
B24: B/quilla | C24: =SUM(D24:I24) -> 0 | D24: =+$J$24*C12 -> 0 | E24: =+$J$24*D12 -> 0 | F24: =+$J$24*E12 -> 0 | G24: =+$J$24*F12 -> 0 | H24: =+$J$24*G12 -> 0 | I24: =+$J$24*H12 -> 0
B25: M/llin | C25: =SUM(D25:I25) -> 0 | D25: =+$J$25*C13 -> 0 | E25: =+$J$25*D13 -> 0 | F25: =+$J$25*E13 -> 0 | G25: =+$J$25*F13 -> 0 | H25: =+$J$25*G13 -> 0 | I25: =+$J$25*H13 -> 0
B26: Cali | C26: =SUM(D26:I26) -> 0 | D26: =+$J$26*C14 -> 0 | E26: =+$J$26*D14 -> 0 | F26: =+$J$26*E14 -> 0 | G26: =+$J$26*F14 -> 0 | H26: =+$J$26*G14 -> 0 | I26: =+$J$26*H14 -> 0
B27: B/manga | C27: =SUM(D27:I27) -> 0 | D27: =+$J$27*C15 -> 0 | E27: =+$J$27*D15 -> 0 | F27: =+$J$27*E15 -> 0 | G27: =+$J$27*F15 -> 0 | H27: =+$J$27*G15 -> 0 | I27: =+$J$27*H15 -> 0
B28: C/gena | C28: =SUM(D28:I28) -> 0 | D28: =+$J$28*C16 -> 0 | E28: =+$J$28*D16 -> 0 | F28: =+$J$28*E16 -> 0 | G28: =+$J$28*F16 -> 0 | H28: =+$J$28*G16 -> 0 | I28: =+$J$28*H16 -> 0
B29: Otras Ciudades | C29: =SUM(D29:I29) -> 0 | D29: =+$J$29*C17 -> 0 | E29: =+$J$29*D17 -> 0 | F29: =+$J$29*E17 -> 0 | G29: =+$J$29*F17 -> 0 | H29: =+$J$29*G17 -> 0 | I29: =+$J$29*H17 -> 0 | K29: No Ciudades para otras ciudades
K30: No Encuestadores para otras ciudades | L30: =+D41+H41+L41+P41 -> 0
B33: Productividad | C33: 5 | F33: 5 | J33: 5 | N33: 5
B34: No Dias | C34: 4 | F34: 2 | J34: 2 | N34: 2
B35: Principal | C35: Muestra | D35: Encuestadores | E35: Costos | F35: Ciudad 1 | G35: Muestra | H35: Encuestadores | I35: Costos | J35: Ciudad 2 | K35: Muestra | L35: Encuestadores | M35: Costos | N35: Ciudad 3 | O35: Muestra | P35: Encuestadores | Q35: Costos
B41: Total | C41: =SUM(C36:C40) -> 0 | D41: =SUM(D36:D40) -> 0 | E41: =SUM(E36:E40) -> 0 | G41: =SUM(G36:G40) -> 0 | H41: =SUM(H36:H40) -> 0 | I41: =SUM(I36:I40) -> 0 | K41: =SUM(K36:K40) -> 0 | L41: =SUM(L36:L40) -> 0 | M41: =SUM(M36:M40) -> 0 | O41: =SUM(O36:O40) -> 0 | P41: =SUM(P36:P40) -> 0 | Q41: =SUM(Q36:Q40) -> 0 | R41: =+O41+K41+G41+C41 -> 0
D42: =+D36*C33*C34 -> 0 | H42: =+H36*F33*F34 -> 0 | L42: =+L36*J33*J34 -> 0 | P42: =+P36*N33*N34 -> 0
O43: Total Transp | Q43: =+Q41+M41+I41+E41 -> 0
K46: 52000 | L46: 40000
K47: Hotel | L47: Alimentación
J54: Total | K54: =SUM(K48:K53) -> 0 | L54: =SUM(L48:L53) -> 0 | M54: Total Hotel + Alim | N54: =+K54+L54 -> 0
M55: Total Viáticos | N55: =+N54+Q43 -> 0
B58: Ciudad | C58: Pasaje Ida y regreso | D58: Teminales | E58: Total | F58: En ciudad
B59: CARTAGENA | C59: =38000*2 -> 76000 | D59: 26000 | E59: =SUM(C59:D59) -> 102000 | F59: 13000
B60: VALLEDUPAR | C60: =60000*2 -> 120000 | D60: 26000 | E60: =SUM(C60:D60) -> 146000 | F60: 13000
B61: SANTA MARTA | C61: =38000*2 -> 76000 | D61: 26000 | E61: =SUM(C61:D61) -> 102000 | F61: 13000
B62: MONTERIA | C62: =69000*2 -> 138000 | D62: 26000 | E62: =SUM(C62:D62) -> 164000 | F62: 13000
B63: SOLEDAD | C63: 26000 | D63: 8000 | E63: =SUM(C63:D63) -> 34000 | F63: 13000
B64: CHÍA | C64: =5000*2 -> 10000 | D64: 8000 | E64: =SUM(C64:D64) -> 18000 | F64: 8000
B65: ITAGUI | C65: =4000*2 -> 8000 | D65: 8000 | E65: =SUM(C65:D65) -> 16000 | F65: 8000
B66: ENVIGADO | C66: =4000*2 -> 8000 | D66: 8000 | E66: =SUM(C66:D66) -> 16000 | F66: 13000
B67: POPAYAN | C67: =40000*2 -> 80000 | D67: 26000 | E67: =SUM(C67:D67) -> 106000 | F67: 13000
B68: PALMIRA | C68: 20000 | D68: 8000 | E68: =SUM(C68:D68) -> 28000 | F68: 13000
B69: JAMUNDI | C69: =20000*2 -> 40000 | D69: 13000 | E69: =SUM(C69:D69) -> 53000 | F69: 12000
B70: BUGA | C70: =30000*2 -> 60000 | D70: 13000 | E70: =SUM(C70:D70) -> 73000 | F70: 13000
B71: FLORIDABLANCA | C71: 8000 | D71: 8000 | E71: =SUM(C71:D71) -> 16000 | F71: 8000
B72: GIRÓN | C72: 8000 | D72: 8000 | E72: =SUM(C72:D72) -> 16000 | F72: 8000
B73: PEREIRA | C73: 80000 | D73: 26000 | E73: =SUM(C73:D73) -> 106000 | F73: 13000
B74: VILLAVICENCIO | C74: 80000 | D74: 30000 | E74: =SUM(C74:D74) -> 110000 | F74: 13000
B75: FACATATIVÁ | C75: 26000 | D75: 16000 | E75: =SUM(C75:D75) -> 42000 | F75: 13000
B76: TUNJA | C76: =36000*2 -> 72000 | D76: 26000 | E76: =SUM(C76:D76) -> 98000 | F76: 13000
B77: DUITAMA | C77: =45000*2 -> 90000 | D77: 26000 | E77: =SUM(C77:D77) -> 116000 | F77: 13000
B78: SOGAMOSO | C78: =45000*2 -> 90000 | D78: 26000 | E78: =SUM(C78:D78) -> 116000 | F78: 13000
B79: NEIA | C79: =49000*2 -> 98000 | D79: 26000 | E79: =SUM(C79:D79) -> 124000 | F79: 13000
B80: PASTO | C80: =70000*2 -> 140000 | D80: 26000 | E80: =SUM(C80:D80) -> 166000 | F80: 13000
B81: IBAGUE | C81: =39000*2 -> 78000 | D81: 26000 | E81: =SUM(C81:D81) -> 104000 | F81: 13000
B82: NEIVA | C82: =50000*2 -> 100000 | D82: 26000 | E82: =SUM(C82:D82) -> 126000 | F82: 13000

Sheet MYSTERY
A2: =MAX(A3,A4,A5) -> 1 | B2: Tipo de Visita | C2: Complejidad | F2: No. Olas | G2: =+Entradas!D72 -> 1 | H2: No. Olas | I2: =+Entradas!E72 -> 1 | J2: No. Olas | K2: =+Entradas!F72 -> 1 | L2: No. Olas | M2: =+G2+I2+K2 -> 3
A3: =VLOOKUP(C3,Parametros!$B$125:$E$135,4,0) -> 1 | B3: TIPO VISITA 1 | C3: =+Entradas!G16 -> Básica - Video | D3: =+IF(C3="Ninguna",0,1) -> 1
A4: =VLOOKUP(C4,Parametros!$B$125:$E$135,4,0) -> 0 | B4: TIPO VISITA 2 | C4: =+Entradas!J16 -> Ninguna | D4: =+IF(C4="Ninguna",0,1) -> 0
A5: =VLOOKUP(C5,Parametros!$B$125:$E$135,4,0) -> 0 | B5: TIPO VISITA 3 | C5: =+Entradas!M16 -> Ninguna | D5: =+IF(C5="Ninguna",0,1) -> 0 | E5: =+F7+H8+J9 -> 0 | F5: TIPO DE VISITA 1 - SEGMENTO 1 | H5: TIPO DE VISITA 2 - SEGMENTO 2 | J5: TIPO DE VISITA 3 - SEGMENTO 3 | L5: TOTAL ESTUDIO X OLA
A6: Costeo Mystery Shopper | C6: Descripción Costo | D6: Cod. Matrix | E6: Vr. Unitario | F6: CANTIDAD | G6: TOTAL | H6: CANTIDAD | I6: TOTAL | J6: CANTIDAD | K6: TOTAL | L6: CANTIDAD | M6: TOTAL | N6: OBSERVACIONES
A7: Costo Directo | B7: Mystery Shopper | C7: TIPO VISITA 1 | D7: 5418 | E7: =VLOOKUP($C$3,Parametros!$B$109:$D$122,3,0) -> 55000 | F7: =+Entradas!H16 -> 0 | G7: =+F7*$E7*D3 -> 0 | I7: =+H7*$E7 -> 0 | L7: =+F7*$G$2 -> 0 | M7: =+G7*G2 -> 0
A8: Costo Directo | B8: Mystery Shopper | C8: TIPO VISITA 2 | D8: 5418 | E8: =VLOOKUP($C$4,Parametros!$B$109:$D$122,3,0) -> 0 | H8: =+Entradas!K16 -> 0 | I8: =+H8*$E8*D4 -> 0 | L8: =+H8*$I$2 -> 0 | M8: =+I8*I2 -> 0
A9: Costo Directo | B9: Mystery Shopper | C9: TIPO VISITA 3 | D9: 5418 | E9: =VLOOKUP($C$5,Parametros!$B$109:$D$122,3,0) -> 0 | J9: =+Entradas!N16 -> 0 | K9: =+J9*E9*D5 -> 0 | L9: =+J9*$K$2 -> 0 | M9: =+K9*K2 -> 0
A10: Costo Directo | B10: Operación | C10: Coord Campo - Capacitaciones / entrega (PMO) | D10: 5420 | E10: =63211*9.53%+63211 -> 69235.008 | F10: =VLOOKUP($A$3,Parametros!$A$125:$D$135,3,0)*2 -> 4 | G10: =+F10*$E10*D3 -> 276940.03 | H10: =VLOOKUP($A$4,Parametros!$A$125:$D$135,3,0)*2 -> 0 | I10: =+H10*$E10*D4 -> 0 | J10: =VLOOKUP($A$5,Parametros!$A$125:$D$135,3,0)*2 -> 0 | K10: =+J10*$E10*D5 -> 0 | L10: =+(F10*$G$2)+(H10*$I$2)+(J10*$K$2) -> 4 | M10: =+(G10*$G$2)+(I10*$I$2)+(K10*$K$2) -> 276940.03
A11: Costo Directo | B11: Operación | C11: Asist. Campo - capacitaciones / entrega (Coord campo) | D11: 5420 | E11: =63211*9.53%+63211 -> 69235.008 | F11: =+Entradas!D79 -> 4 | G11: =+F11*$E11*D3 -> 276940.03 | H11: =+Entradas!E79 -> 0 | I11: =+H11*$E11*D4 -> 0 | J11: =+Entradas!F79 -> 0 | K11: =+J11*$E11*D5 -> 0 | L11: =+(F11*$G$2)+(H11*$I$2)+(J11*$K$2) -> 4 | M11: =+(G11*$G$2)+(I11*$I$2)+(K11*$K$2) -> 276940.03
A12: Costo Directo | B12: Operación | C12: Coord Campo (PMO) | D12: 5420 | E12: =63211*9.53%+63211 -> 69235.008 | F12: =+Entradas!D80 -> 36 | G12: =+F12*$E12*D3 -> 2492460.3 | H12: =+Entradas!E80 -> 0 | I12: =+H12*$E12*D4 -> 0 | J12: =+Entradas!F80 -> 0 | K12: =+J12*$E12*D5 -> 0 | L12: =+(F12*$G$2)+(H12*$I$2)+(J12*$K$2) -> 36 | M12: =+(G12*$G$2)+(I12*$I$2)+(K12*$K$2) -> 2492460.3
A13: Costo Directo | B13: Operación | C13: Asist. Campo (Coord. Campo) | D13: 5420 | E13: =63211*9.53%+63211 -> 69235.008 | F13: =+Entradas!D81 -> 36 | G13: =+F13*$E13*D3 -> 2492460.3 | H13: =+Entradas!E81 -> 0 | I13: =+H13*$E13*D4 -> 0 | J13: =+Entradas!F81 -> 0 | K13: =+J13*$E13*D5 -> 0 | L13: =+(F13*$G$2)+(H13*$I$2)+(J13*$K$2) -> 36 | M13: =+(G13*$G$2)+(I13*$I$2)+(K13*$K$2) -> 2492460.3
A14: Costo Directo | B14: Operación | C14: Apoyo otra asistencia - Unificación videos | D14: 200 | E14: =63211*9.53%+63211 -> 69235.008 | F14: =VLOOKUP(IF($F$7<=50,50,IF($F$7<=100,100,IF($F$7<=200,200,IF($F$7<=300,300,300)))),Parametros!$H$124:$M$128,2,0) -> 10 | G14: =+F14*$E14*D3 -> 692350.08 | H14: =VLOOKUP(IF($H$8<=50,50,IF($H$8<=100,100,IF($H$8<=200,200,IF($H$8<=300,300,300)))),Parametros!$H$124:$M$128,2,0) -> 10 | I14: =+H14*$E14*D4 -> 0 | J14: =VLOOKUP(IF($J$9<=50,50,IF($J$9<=100,100,IF($J$9<=200,200,IF($J$9<=300,300,300)))),Parametros!$H$124:$M$128,2,0) -> 10 | K14: =+J14*$E14*D5 -> 0 | L14: =+(F14*$G$2)+(H14*$I$2)+(J14*$K$2) -> 30 | M14: =+(G14*$G$2)+(I14*$I$2)+(K14*$K$2) -> 692350.08
A15: Costo Directo | B15: Operación | C15: Apoyo otra asistencia - RMC | D15: 200 | E15: =63211*9.53%+63211 -> 69235.008 | F15: =VLOOKUP(IF($F$7<=50,50,IF($F$7<=100,100,IF($F$7<=200,200,IF($F$7<=300,300,300)))),Parametros!$H$124:$M$128,2,0) -> 10 | G15: =+F15*$E15*D3 -> 692350.08 | H15: =VLOOKUP(IF($H$8<=50,50,IF($H$8<=100,100,IF($H$8<=200,200,IF($H$8<=300,300,300)))),Parametros!$H$124:$M$128,2,0) -> 10 | I15: =+H15*$E15*D4 -> 0 | J15: =VLOOKUP(IF($J$9<=50,50,IF($J$9<=100,100,IF($J$9<=200,200,IF($J$9<=300,300,300)))),Parametros!$H$124:$M$128,2,0) -> 10 | K15: =+J15*$E15*D5 -> 0 | L15: =+(F15*$G$2)+(H15*$I$2)+(J15*$K$2) -> 30 | M15: =+(G15*$G$2)+(I15*$I$2)+(K15*$K$2) -> 692350.08
A16: Costo Directo | C16: Seguimiento Mysterys | F16: =SUM(F7:F9) -> 0 | G16: =SUM(G7:G15) -> 6923500.8 | H16: =SUM(H7:H9) -> 0 | I16: =SUM(I7:I15) -> 0 | J16: =SUM(J7:J9) -> 0 | K16: =SUM(K7:K15) -> 0 | L16: =SUM(L7:L9) -> 0 | M16: =SUM(M7:M15) -> 6923500.8
A17: Costo Directo | B17: CRITICA-Revisión encuestas | C17: TIPO VISITA 1 | D17: 5504 | E17: =102183*9.53%+102183 -> 111921.04 | F17: =(F7/12)*1.1 -> 0 | G17: =+F17*$E17*D3 -> 0 | L17: =+(F17*$G$2)+(H17*$I$2)+(J17*$K$2) -> 0 | M17: =+(G17*$G$2)+(I17*$I$2)+(K17*$K$2) -> 0
A18: Costo Directo | B18: CRITICA-Revisión encuestas | C18: TIPO VISITA 2 | D18: 5504 | E18: =102183*9.53%+102183 -> 111921.04 | H18: =(H8/12)*1.1 -> 0 | I18: =+H18*$E18*D4 -> 0 | L18: =+(F18*$G$2)+(H18*$I$2)+(J18*$K$2) -> 0 | M18: =+(G18*$G$2)+(I18*$I$2)+(K18*$K$2) -> 0
A19: Costo Directo | B19: CRITICA-Revisión encuestas | C19: TIPO VISITA 3 | D19: 5504 | E19: =102183*9.53%+102183 -> 111921.04 | J19: =(J9/12)*1.1 -> 0 | K19: =+J19*$E19*D5 -> 0 | L19: =+(F19*$G$2)+(H19*$I$2)+(J19*$K$2) -> 0 | M19: =+(G19*$G$2)+(I19*$I$2)+(K19*$K$2) -> 0
A20: Costo Directo | B20: CRITICA-Revisión encuestas | C20: Capacitación y entrega | D20: 5504 | E20: =102183*9.53%+102183 -> 111921.04 | F20: =+((2*1)+(4*2))/9 -> 1.1111111 | G20: =+F20*$E20*D3 -> 124356.71 | H20: =+((2*1)+(4*2))/9 -> 1.1111111 | I20: =+H20*$E20*D4 -> 0 | J20: =+((2*1)+(4*2))/9 -> 1.1111111 | K20: =+J20*$E20*D5 -> 0 | L20: =+(F20*$G$2)+(H20*$I$2)+(J20*$K$2) -> 3.3333333 | M20: =+(G20*$G$2)+(I20*$I$2)+(K20*$K$2) -> 124356.71 | N20: El valor para otras olas será del 50% del costo de la ola 1
A21: Costo Directo | B21: CRITICA-Revisión encuestas | C21: Solución a descargos | D21: 5504 | E21: =102183*9.53%+102183 -> 111921.04 | F21: =VLOOKUP(IF($F$7<=50,50,IF($F$7<=100,100,IF($F$7<=200,200,IF($F$7<=300,300,300)))),Parametros!$H$124:$M$128,4,0) -> 1 | G21: =+F21*$E21*D3 -> 111921.04 | H21: =VLOOKUP(IF($H$8<=50,50,IF($H$8<=100,100,IF($H$8<=200,200,IF($H$8<=300,300,300)))),Parametros!$H$124:$M$128,4,0) -> 1 | I21: =+H21*$E21*D4 -> 0 | J21: =VLOOKUP(IF($J$9<=50,50,IF($J$9<=100,100,IF($J$9<=200,200,IF($J$9<=300,300,300)))),Parametros!$H$124:$M$128,4,0) -> 1 | K21: =+J21*$E21*D5 -> 0 | L21: =+(F21*$G$2)+(H21*$I$2)+(J21*$K$2) -> 3 | M21: =+(G21*$G$2)+(I21*$I$2)+(K21*$K$2) -> 111921.04
A22: Costo Directo | C22: Critica | D22: =+D17 -> 5504 | G22: =SUM(G17:G21) -> 236277.75 | I22: =SUM(I17:I21) -> 0 | K22: =SUM(K17:K21) -> 0 | M22: =SUM(M17:M21) -> 236277.75
A23: Costo Directo | B23: Desplazamientos (viaticos) | C23: Desplazamientos (viaticos) | D23: 9997 | E23: 1 | F23: =+Entradas!D73 -> 0 | G23: =+F23*$E23*D3 -> 0 | H23: =+Entradas!E73 -> 0 | I23: =+H23*$E23*D4 -> 0 | J23: =+Entradas!F73 -> 0 | K23: =+J23*$E23*D5 -> 0 | L23: =+(F23*$G$2)+(H23*$I$2)+(J23*$K$2) -> 0 | M23: =+(G23*$G$2)+(I23*$I$2)+(K23*$K$2) -> 0
A24: Costo Directo | B24: Otro tipo de desplazamiento - Tanqueos - consumos | C24: XXXX | D24: 9997 | E24: 1 | F24: =+Entradas!D74 -> 0 | G24: =+F24*$E24*D3 -> 0 | H24: =+Entradas!E74 -> 0 | I24: =+H24*$E24*D4 -> 0 | J24: =+Entradas!F74 -> 0 | K24: =+J24*$E24*D5 -> 0 | L24: =+E24 -> 1 | M24: =+(G24*$G$2)+(I24*$I$2)+(K24*$K$2) -> 0
A25: Costo Directo | C25: Desplazamientos | G25: =SUM(G23:G24) -> 0 | I25: =SUM(I23:I24) -> 0 | K25: =SUM(K23:K24) -> 0 | M25: =SUM(M23:M24) -> 0
A26: Costo Directo | B26: Costo Telefonico Obtención citas | D26: 6305 | E26: =VLOOKUP(IF($F$7<=50,50,IF($F$7<=100,100,IF($F$7<=200,200,IF($F$7<=300,300,300)))),Parametros!$H$124:$M$128,5,0) -> 30000 | F26: 1 | G26: =+F26*$E26*D3 -> 30000 | H26: =+H8 -> 0 | I26: =+H26*$E26*D4 -> 0 | J26: =+J9 -> 0 | K26: =+J26*$E26*D5 -> 0 | L26: =+(F26*$G$2)+(H26*$I$2)+(J26*$K$2) -> 1 | M26: =+(G26*$G$2)+(I26*$I$2)+(K26*$K$2) -> 30000
A27: Costo Directo | B27: Fotocopias | C27: Alertas tempranas - Fotocopia a color | D27: 9997 | E27: =1100*5.2%+1100 -> 1157.2 | F27: =+Entradas!D75 -> 0 | G27: =+SUM(F27:F27)*E27*D3 -> 0 | H27: =+Entradas!E75 -> 1 | I27: =+SUM(H27:H27)*G27*D4 -> 0 | J27: =+Entradas!F75 -> 0 | K27: =+SUM(J27:J27)*I27*D5 -> 0 | L27: =+(F27*$G$2)+(H27*$I$2)+(J27*$K$2) -> 1 | M27: =+(G27*$G$2)+(I27*$I$2)+(K27*$K$2) -> 0
B28: SUBTOTAL COSTOS DIRECTOS | G28: =+G16+G22+G25+G26+G27 -> 7189778.6 | I28: =+I16+I22+I25+I26+I27 -> 0 | K28: =+K16+K22+K25+K26+K27 -> 0 | M28: =+M16+M22+M25+M26+M27 -> 7189778.6
A29: Costo Directo | B29: Edición videos - Apoyo Logístico | D29: 8005 | E29: =+Parametros!C139 -> 23144 | F29: =+Entradas!D76 -> 0 | G29: =+F29*$E29*D3 -> 0 | H29: =+Entradas!E75 -> 1 | I29: =+H29*$E29*D4 -> 0 | J29: =+Entradas!F76 -> 0 | K29: =+J29*$E29*D5 -> 0 | L29: =+(F29*$G$2)+(H29*$I$2)+(J29*$K$2) -> 1 | M29: =+(G29*$G$2)+(I29*$I$2)+(K29*$K$2) -> 0
A30: Costo Directo | B30: Edición videos - Apoyo Logístico Extra | D30: 8005 | E30: =+Parametros!C140 -> 18936 | F30: =+F29*15% -> 0 | G30: =+F30*$E30*D3 -> 0 | H30: =+H29*15% -> 0.15 | I30: =+H30*$E30*D4 -> 0 | J30: =+J29*15% -> 0 | K30: =+J30*$E30*D5 -> 0 | L30: =+(F30*$G$2)+(H30*$I$2)+(J30*$K$2) -> 0.15 | M30: =+(G30*$G$2)+(I30*$I$2)+(K30*$K$2) -> 0
A31: Costo Directo | B31: Alquiler equipos y otros - Tablets - Plan de datos - Vr. Mensual (Act. Subcontratada) | C31: Solicitud recargas alertas tempranas | D31: 454 | E31: 1 | F31: =+Entradas!D77 -> 0 | G31: =+F31*E31*D3 -> 0 | H31: =+Entradas!E77 -> 0 | I31: =+H31*E31*D4 -> 0 | J31: =+Entradas!F77 -> 0 | K31: =+J31*E31*D5 -> 0 | L31: =+E31 -> 1 | M31: =+(G31*$G$2)+(I31*$I$2)+(K31*$K$2) -> 0
A32: Costo Directo | B32: Otros | C32: Botas de seguridad, implementos adicionales para la opreación | D32: 9997 | E32: 1 | F32: =+Entradas!D86 -> 0 | G32: =+F32 -> 0 | H32: =+Entradas!E86 -> 0 | I32: =+H32 -> 0 | J32: =+Entradas!F86 -> 0 | K32: =+J32 -> 0 | L32: 1 | M32: =+(G32*$G$2)+(I32*$I$2)+(K32*$K$2) -> 0
A33: Costo Directo | B33: Valor de reclutamiento VISITA TIPO 1 | D33: 9997 | E33: =VLOOKUP(C3,Parametros!$B$124:$G$135,6,0) -> 25000 | F33: =+F7 -> 0 | G33: =+F33*E33*D3 -> 0 | L33: =+(F33*$G$2)+(H33*$I$2)+(J33*$K$2) -> 0 | M33: =+(G33*$G$2)+(I33*$I$2)+(K33*$K$2) -> 0
A34: Costo Directo | B34: Valor de reclutamiento VISITA TIPO 2 | D34: 9997 | E34: =VLOOKUP(C4,Parametros!$B$124:$G$135,6,0) -> 0 | H34: =+H8 -> 0 | I34: =+H34*E34*D4 -> 0 | L34: =+(F34*$G$2)+(H34*$I$2)+(J34*$K$2) -> 0 | M34: =+(G34*$G$2)+(I34*$I$2)+(K34*$K$2) -> 0
A35: Costo Directo | B35: Valor de reclutamiento VISITA TIPO 3 | D35: 9997 | E35: =VLOOKUP(C5,Parametros!$B$124:$G$135,6,0) -> 0 | J35: =+J9 -> 0 | K35: =+J35*E35*D5 -> 0 | L35: =+(F35*$G$2)+(H35*$I$2)+(J35*$K$2) -> 0 | M35: =+(G35*$G$2)+(I35*$I$2)+(K35*$K$2) -> 0
A36: Tecnología | B36: Procesamiento otro pais - Shopmetrics | D36: 898 | E36: =(0.83*3700)*1.25 -> 3838.75 | F36: =+F16 -> 0 | G36: =+F36*$E36*D3 -> 0 | H36: =+H16 -> 0 | I36: =+H36*$E36*D4 -> 0 | J36: =+J16 -> 0 | K36: =+J36*$E36*D5 -> 0 | L36: =+F36+(H36*$I$2) -> 0 | M36: =+(G36*$G$2)+(I36*$I$2)+(K36*$K$2) -> 0
B37: SUBTOTAL SUBCONTRATADAS INTERNAS | G37: =+SUM(G29:G36) -> 0 | I37: =+SUM(I29:I36) -> 0 | K37: =+SUM(K29:K36) -> 0 | M37: =+SUM(M29:M36) -> 0
A39: TOTAL COSTO DIRECTO | G39: =+G28+G37 -> 7189778.6 | I39: =+I28+I37 -> 0 | K39: =+K28+K37 -> 0 | M39: =+M28+M37 -> 7189778.6
A42: Costo Directo | B42: Vimeo | C42: Plan vimeo | D42: 654 | E42: 0 | F42: 1 | G42: =+F42*$E42*D3 -> 0 | H42: 1 | I42: =+H42*$E42*D4 -> 0 | J42: 1 | K42: =+J42*$E42*D5 -> 0 | L42: =+F42+(H42*$I$2) -> 2 | M42: =+(G42*$G$2)+(I42*$I$2)+(K42*$K$2) -> 0
A43: Costo Directo | B43: Bonos | C43: Bonos a reclutado visita 1 | D43: 500 | E43: =VLOOKUP(C3,Parametros!$B$124:$G$135,5,0) -> 35000 | F43: =+F7 -> 0 | G43: =+F43*$E43*D3 -> 0 | L43: =+F43+(H43*$I$2) -> 0 | M43: =+(G43*$G$2)+(I43*$I$2)+(K43*$K$2) -> 0
A44: Costo Directo | B44: Bonos | C44: Bonos a reclutado visita 2 | D44: 500 | E44: =VLOOKUP(C4,Parametros!$B$124:$G$135,5,0) -> 0 | H44: =+H8 -> 0 | I44: =+H44*$E44*D4 -> 0 | L44: =+F44+(H44*$I$2) -> 0 | M44: =+(G44*$G$2)+(I44*$I$2)+(K44*$K$2) -> 0
A45: Costo Directo | B45: Bonos | C45: Bonos a reclutado visita 3 | D45: 500 | E45: =VLOOKUP(C5,Parametros!$B$124:$G$135,5,0) -> 0 | J45: =+J9 -> 0 | K45: =+J45*$E45*D5 -> 0 | L45: =+F45+(H45*$I$2) -> 0 | M45: =+(G45*$G$2)+(I45*$I$2)+(K45*$K$2) -> 0
A46: Costo Directo | B46: Bonos | C46: Comisión | D46: 500 | E46: 0.1 | G46: =+SUM(G43:G45)*$E$46 -> 0 | I46: =+SUM(I43:I45)*10% -> 0 | K46: =+SUM(K43:K45)*10% -> 0 | L46: =+F46+(H46*$I$2) -> 0 | M46: =+(G46*$G$2)+(I46*$I$2)+(K46*$K$2) -> 0
A47: Costo Directo | B47: Bonos | C47: Otras compras | D47: 500 | E47: 1 | F47: 0 | G47: =+F47*$E47*D3 -> 0 | I47: =+H47*$E47*D4 -> 0 | K47: =+J47*$E47*D5 -> 0 | M47: =+(G47*$G$2)+(I47*$I$2)+(K47*$K$2) -> 0
A48: Costo Directo | B48: Bonos | C48: Compra de dispositivos de grabación | D48: 500 | E48: 0 | F48: =VLOOKUP(IF($F$7<=50,50,IF($F$7<=100,100,IF($F$7<=200,200,IF($F$7<=300,300,300)))),Parametros!$H$124:$M$128,6,0) -> 300000 | G48: =+F48*$E$48*D3 -> 0 | H48: =VLOOKUP(IF($H$8<=50,50,IF($H$8<=100,100,IF($H$8<=200,200,IF($H$8<=F6256,300,300)))),Parametros!$H$124:$M$128,6,0) -> 300000 | I48: =+H48*$E$48*D4 -> 0 | J48: =VLOOKUP(IF($J$9<=50,50,IF($J$9<=100,100,IF($J$9<=200,200,IF($J$9<=300,300,300)))),Parametros!$H$124:$M$128,6,0) -> 300000 | K48: =+J48*$E$48*D5 -> 0 | L48: =+F48+(H48*$I$2) -> 600000 | M48: =+(G48*$G$2)+(I48*$I$2)+(K48*$K$2) -> 0
A49: SUBCONTRATADAS EXTERNAS | G49: =+SUM(G42:G48) -> 0 | I49: =+SUM(I42:I48) -> 0 | K49: =+SUM(K42:K48) -> 0 | M49: =+SUM(M42:M48) -> 0

Sheet Costos Directos discriminados
B3: Nombre Propuesta | C3: =+Entradas!D4 -> 0
B4: Grupo Objetivo | C4: =+Entradas!D5 -> 0
B5: Cliente | C5: =+Entradas!D6 -> 0
B6: Fecha de aprobación estimada | C6: =+Entradas!D7 -> 0
B7: Fecha de campo | C7: =+Entradas!D8 -> 0 | D7: =+Entradas!E8 -> 0
B8: Probabilidad de aprobación | C8: =+Entradas!D9 -> Alta
B9: SL | C9: =+Entradas!D10 -> MSU
B10: Metodología SL | C10: =+Entradas!D11 -> MSC005 - U&A | D10: =+VLOOKUP(C10,Parametros!B306:C336,2,0) -> 0
B11: Record Detail | C11: =+Entradas!D12 -> Ops
B12: Producto | C12: =+Entradas!D13 -> Otro | D12: =+Entradas!E13 -> 0
B13: Metodología de Recolección | C13: =+Entradas!D16 -> Hogares | D13: =+Entradas!E16 -> 0
B14: Técnica de Recolección 1 | C14: =+Entradas!D17 -> F2F | D14: =+Entradas!E17 -> 1 | E14: =IF(D14=2,2,1) -> 1 | F14: =+MuestraTec1!C22 -> 400
B15: Técnica de Recolección 2 | C15: =+Entradas!D18 -> NINGUNA | D15: =+Entradas!E18 -> 0 | F15: =+MuestraTec2!C22 -> 0
B16: Bases de Datos | C16: =+Entradas!D19 -> No requiere | D16: =+Entradas!E19 -> 0
B17: Penetración | D17: =+Entradas!E20 -> Mas 82%
B18: Duracion | D18: =+Entradas!E21 -> 16-20minutos
B19: # Preguntas abiertas | D19: =+Entradas!E22 -> 0
B20: # Preguntas abiertas Multiples | D20: =+Entradas!E23 -> 0
B21: Otros | D21: =+Entradas!E24 -> 0
B22: Top line | C22: =+Entradas!D25 -> No | D22: {=VLOOKUP(C22,+Parametros!$B$218:$C$220,2,0)} -> 0
B23: Datacleaning | C23: =VLOOKUP(C22,Parametros!$B$222:$C$223,2,FALSE) -> Total | D23: =VLOOKUP(C23,Parametros!$B$203:$C$205,2,0) -> 1
B24: Conversión/generación archivos ASCII y otros | C24: =+Entradas!D27 -> No | D24: {=VLOOKUP(C24,+Parametros!$B$218:$C$220,2,0)} -> 0
B25: Requiere Script para reclutamiento | C25: =+Entradas!D28 -> No | D25: {=VLOOKUP(C25,+Parametros!$B$218:$C$220,2,0)} -> 0
B26: Scripting | C26: =+Entradas!D29 -> Si | D26: {=VLOOKUP(C26,+Parametros!$B$218:$C$220,2,0)} -> 1 | E26: =+Entradas!F29 -> Nuevo | F26: =VLOOKUP(E26,Parametros!$B$180:$C$182,2,0) -> 1
B27: Codificación | C27: =+Entradas!D30 -> No | D27: {=VLOOKUP(C27,+Parametros!$B$218:$C$220,2,0)} -> 0
B28: Procesamiento | C28: =+Entradas!D31 -> Si | D28: =+Entradas!E31 -> 1
B29: # Procesamientos | D29: =+Entradas!E32 -> 1
B30: Requiere proceso Estadistico | C30: =+Entradas!D33 -> No | D30: {=VLOOKUP(C30,+Parametros!$B$218:$C$220,2,0)} -> 0
B31: =+Entradas!C34 -> Valor GMU (Brasil, francia, EEUU, etc.)
B32: =+Entradas!C37 -> Harmoni | C32: =+Entradas!D37 -> No | D32: =+Entradas!E37 -> 0
B33: =+Entradas!C38 -> Graficación | C33: =+Entradas!D38 -> No | D33: =+Entradas!E38 -> 0
B34: =+Entradas!C39 -> Otros costos | C34: =+Entradas!D39 -> 0 | D34: =+Entradas!E39 -> 0
B35: # Pag. Reprografia | D35: =+Entradas!E42 -> 0
B36: Número de Olas/rondas | C36: =+Entradas!D43 -> 1
B37: Envío a ciudades | C37: =+Entradas!D44 -> No | D37: =VLOOKUP(C37,Parametros!B219:C220,2,0) -> 0
B38: Ciudades | C38: =+Entradas!D47 -> 1
B39: El estudio contempla niños | C39: =+Entradas!D58 -> No
B40: Taxi a participantes | C40: =+Entradas!D59 -> No
B41: Clase de Prueba | C41: =+Entradas!D60 -> Monádica sequencial | D41: =+Entradas!E60 -> 2 | E41: =IF(D41>1,1,2) -> 1
B42: Requiere refrigeración anticipada | C42: =+Entradas!D61 -> No | D42: =VLOOKUP(C42,Parametros!B219:C220,2,0) -> 0
B43: Valor de la compra del producto en caso de requerirlo | C43: =+Entradas!D62 -> 0
B44: Si requiere traslado del producto indique el Peso en gramos | C44: =+Entradas!D45 -> 0
B45: Etiquetado o Empaque(Dosificarlo),blind, o prueba a ciegas | C45: =+Entradas!D63 -> Blind, o prueba a ciegas | D45: =VLOOKUP(C45,Parametros!B226:D229,3,0) -> 1
B46: Emabalaje | C46: =+Entradas!D64 -> No
B47: # Producto a testear | D47: =+Entradas!E65 -> 2
B48: # Product por respondiente | D48: =+Entradas!E66 -> 2
B49: # Patinadores por ciudad | C49: 2 | D49: =+C38*C49 -> 2
B50: Siembra y recolección | C50: =+Entradas!D68 -> No | D50: =+Entradas!E68 -> 0 | E50: =IF(D50,2,1) -> 1
B51: Apoyo Reclutamiento en sitio | C51: =+Entradas!D69 -> Ninguno | D51: =VLOOKUP($C$51,Parametros!$B$214:$C$217,2,0) -> 0
B52: Muestra | C52: =+Entradas!D48 -> 400
B53: Sobre Muestra | C53: =+Entradas!D46 -> 0 | D53: =+C52*C53 -> 0
B54: Muestra | C54: =+C52+D53 -> 400
B55: Productividad | C55: 6
B56: Días de Set up | C56: 4
B57: #Días de campo | C57: =+ROUNDUP(C58,0) -> 15
B58: #Días | C58: =+'Valores Insumos reclutamiento'!I15 -> 14.392857
B59: # Horas DP | C59: 18
B60: # de Encuestadores | C60: =+'Valores Insumos reclutamiento'!I13 -> 7
B61: # de Supervisores | C61: =+'Valores Insumos reclutamiento'!I16 -> 1.75
B62: Incidencia | D62: =+Entradas!E20 -> Mas 82%
B63: Valor por encuesta a encuestador sin parafiscales | C63: =VLOOKUP(D18,Parametros!$B$3:$AI$12,HLOOKUP(D62,Parametros!B1:AI2,2,0),0) -> 12227.396 | D63: =+C63 -> 12227.396
B64: Parafiscales | C64: 0.16522 | D64: =+D63*C64 -> 2020.2104
B65: Tasa Cambiaria | C65: Junio | D65: 4111.28
B67: Valor encuestas | D67: =(IF(D14=1,(IFERROR((D63+D64)*C54,0)*E50),IF(D15=1,(IFERROR((D63+D64)*C54,0)*E50),0))) -> 5699042.5 | E67: =+D67/$C$52 -> 14247.606 | G67: =+D67-F67 -> 5699042.5 | H67: =+G67/F67 -> #DIV/0!
B68: Valor encuestas CATI | D68: =(IF(D14=2,(+VLOOKUP(D18,Parametros!$B$80:$AI$88,HLOOKUP(D62,Parametros!B1:AI2,2,0),0)*F14),IF(D15=2,(+VLOOKUP(D18,Parametros!$B$80:$AI$88,HLOOKUP(D62,Parametros!B1:AI2,2,0),0)*F14),0))) -> 0 | E68: =+D68/$C$52 -> 0 | G68: =+D68-F68 -> 0 | H68: =+G68/F68 -> #DIV/0!
B69: Valor Campo Internacional | D69: =IF(D14=7,+Entradas!D15,0) -> 0 | E69: =+D69/$C$52 -> 0 | G69: =+D69-F69 -> 0 | H69: =+G69/F69 -> #DIV/0!
B70: Valor Campo EXTERNO | D70: =IF(D14=6,+Entradas!D14,0) -> 0 | E70: =+D70/$C$52 -> 0 | G70: =+D70-F70 -> 0 | H70: =+G70/F70 -> #DIV/0!
B71: Valor encuestas Auto aplicado/Online | D71: =(IF(D14=10,(+VLOOKUP(D18,Parametros!$B$96:$AI$104,HLOOKUP(D62,Parametros!B94:AI95,2,0),0)*F14),IF(D15=3,(+VLOOKUP(D18,Parametros!$B$96:$AI$104,HLOOKUP(D62,Parametros!B94:AI95,2,0),0)*F14),0))) -> 0 | E71: =+D71/$C$52 -> 0 | G71: =+D71-F71 -> 0 | H71: =+G71/F71 -> #DIV/0!
B72: Valor encuestas Auto aplicado INNO | C72: =81000*9.53%+81000 -> 88719.3 | D72: =+C72*Entradas!H15*Entradas!G15*6 -> 0 | E72: =+D72/$C$52 -> 0 | G72: =+D72-F72 -> 0 | H72: =+G72/F72 -> #DIV/0!
B73: Valor encuestas Mystery | D73: =(IF(D14=5,(IFERROR(MYSTERY!M39,0)),0)) -> 0 | E73: =+D73/$C$52 -> 0 | G73: =+D73-F73 -> 0 | H73: =+G73/F73 -> #DIV/0!
B74: Valor encuesta Shopper por día | C74: =81000*9.53%+81000 -> 88719.3 | D74: =(IF(D14=8,(IFERROR((C74)*((C56+C57+C58)*(C60+C61)),0)),0)) -> 0 | E74: =+D74/$C$52 -> 0 | G74: =+D74-F74 -> 0 | H74: =+G74/F74 -> #DIV/0!
B75: Valor encuesta Shopper por productividad | D75: =IF(D14=9,+MYSTERY!M39,0) -> 0 | E75: =+D75/$C$52 -> 0 | G75: =+D75-F75 -> 0 | H75: =+G75/F75 -> #DIV/0!
B76: Reclutamiento | D76: =IFERROR('Valores Insumos reclutamiento'!$F$59,0) -> 0 | E76: =+D76/C54 -> 0 | G76: =+D76-F76 -> 0 | H76: =+G76/F76 -> #DIV/0!
B77: Insumos Productos para Pruebas | C77: =+'Valores Insumos reclutamiento'!G52*1.02 -> 0 | D77: =IF(D14<5,(IFERROR($C$77*$C$54*$D$10,0)),0) -> 0 | G77: =+D77-F77 -> 0 | H77: =+G77/F77 -> #DIV/0!
B78: Rotulación, marcación, tapar marca | C78: =3484*5.2%+3484 -> 3665.168 | D78: =IFERROR(($C$78*$C$54)*'Valores Insumos reclutamiento'!$C$2*$D$10,0)*D45 -> 0 | E78: =+D78+D77 -> 0 | G78: =+D78-F78 -> 0 | H78: =+G78/F78 -> #DIV/0!
B79: Transporte Enc. | C79: =3750*5.2%+3750 -> 3945 | D79: =IF(D14=1,(IFERROR(($C$79*$C$57*($C$60*$C$38)),0)*$E$50),0) -> 414225 | G79: =+D79-F79 -> 414225 | H79: =+G79/F79 -> #DIV/0!
B80: Transporte Superv. | C80: =7500*5.2%+7500 -> 7890 | D80: =IF(D14=1,(IFERROR(($C$80*C57)*(C61*C38),0)*E50),0) -> 207112.5 | G80: =+D80-F80 -> 207112.5 | H80: =+G80/F80 -> #DIV/0!
B81: Envios | C81: =+'Valores Insumos reclutamiento'!F106 -> 14728 | D81: =IFERROR('Valores Insumos reclutamiento'!$F$107*$D$10*D37,0) -> 0 | G81: =+D81-F81 -> 0 | H81: =+G81/F81 -> #DIV/0!
B82: Transporte Niños | C82: =15000*5.2%+15000 -> 15780 | D82: =IFERROR(($C$82*C54)*(Entradas!$A$58),0) -> 0 | G82: =+D82-F82 -> 0 | H82: =+G82/F82 -> #DIV/0!
B83: Transporte Bebidas Alcoholicas | C83: =28000*5.2%+28000 -> 29456 | D83: =IF(Entradas!$E$59=1,($C$83*$C$54),0) -> 0 | G83: =+D83-F83 -> 0 | H83: =+G83/F83 -> #DIV/0!
B84: Tpe Locaciones | C84: =90000*5.2%+90000 -> 94680 | D84: =IF(D14<5,(IFERROR(($C$84*2*$C$38)*$D$13,0)),0) -> 0 | G84: =+D84-F84 -> 0 | H84: =+G84/F84 -> #DIV/0! | J84: =+D93+D95+D97 -> 1553261.9 | K84: =+J84/(1-30%) -> 2218945.6
B85: Apoyo Compras | C85: =81000*9.53%+81000 -> 88719.3 | D85: =IF(D14<5,(IFERROR(($C$85*$C$38)*$D$10,0)),0) -> 0 | G85: =+D85-F85 -> 0 | H85: =+G85/F85 -> #DIV/0! | K85: 5547363.9
B86: Apoyo Reclutador en sitio | C86: =81000*9.53%+81000 -> 88719.3 | D86: =IFERROR((($C$86*$C$57)*$C$38/$D$51)*$D$10,0) -> 0 | G86: =+D86-F86 -> 0 | H86: =+G86/F86 -> #DIV/0!
B87: Apoyo Pasantes 2xCiudad | C87: =81000*9.53%+81000 -> 88719.3 | D87: =IF(D14<5,(IFERROR((($C$87*($C$57*$D$49)))*$D$10,0)*$D$13),0) -> 0 | G87: =+D87-F87 -> 0 | H87: =+G87/F87 -> #DIV/0! | K87: 6656836.7
B88: Apoyo Puerta OPS Bta | C88: =81000*9.53%+81000 -> 88719.3 | D88: =IF(D14<5,(IFERROR((($C$88*('Valores Insumos reclutamiento'!$B$12>0))*$C$57)*$D$10,0)*$D$13),0) -> 0 | G88: =+D88-F88 -> 0 | H88: =+G88/F88 -> #DIV/0!
B89: Reprografía | C89: =1100*5.2%+1100 -> 1157.2 | D89: =IF(D14=1,(IFERROR($C$89*$D$35*$C$60*$C$38,0)),0) -> 0 | G89: =+D89-F89 -> 0 | H89: =+G89/F89 -> #DIV/0!
B90: Supervisión de campo personal | C90: =102037*9.53%+102037 -> 111761.13 | D90: =IF(D14<5,(IFERROR(((($C$90*$C$64)+$C$90)*($C$61))*(($C$57+1)),0)),0) -> 3646336.4 | E90: =+D90+D91 -> 5736147.8 | G90: =+D90-F90 -> 3646336.4 | H90: =+G90/F90 -> #DIV/0!
B91: Coordinación Campo | C91: =134681*9.53%+134681 -> 147516.1 | D91: =IF(D14<5,(IFERROR(($C$91)*((($C$57+C56)/1.5)+(3/2)),0)),0) -> 2089811.4 | G91: =+D91-F91 -> 2089811.4 | H91: =+G91/F91 -> #DIV/0!
B92: Entrenamiento | C92: =28403*9.53%+28403 -> 31109.806 | D92: =IF(D14<5,(IFERROR($C$92*($C$60+('Valores Insumos reclutamiento'!H13/MuestraTec1!L29)+$C$61)*$C$38,0)),0) -> 365540.22 | G92: =+D92-F92 -> 365540.22 | H92: =+G92/F92 -> #DIV/0!
B93: Verificación | C93: =28727*9.53%+28727 -> 31464.683 | D93: =IF(D14<5,(IFERROR($C$93*($C$54/12),0)),0) -> 1048822.8 | E93: =+D93/(1-21.45%) -> 1335229.5 | G93: =+D93-F93 -> 1048822.8 | H93: =+G93/F93 -> #DIV/0!
B94: Codificacion | C94: =25660*9.53%+25660 -> 28105.398 | D94: =IFERROR(($C$94*Codificación!$V$22)*$D$27,0) -> 0 | E94: =+D94/(1-21.45%) -> 0 | G94: =+D94-F94 -> 0 | H94: =+G94/F94 -> #DIV/0!
B95: Verificacion-Campo Costo telefónico | C95: =137*5.2%+137 -> 144.124 | D95: =IF(D14<5,(+$C$95*(($C$54*35%)*5)),0) -> 100886.8 | E95: =+D95/(1-21.45%) -> 128436.41 | G95: =+D95-F95 -> 100886.8 | H95: =+G95/F95 -> #DIV/0!
B96: Costo telefónico para Siembra | C96: 215 | D96: =IF(D50=1,(C96*4*150)+(C85*(C57+3)*2),0) -> 0
B97: Crítica Encuestas | C97: =27633*9.53%+27633 -> 30266.425 | D97: =IF(D14<5,(+$C$97*($C$54/30)),0) -> 403552.33 | E97: =+D97/(1-21.45%) -> 513752.17 | G97: =+D97-F97 -> 403552.33 | H97: =+G97/F97 -> #DIV/0!
B98: Alojamiento en Ifield (0,19) | C98: =0.19*5.2%+0.19 -> 0.19988 | D98: =+($C$98*$D$65)*$C$54 -> 328705.06 | E98: =+E97+E95+E93 -> 1977418.1 | G98: =+D98-F98 -> 328705.06 | H98: =+G98/F98 -> #DIV/0!
B99: Otros Costos | D99: =+$C$34 -> 0 | G99: =+D99-F99 -> 0 | H99: =+G99/F99 -> #DIV/0!
B100: Viaticos | D100: =+Entradas!D40 -> 0
B101: Locacion btá | C101: =650000*5.2%+650000 -> 683800 | D101: =IF(D14<5,(((+'Valores Insumos reclutamiento'!$E$67))*$D$13+E101),0) -> 0 | G101: =+D101-F101 -> 0 | H101: =+G101/F101 -> #DIV/0!
B102: Locacion Mdellín | C102: =841000*5.2%+841000 -> 884732 | D102: =IF(D14<5,((+'Valores Insumos reclutamiento'!$E$68)*$D$13+E102),0) -> 0 | E102: =+'Valores Insumos reclutamiento'!G68 -> 0 | G102: =+D102-F102 -> 0 | H102: =+G102/F102 -> #DIV/0!
B103: Locación Barranquilla | C103: =860000*5.2%+860000 -> 904720 | D103: =IF(D14<5,((+'Valores Insumos reclutamiento'!$E$69)*$D$13+E103),0) -> 0 | G103: =+D103-F103 -> 0 | H103: =+G103/F103 -> #DIV/0!
...

Sheet Valores Insumos reclutamiento
B1: Duración | C1: =+Entradas!E21 -> 16-20minutos | D1: # Ciudades | E1: =+Entradas!D47 -> 1 | F1: Incidencia | G1: =+Entradas!E20 -> Mas 82%
B2: # de Productos | C2: =+Entradas!E66 -> 2
B4: CIUDAD
B5: Bogota | C5: B/quilla | D5: M/llin | E5: Cali | F5: B/manga | G5: C/gena | H5: Otras Ciudades | I5: Total
A6: NSE 6 | B6: =+ROUNDUP(+Entradas!$J$49/(1-'Costos Directos discriminados'!C53),0) -> 15 | C6: =+ROUNDUP(+Entradas!$J$50/(1-'Costos Directos discriminados'!C53),0) -> 0 | D6: =+ROUNDUP(+Entradas!$J$51/(1-'Costos Directos discriminados'!C53),0) -> 0 | E6: =+ROUNDUP(+Entradas!$J$52/(1-'Costos Directos discriminados'!C53),0) -> 0 | F6: =+ROUNDUP(+Entradas!$J$53/(1-'Costos Directos discriminados'!C53),0) -> 0 | G6: =+ROUNDUP(+Entradas!$J$54/(1-'Costos Directos discriminados'!C53),0) -> 0 | H6: =+ROUNDUP(+Entradas!$J$55/(1-'Costos Directos discriminados'!C53),0) -> 0 | I6: =SUM(B6:H6) -> 15
A7: NSE 5 | B7: =+ROUNDUP(+Entradas!$I$49/(1-'Costos Directos discriminados'!C53),0) -> 19 | C7: =+ROUNDUP(+Entradas!$I$50/(1-'Costos Directos discriminados'!C53),0) -> 0 | D7: =+ROUNDUP(+Entradas!$I$51/(1-'Costos Directos discriminados'!C53),0) -> 0 | E7: =+ROUNDUP(+Entradas!$I$52/(1-'Costos Directos discriminados'!C53),0) -> 0 | F7: =+ROUNDUP(+Entradas!$I$53/(1-'Costos Directos discriminados'!C53),0) -> 0 | G7: =+ROUNDUP(+Entradas!$I$54/(1-'Costos Directos discriminados'!C53),0) -> 0 | H7: =+ROUNDUP(+Entradas!$I$55/(1-'Costos Directos discriminados'!C53),0) -> 0 | I7: =SUM(B7:H7) -> 19
A8: NSE 4 | B8: =+ROUNDUP(+Entradas!$H$49/(1-'Costos Directos discriminados'!C53),0) -> 58 | C8: =+ROUNDUP(+Entradas!$H$50/(1-'Costos Directos discriminados'!C53),0) -> 0 | D8: =+ROUNDUP(+Entradas!$H$51/(1-'Costos Directos discriminados'!C53),0) -> 0 | E8: =+ROUNDUP(+Entradas!$H$52/(1-'Costos Directos discriminados'!C53),0) -> 0 | F8: =+ROUNDUP(+Entradas!$H$53/(1-'Costos Directos discriminados'!C53),0) -> 0 | G8: =+ROUNDUP(+Entradas!$H$54/(1-'Costos Directos discriminados'!C53),0) -> 0 | H8: =+ROUNDUP(+Entradas!$H$55/(1-'Costos Directos discriminados'!C53),0) -> 0 | I8: =SUM(B8:H8) -> 58
A9: NSE 3 | B9: =+ROUNDUP(+Entradas!$G$49/(1-'Costos Directos discriminados'!C53),0) -> 143 | C9: =+ROUNDUP(+Entradas!$G$50/(1-'Costos Directos discriminados'!C53),0) -> 0 | D9: =+ROUNDUP(+Entradas!$G$51/(1-'Costos Directos discriminados'!C53),0) -> 0 | E9: =+ROUNDUP(+Entradas!$G$52/(1-'Costos Directos discriminados'!C53),0) -> 0 | F9: =+ROUNDUP(+Entradas!$G$53/(1-'Costos Directos discriminados'!C53),0) -> 0 | G9: =+ROUNDUP(+Entradas!$G$54/(1-'Costos Directos discriminados'!C53),0) -> 0 | H9: =+ROUNDUP(+Entradas!$G$55/(1-'Costos Directos discriminados'!C53),0) -> 0 | I9: =SUM(B9:H9) -> 143
A10: NSE 2 | B10: =+ROUNDUP(+Entradas!$F$49/(1-'Costos Directos discriminados'!C53),0) -> 137 | C10: =+ROUNDUP(+Entradas!$F$50/(1-'Costos Directos discriminados'!C53),0) -> 0 | D10: =+ROUNDUP(+Entradas!$F$51/(1-'Costos Directos discriminados'!C53),0) -> 0 | E10: =+ROUNDUP(+Entradas!$F$52/(1-'Costos Directos discriminados'!C53),0) -> 0 | F10: =+ROUNDUP(+Entradas!$F$53/(1-'Costos Directos discriminados'!C53),0) -> 0 | G10: =+ROUNDUP(+Entradas!$F$54/(1-'Costos Directos discriminados'!C53),0) -> 0 | H10: =+ROUNDUP(+Entradas!$F$55/(1-'Costos Directos discriminados'!C53),0) -> 0 | I10: =SUM(B10:H10) -> 137
A11: NSE 1 | B11: =+ROUNDUP(+Entradas!$E$49/(1-'Costos Directos discriminados'!C53),0) -> 31 | C11: =+ROUNDUP(+Entradas!$E$50/(1-'Costos Directos discriminados'!C53),0) -> 0 | D11: =+ROUNDUP(+Entradas!$E$51/(1-'Costos Directos discriminados'!C53),0) -> 0 | E11: =+ROUNDUP(+Entradas!$E$52/(1-'Costos Directos discriminados'!C53),0) -> 0 | F11: =+ROUNDUP(+Entradas!$E$53/(1-'Costos Directos discriminados'!C53),0) -> 0 | G11: =+ROUNDUP(+Entradas!$E$54/(1-'Costos Directos discriminados'!C53),0) -> 0 | H11: =+ROUNDUP(+Entradas!$E$55/(1-'Costos Directos discriminados'!C53),0) -> 0 | I11: =SUM(B11:H11) -> 31
A12: Total | B12: =SUM(B6:B11) -> 403 | C12: =SUM(C6:C11) -> 0 | D12: =SUM(D6:D11) -> 0 | E12: =SUM(E6:E11) -> 0 | F12: =SUM(F6:F11) -> 0 | G12: =SUM(G6:G11) -> 0 | H12: =SUM(H6:H11) -> 0 | I12: =SUM(B12:H12) -> 403
A13: Enc | B13: 7 | C13: 6 | D13: 7 | E13: 7 | F13: 7 | G13: 7 | H13: =+MuestraTec1!L30 -> 6 | I13: =MAX(B13:G13) -> 7
A14: Prod | B14: 4 | C14: 5 | D14: 5 | E14: 5 | F14: 5 | G14: 5 | H14: 5 | I14: =MAX(B14:H14) -> 5
A15: Dias | B15: =+IFERROR(B12/B13/B14,0) -> 14.392857 | C15: =+IFERROR(C12/C13/C14,0) -> 0 | D15: =+IFERROR(D12/D13/D14,0) -> 0 | E15: =+IFERROR(E12/E13/E14,0) -> 0 | F15: =+IFERROR(F12/F13/F14,0) -> 0 | G15: =+IFERROR(G12/G13/G14,0) -> 0 | H15: =+IFERROR(H12/H13/H14,0) -> 0 | I15: =MAX(B15:H15) -> 14.392857
A16: Sup | B16: =IF(B12>0,B13/4,0) -> 1.75 | C16: =IF(C12>0,C13/4,0) -> 0 | D16: =IF(D12>0,D13/4,0) -> 0 | E16: =IF(E12>0,E13/4,0) -> 0 | F16: =IF(F12>0,F13/4,0) -> 0 | G16: =IF(G12>0,G13/4,0) -> 0 | H16: =IF(H12>0,H13/4,0) -> 0 | I16: =SUM(B16:H16) -> 1.75
A17: Log | B17: =+B13/4 -> 1.75 | C17: =+C13/3 -> 2 | D17: =+D13/3 -> 2.3333333 | E17: =+E13/3 -> 2.3333333 | F17: =+F13/3 -> 2.3333333 | G17: =+G13/3 -> 2.3333333 | H17: =+H13/3 -> 2 | I17: =MAX(B17:H17) -> 2.3333333
B18: =IF(B12>0,1,0) -> 1 | C18: =IF(C12>0,1,0) -> 0 | D18: =IF(D12>0,1,0) -> 0 | E18: =IF(E12>0,1,0) -> 0 | F18: =IF(F12>0,1,0) -> 0 | G18: =IF(G12>0,1,0) -> 0 | H18: =IF(H12>0,1,0) -> 0
B19: Insumos CLT | C19: Precio 2024 | D19: Unid | E19: Cantidad | F19: Valor Total
A20: 690 | B20: agua Prueba | C20: =+A20*5.2%+A20 -> 725.88 | D20: 1 | E20: =+$I$12*C2 -> 806 | F20: =IF('Costos Directos discriminados'!D13=1,E20*C20,0) -> 0
A21: 4300 | B21: platos | C21: =+A21*5.2%+A21 -> 4523.6 | D21: 20 | E21: =(+$I$12*$C$2)/(D21)*4 -> 161.2 | F21: =IF('Costos Directos discriminados'!$D$13=1,E21*C21,0) -> 0
A22: 6200 | B22: galletas soda | C22: =+A22*5.2%+A22 -> 6522.4 | D22: 20 | E22: =(+$I$12*$C$2)/(D22) -> 40.3 | F22: =IF('Costos Directos discriminados'!$D$13=1,E22*C22,0) -> 0
A23: 3500 | B23: vasos Agua | C23: =+A23*5.2%+A23 -> 3682 | D23: 25 | E23: =(+$I$12*$C$2)/(D23) -> 32.24 | F23: =IF('Costos Directos discriminados'!$D$13=1,E23*C23,0) -> 0
A24: 5200 | B24: vasos Murano | C24: =+A24*5.2%+A24 -> 5470.4 | D24: 12 | E24: =(+$I$12*$C$2)/(D24) -> 67.166667 | F24: =IF('Costos Directos discriminados'!$D$12=2,E24*C24,0) -> 0
A25: 5000 | B25: servilletas | C25: =+A25*5.2%+A25 -> 5260 | D25: 200 | E25: =(+$I$12*$C$2)/(D25) -> 4.03 | F25: =IF('Costos Directos discriminados'!D13=1,E25*C25,0) -> 0
A26: 5000 | B26: bolsas basura | C26: =+A26*5.2%+A26 -> 5260 | D26: 6 | E26: =+E1 -> 1 | F26: =IF('Costos Directos discriminados'!D13=1,E26*C26,0) -> 0
A27: 37000 | B27: guantes nitrilo | C27: =+A27*5.2%+A27 -> 38924 | D27: 50 | E27: =ROUNDUP((I15*I13*E1/D27),0) -> 3 | F27: =IF('Costos Directos discriminados'!D13=1,E27*C27,0) -> 0
A28: 27000 | B28: Cofias | C28: =+A28*5.2%+A28 -> 28404 | D28: 100 | E28: =+ROUNDUP(I13*I15*E1/D28,0) -> 2 | F28: =IF('Costos Directos discriminados'!D13=1,E28*C28,0) -> 0
A29: 1600 | B29: delantales desechables | C29: =+A29*5.2%+A29 -> 1683.2 | D29: 1 | E29: =+I13*I15*E1 -> 100.75 | F29: =IF('Costos Directos discriminados'!D13=1,E29*C29,0) -> 0
A30: 14000 | B30: Rollo de papel secante | C30: =+A30*5.2%+A30 -> 14728 | D30: 120 | E30: =(+$I$12/D30)*I15 -> 48.336012 | F30: =IF('Costos Directos discriminados'!D13=1,E30*C30,0) -> 0
A31: 40000 | B31: Gel antibacterial | C31: =+A31*5.2%+A31 -> 42080 | D31: 1 | E31: =+D31*$E$1 -> 1 | F31: =IF('Costos Directos discriminados'!D13=1,E31*C31,0) -> 0
A32: 37000 | B32: Alcohol | C32: =+A32*5.2%+A32 -> 38924 | D32: 1 | E32: =+D32*$E$1 -> 1 | F32: =IF('Costos Directos discriminados'!D13=1,E32*C32,0) -> 0
A33: 8700 | B33: Toalla de Mano | C33: =+A33*5.2%+A33 -> 9152.4 | D33: 150 | E33: =(+$I$12/D33*3) -> 8.06 | F33: =IF('Costos Directos discriminados'!D13=1,E33*C33,0) -> 0
A34: 13000 | B34: Tapabocas | C34: =+A34*5.2%+A34 -> 13676 | D34: 100 | E34: =+$I$12/D34*$E$1 -> 4.03 | F34: =IF('Costos Directos discriminados'!D13=1,E34*C34,0) -> 0
A35: 13000 | B35: Tapabocas Entrevistados | C35: =+A35*5.2%+A35 -> 13676 | D35: 100 | E35: =+$I$12/D35*$E$1 -> 4.03 | F35: =IF('Costos Directos discriminados'!D13=1,E35*C35,0) -> 0
A36: 35000 | B36: Jabon liquido | C36: =+A36*5.2%+A36 -> 36820 | D36: 1 | E36: =+D36*$E$1 -> 1 | F36: =IF('Costos Directos discriminados'!D13=1,E36*C36,0) -> 0
A37: 4090 | B37: Jabo lavaloza | C37: =+A37*5.2%+A37 -> 4302.68 | D37: 1 | E37: =+E1 -> 1 | F37: =IF('Costos Directos discriminados'!D13=1,E37*C37,0) -> 0
A38: 4950 | B38: Esponjas | C38: =+A38*5.2%+A38 -> 5207.4 | D38: 1 | E38: =+E1 -> 1 | F38: =IF('Costos Directos discriminados'!D13=1,E38*C38,0) -> 0
A39: 4700 | B39: Guantes de cocina | C39: =+A39*5.2%+A39 -> 4944.4 | D39: 1 | E39: =+E1 -> 1 | F39: =IF('Costos Directos discriminados'!D13=1,E39*C39,0) -> 0
A40: 1100 | B40: Envase gel | C40: =+A40*5.2%+A40 -> 1157.2 | D40: 1 | E40: =+E1 -> 1 | F40: =IF('Costos Directos discriminados'!D13=1,E40*C40,0) -> 0
A41: 220000 | B41: Envio Prod a Mllin | C41: =+A41*5.2%+A41 -> 231440 | D41: 1 | F41: =IF('Costos Directos discriminados'!D36=1,E41*C41,0) -> 0
A42: 50000 | B42: Envio Prod a BAQ | C42: =+A42*5.2%+A42 -> 52600 | D42: 1 | F42: =IF('Costos Directos discriminados'!D37=1,E42*C42,0) -> 0
A43: 50000 | B43: Envio Prod a Data System | C43: =+A43*5.2%+A43 -> 52600 | D43: 1 | F43: =IF('Costos Directos discriminados'!D38=1,E43*C43,0) -> 0
A44: 970000 | B44: Neveras | C44: =+A44*5.2%+A44 -> 1020440 | D44: 1 | F44: =IF(Entradas!E61=1,(C44*D44),0) -> 0
A45: 430000 | B45: Alquiler de Congelador | C45: =+A45*5.2%+A45 -> 452360 | D45: 1 | F45: =+C45*E45 -> 0
D46: 1 | F46: =+C46*D46*E46 -> 0
D47: 2 | F47: =+C47*D47*E47 -> 0
D48: 1 | F48: =+C48*D48*E48 -> 0
D49: 1 | F49: =+C49*D49*E49 -> 0
D50: 1 | F50: =+C50*D50*E50 -> 0
D51: 1 | F51: =+C51*D51*E51 -> 0
B52: Total | F52: =SUM(F20:F51) -> 0 | G52: =+F52/Entradas!D48 -> 0
C54: =+'Costos Directos discriminados'!D62 -> Mas 82%
C55: Valor | D55: Cantidad | E55: Valor Total | J55: Cencosud | K55: Virtual | L55: No hay comisión no hay cobros adicionales
A56: 15 | B56: Reclutamiento NSE 5 - 6 | C56: =+Entradas!I56 -> 30000 | D56: =+I6+I7 -> 34 | E56: =+C56*D56*H56 -> 0 | G56: =VLOOKUP(Entradas!$D$56,Parametros!$B$215:$C$217,2,0) -> 0 | H56: =IF(G56>0,1,0) -> 0 | K56: Fisico
A57: 17 | B57: Reclutamiento NSE 4 | C57: =+Entradas!H56 -> 25000 | D57: =+I8 -> 58 | E57: =+C57*D57*H57 -> 0 | G57: =VLOOKUP(Entradas!$D$56,Parametros!$B$215:$C$217,2,0) -> 0 | H57: =IF(G57>0,1,0) -> 0
A58: 18 | B58: Reclutamiento NSE 3 | C58: =+Entradas!G56 -> 20000 | D58: =+I9 -> 143 | E58: =+C58*D58*G58 -> 0 | G58: =VLOOKUP(Entradas!$D$56,Parametros!$B$215:$C$217,2,0) -> 0 | J58: Éxito | K58: Comisión del 3%
A59: 19 | B59: Reclutamiento NSE 1-2 | C59: =+Entradas!E56 -> 20000 | D59: =+I10+I11 -> 168 | E59: =+C59*D59*G59 -> 0 | F59: =SUM(E56:E59) -> 0 | G59: =VLOOKUP(Entradas!$D$56,Parametros!$B$215:$C$217,2,0) -> 0 | K59: Fisico | L59: 15000 | M59: Valor adicional por el envio
A60: 20 | B60: Obsequios NSE 5-6 | C60: =+Entradas!I57 -> 30000 | D60: =+I6+I7 -> 34 | E60: =+C60*D60*G60 -> 0 | F60: Sin gross ops | G60: =VLOOKUP(Entradas!$D$57,Parametros!$B$219:$C$220,2,0) -> 0
A61: 22 | B61: Obsequios NSE 4 | C61: =+Entradas!H57 -> 30000 | D61: =+I8 -> 58 | E61: =+C61*D61*G61 -> 0 | G61: =VLOOKUP(Entradas!$D$57,Parametros!$B$219:$C$220,2,0) -> 0 | N61: MSU
A62: 23 | B62: Obsequios NSE 3 | C62: =+Entradas!G57 -> 25000 | D62: =+I9 -> 143 | E62: =+C62*D62*G62 -> 0 | G62: =VLOOKUP(Entradas!$D$57,Parametros!$B$219:$C$220,2,0) -> 0 | J62: D1 | K62: Hasta ahora vamos a manejarlo | L62: Comisión del 3%
A63: 24 | B63: Obsequios NSE 2-1 | C63: =+Entradas!E57 -> 25000 | D63: =+I10+I11 -> 168 | E63: =+C63*D63*G63 -> 0 | G63: =VLOOKUP(Entradas!$D$57,Parametros!$B$219:$C$220,2,0) -> 0 | L63: Fisico aumenta 15.000
B64: Total | D64: =SUM(D60:D63) -> 403 | E64: =SUM(E60:E63) -> 0 | J64: Usearch Transferencia bancarias desde México | K64: Comisión 6% | L64: Pago inmediato
B65: Comisión de los bonos | D65: 0.1 | E65: =+E66-E64 -> 0 | J65: Angelica Maldonado | K65: Comisión 8% | L65: Pago inmediato
B66: Total con comisión | E66: =+(E64/(1-D65)) -> 0
A67: 650000 | B67: Locacion btá | C67: =+A67*5.2%+A67 -> 683800 | D67: =+$I$15 -> 14.392857 | E67: =IF(Entradas!E16=1,+C67*D67*B18,0) -> 0 | F67: con gross ops, % | G67: =IF('Costos Directos discriminados'!$D$42=1,(E67*1),0) -> 0
A68: 756000 | B68: Locacion Mdellín | C68: =+A68*5.2%+A68 -> 795312 | D68: =+$I$15 -> 14.392857 | E68: =IF(Entradas!E16=1,+C68*D68*D18,0) -> 0 | G68: =IF('Costos Directos discriminados'!$D$42=1,(E68*1),0) -> 0
A69: 860000 | B69: Locación Barranquilla | C69: =+A69*5.2%+A69 -> 904720 | D69: =+$I$15 -> 14.392857 | E69: =IF(Entradas!E16=1,(C69*D69*C18),0) -> 0 | G69: =IF('Costos Directos discriminados'!$D$42=1,(E69*1),0) -> 0
A70: 600000 | B70: Locación cali | C70: 683800 | D70: =+$I$15 -> 14.392857 | E70: =IF(Entradas!E16=1,(C70*D70*E18),0) -> 0 | G70: =IF('Costos Directos discriminados'!$D$42=1,(E70*1),0) -> 0
B71: Fotocopias | D71: =+I13 -> 7 | E71: =+C71*D71 -> 0
B72: Total | E72: =SUM(E67:E71) -> 0
A75: Costo Unitario | B75: ID | C75: ACTIVIDAD | D75: PRESUPUESTADO | E75: UNIDADES | F75: DESCRIPCION | G75: HORAS
A76: 3260 | B76: 1300 | C76: Transportes PST Encuestadores | D76: 42396 | E76: 13 | F76: Dias | G76: 0 | H76: =+D76/E76 -> 3261.2308 | I76: =+H76*(I13+I17)*I15 -> 438092
A77: 6522 | B77: 1301 | C77: Transportes PST Supervisores | D77: 19567 | E77: 3 | F77: Dias | G77: 0 | H77: =+D77/E77/I16 -> 3727.0476 | J77: Bimbo
A78: 4737.3125 | B78: 4428 | C78: Duplicar cuestionarios e instructivos | D78: 75797 | E78: 16 | F78: Paginas | G78: 0 | H78: =+D78/E78 -> 4737.3125 | J78: 50000
A79: 10465.3 | B79: 5400 | C79: Realización encuestas personal | D79: 1046530 | E79: 13 | F79: Dias | G79: 0 | H79: =+D79/100 -> 10465.3 | I79: =+H79+H76 -> 13726.531
A80: 102036.33 | B80: 5401 | C80: Supervisión de campo personal | D80: 306109 | E80: 3 | F80: Dias | G80: 0 | H80: =+D80/E80 -> 102036.33 | I80: =+(D80+C833)/3 -> 102036.33
A81: 134681 | B81: 5402 | C81: Campo Coordinación | D81: 134681 | E81: 1 | F81: Dias | G81: 0 | H81: =+D81/E81 -> 134681
A82: 28683.625 | B82: 5403 | C82: Verificacion Campo | D82: 229469 | E82: 8 | F82: Horas | G82: 0 | H82: =+D82/E82 -> 28683.625
A83: 26526.667 | B83: 5409 | C83: Entrenamiento a equipos de campo | D83: 79580 | E83: 3 | F83: Horas | G83: 0 | H83: =+D83/E83 -> 26526.667
A84: 15000 | B84: 5430 | C84: Reclutamiento campo presencial | D84: 1500000 | E84: 100 | F84: Reclutados | G84: 0 | H84: =+D84/E84 -> 15000
A85: 4476 | B85: 5431 | C85: Productos para pruebas | D85: 447600 | E85: 100 | F85: Productos | G85: 0 | H85: =+D85/E85 -> 4476 | I85: =+F52 -> 0 | J85: Bimbo | K85: =+I85/100 -> 0
A86: 81000 | B86: 5433 | C86: Apoyo logistico localizacion central | D86: 160844 | E86: 2 | F86: Dias | G86: 0 | H86: =+D86/E86 -> 80422 | J86: 81000
A87: 93.606061 | B87: 5472 | C87: Verificacion-Campo Costo telefónico | D87: 15445 | E87: 165 | F87: Minutos | G87: 0 | H87: =+D87/E87 -> 93.606061
A88: 1360.6 | B88: 5504 | C88: Crítica Encuestas | D88: 149666 | E88: 110 | F88: <-Encuestas-Horas-> | G88: 5 | H88: =+D88/E88 -> 1360.6 | J88: Bimbo
A89: 25740 | B89: 5506 | C89: Codificación | D89: 718699 | E89: 31 | F89: Horas | G89: 0 | H89: =+D89/E89 -> 23183.839 | J89: 25872
A90: 54235 | B90: 5601 | C90: Scripting | D90: 1973553 | E90: 41 | F90: Horas | G90: 0 | H90: =+D90/E90 -> 48135.439 | J90: 54000
A91: 54235 | B91: 5701 | C91: Datacleaning | D91: 693762 | E91: 18 | F91: Horas | G91: 0 | H91: =+D91/E91 -> 38542.333 | J91: 54000
A92: 54235 | B92: 5705 | C92: TopLines | D92: 693762 | E92: 18 | F92: Horas | G92: 0 | H92: =+D92/E92 -> 38542.333 | J92: 54000
A93: 54235 | B93: 5710 | C93: Procesamiento | D93: 693762 | E93: 18 | F93: Horas | G93: 0 | H93: =+D93/E93 -> 38542.333 | J93: 54000
A94: 54235 | B94: 5720 | C94: Conversión/generación archivos ASCII y otros | D94: 353259 | E94: 9 | F94: Horas | G94: 0 | H94: =+D94/E94 -> 39251 | J94: 54000
D96: =SUM(D76:D94) -> 9334481
B100: Producto | C100: =+Entradas!D13 -> Otro | D100: 3200 GR | E100: 1 Gramo a Kilos | F100: Gramos a Kilos
B101: gramos | C101: =+Entradas!D45 -> 0 | D101: 25 | E101: 0.001 | F101: 1000
B102: Muestra | C102: =C12+D12+E12+F12+G12+H12 -> 0
B103: Total | C103: =+C101*C102 -> 0 | D103: =+D101*D102 -> 0 | E103: =+C103+D103 -> 0
B104: Kilos | E104: =+E103/F101 -> 0
B105: Kilos cobrados | E105: =+ROUNDUP(E104,0) -> 0
A106: 14000 | B106: 1er Kilo | D106: =+A106*5.2%+A106 -> 14728 | E106: 1 | F106: =+D106*E106 -> 14728
A107: 3000 | B107: Kl adicional | D107: =+A107*5.2%+A107 -> 3156 | E107: =+E105-E106 -> -1 | F107: =+F106+(D107*E107) -> 11572

Sheet Parametros
B1: =B3 -> Perfil | C1: =C3 -> Mas 82% | D1: =D3 -> Coordinación, supervisión y tablets | E1: =E3 -> Total Mas 82% | F1: =F3 -> 75%-82% | G1: =G3 -> Coordinación, supervisión y tablets | H1: =H3 -> Total 75%-82% | I1: =I3 -> 67%-74% | ... AI1: =AI3 -> Total Mas 0-9%
B2: 1 | C2: 2 | D2: 3 | E2: 4 | F2: 5 | G2: 6 | H2: 7 | I2: 8 | J2: 9 | K2: 10 | L2: 11 | M2: 12 | N2: 13 | O2: 14 | P2: 15 | Q2: 16 | R2: 17 | S2: 18 | T2: 19 | U2: 20 | V2: 21 | W2: 22 | X2: 23 | Y2: 24 | Z2: 25 | AA2: 26 | AB2: 27 | AC2: 28 | AD2: 29 | AE2: 30 | AF2: 31 | AG2: 32 | AH2: 33 | AI2: 34 | AX2: Diferencia entre duraciones
B3: Perfil | C3: Mas 82% | D3: Coordinación, supervisión y tablets | E3: Total Mas 82% | F3: 75%-82% | G3: Coordinación, supervisión y tablets | H3: Total 75%-82% | I3: 67%-74% | J3: Coordinación, supervisión y tablets | K3: Total 67%-74% | L3: 55-66% | M3: Coordinación, supervisión y tablets | N3: Total Mas 55-66% | O3: 46-54% | P3: Coordinación, supervisión y tablets | Q3: Total Mas 46-54% | R3: 37-45% | S3: Coordinación, supervisión y tablets | T3: Total Mas 37-45% | U3: =+B197 -> 30-36% | V3: Coordinación, supervisión y tablets | W3: Total Mas 30-36% | X3: =+B198 -> 22-29% | Y3: Coordinación, supervisión y tablets | Z3: Total Mas 22-29% | AA3: =+B199 -> 15-21% | AB3: Coordinación, supervisión y tablets | AC3: Total Mas 15-21% | AD3: =+B200 -> 10-14% | AE3: Coordinación, supervisión y tablets | AF3: Total Mas 10-14% | AG3: =+B201 -> 0-9% | AH3: Coordinación, supervisión y tablets | AI3: Total Mas 0-9% | AL3: Diferencia entre perfiles | AM3: Mas 82% | AN3: 75%-82% | AO3: 67%-74% | AP3: 55-66% | AQ3: 46-54% | AR3: 37-45% | AS3: 30-36% | AT3: 22-29% | AU3: 15-21% | AV3: 10-14% | AW3: 0-9% | AX3: Mas 82% | AY3: 75%-82% | AZ3: 67%-74% | BA3: 55-66% | BB3: 46-54% | BC3: 37-45% | BD3: 30-36% | BE3: 22-29% | BF3: 15-21% | BG3: 10-14% | BH3: 0-9%
A4: 5 | B4: 0-5 minutos | C4: =+'Precios bases'!C4*5.2%+'Precios bases'!C4 -> 7493.396 | D4: =+'Precios bases'!D4*5.2%+'Precios bases'!D4 -> 13893.764 | E4: =+'Precios bases'!E4*5.2%+'Precios bases'!E4 -> 21387.16 | F4: =+'Precios bases'!F4*5.2%+'Precios bases'!F4 -> 8019.396 | G4: =+'Precios bases'!G4*5.2%+'Precios bases'!G4 -> 13893.764 | H4: =+'Precios bases'!H4*5.2%+'Precios bases'!H4 -> 21913.16 | I4: =+'Precios bases'!I4*5.2%+'Precios bases'!I4 -> 8545.396 | J4: =+'Precios bases'!J4*5.2%+'Precios bases'!J4 -> 13893.764 | ... AI4: =+'Precios bases'!AI4*5.2%+'Precios bases'!AI4 -> 40323.16 | AL4: 0-5 minutos | AN4: =+H4-E4 -> 526 | AO4: =+K4-H4 -> 526 | AP4: =+N4-K4 -> 526 | AQ4: =+Q4-N4 -> 1052 | AR4: =+T4-Q4 -> 1578 | AS4: =+W4-T4 -> 3682 | AT4: =+Z4-W4 -> 3156 | AU4: =+AC4-Z4 -> 2630 | AV4: =+AF4-AC4 -> 2630 | AW4: =+AI4-AF4 -> 2630
A5: 10 | B5: 6-10 minutos | C5: =+'Precios bases'!C5*5.2%+'Precios bases'!C5 -> 8545.396 | D5: =+'Precios bases'!D5*5.2%+'Precios bases'!D5 -> 13893.764 | E5: =+'Precios bases'!E5*5.2%+'Precios bases'!E5 -> 22439.16 | F5: =+'Precios bases'!F5*5.2%+'Precios bases'!F5 -> 9071.396 | G5: =+'Precios bases'!G5*5.2%+'Precios bases'!G5 -> 13893.764 | H5: =+'Precios bases'!H5*5.2%+'Precios bases'!H5 -> 22965.16 | I5: =+'Precios bases'!I5*5.2%+'Precios bases'!I5 -> 9597.396 | J5: =+'Precios bases'!J5*5.2%+'Precios bases'!J5 -> 13893.764 | ... AI5: =+'Precios bases'!AI5*5.2%+'Precios bases'!AI5 -> 42427.16 | AL5: 6-10 minutos | AN5: =+H5-E5 -> 526 | AO5: =+K5-H5 -> 526 | AP5: =+N5-K5 -> 526 | AQ5: =+Q5-N5 -> 1052 | AR5: =+T5-Q5 -> 1578 | AS5: =+W5-T5 -> 3682 | AT5: =+Z5-W5 -> 4208 | AU5: =+AC5-Z5 -> 2630 | AV5: =+AF5-AC5 -> 2630 | AW5: =+AI5-AF5 -> 2630 | AX5: =+E5-E4 -> 1052 | AY5: =+H5-H4 -> 1052 | AZ5: =+K5-K4 -> 1052 | BA5: =+N5-N4 -> 1052 | BB5: =+Q5-Q4 -> 1052 | BC5: =+T5-T4 -> 1052 | BD5: =+W5-W4 -> 1052 | BE5: =+Z5-Z4 -> 2104 | BF5: =+AC5-AC4 -> 2104 | BG5: =+AF5-AF4 -> 2104 | BH5: =+AI5-AI4 -> 2104
A6: 15 | B6: 11-15minutos | C6: =+'Precios bases'!C6*5.2%+'Precios bases'!C6 -> 10123.396 | D6: =+'Precios bases'!D6*5.2%+'Precios bases'!D6 -> 13893.764 | E6: =+'Precios bases'!E6*5.2%+'Precios bases'!E6 -> 24017.16 | F6: =+'Precios bases'!F6*5.2%+'Precios bases'!F6 -> 10649.396 | G6: =+'Precios bases'!G6*5.2%+'Precios bases'!G6 -> 13893.764 | H6: =+'Precios bases'!H6*5.2%+'Precios bases'!H6 -> 24543.16 | I6: =+'Precios bases'!I6*5.2%+'Precios bases'!I6 -> 11175.396 | J6: =+'Precios bases'!J6*5.2%+'Precios bases'!J6 -> 13893.764 | ... AI6: =+'Precios bases'!AI6*5.2%+'Precios bases'!AI6 -> 44531.16 | AL6: 11-20minutos | AN6: =+H6-E6 -> 526 | AO6: =+K6-H6 -> 526 | AP6: =+N6-K6 -> 526 | AQ6: =+Q6-N6 -> 1052 | AR6: =+T6-Q6 -> 1578 | AS6: =+W6-T6 -> 3682 | AT6: =+Z6-W6 -> 4734 | AU6: =+AC6-Z6 -> 2630 | AV6: =+AF6-AC6 -> 2630 | AW6: =+AI6-AF6 -> 2630 | AX6: =+E6-E5 -> 1578 | AY6: =+H6-H5 -> 1578 | AZ6: =+K6-K5 -> 1578 | BA6: =+N6-N5 -> 1578 | BB6: =+Q6-Q5 -> 1578 | BC6: =+T6-T5 -> 1578 | BD6: =+W6-W5 -> 1578 | BE6: =+Z6-Z5 -> 2104 | BF6: =+AC6-AC5 -> 2104 | BG6: =+AF6-AF5 -> 2104 | BH6: =+AI6-AI5 -> 2104
A7: 20 | B7: 16-20minutos | C7: =+'Precios bases'!C7*5.2%+'Precios bases'!C7 -> 12227.396 | D7: =+'Precios bases'!D7*5.2%+'Precios bases'!D7 -> 13893.764 | E7: =+'Precios bases'!E7*5.2%+'Precios bases'!E7 -> 26121.16 | F7: =+'Precios bases'!F7*5.2%+'Precios bases'!F7 -> 12753.396 | G7: =+'Precios bases'!G7*5.2%+'Precios bases'!G7 -> 13893.764 | H7: =+'Precios bases'!H7*5.2%+'Precios bases'!H7 -> 26647.16 | I7: =+'Precios bases'!I7*5.2%+'Precios bases'!I7 -> 13279.396 | J7: =+'Precios bases'!J7*5.2%+'Precios bases'!J7 -> 13893.764 | ... AI7: =+'Precios bases'!AI7*5.2%+'Precios bases'!AI7 -> 46635.16
A8: 30 | B8: 21-30 minutos | C8: =+'Precios bases'!C8*5.2%+'Precios bases'!C8 -> 14857.396 | D8: =+'Precios bases'!D8*5.2%+'Precios bases'!D8 -> 13893.764 | E8: =+'Precios bases'!E8*5.2%+'Precios bases'!E8 -> 28751.16 | F8: =+'Precios bases'!F8*5.2%+'Precios bases'!F8 -> 15383.396 | G8: =+'Precios bases'!G8*5.2%+'Precios bases'!G8 -> 13893.764 | H8: =+'Precios bases'!H8*5.2%+'Precios bases'!H8 -> 29277.16 | I8: =+'Precios bases'!I8*5.2%+'Precios bases'!I8 -> 15909.396 | J8: =+'Precios bases'!J8*5.2%+'Precios bases'!J8 -> 13893.764 | ... AI8: =+'Precios bases'!AI8*5.2%+'Precios bases'!AI8 -> 48739.16 | AL8: 21-30 minutos | AN8: =+H8-E8 -> 526 | AO8: =+K8-H8 -> 526 | AP8: =+N8-K8 -> 526 | AQ8: =+Q8-N8 -> 1052 | AR8: =+T8-Q8 -> 1578 | AS8: =+W8-T8 -> 3682 | AT8: =+Z8-W8 -> 4208 | AU8: =+AC8-Z8 -> 2630 | AV8: =+AF8-AC8 -> 2630 | AW8: =+AI8-AF8 -> 2630 | AX8: =+E8-E6 -> 4734 | AY8: =+H8-H6 -> 4734 | AZ8: =+K8-K6 -> 4734 | BA8: =+N8-N6 -> 4734 | BB8: =+Q8-Q6 -> 4734 | BC8: =+T8-T6 -> 4734 | BD8: =+W8-W6 -> 4734 | BE8: =+Z8-Z6 -> 4208 | BF8: =+AC8-AC6 -> 4208 | BG8: =+AF8-AF6 -> 4208 | BH8: =+AI8-AI6 -> 4208
A9: 40 | B9: 31-40 minutos | C9: =+'Precios bases'!C9*5.2%+'Precios bases'!C9 -> 18013.396 | D9: =+'Precios bases'!D9*5.2%+'Precios bases'!D9 -> 13893.764 | E9: =+'Precios bases'!E9*5.2%+'Precios bases'!E9 -> 31907.16 | F9: =+'Precios bases'!F9*5.2%+'Precios bases'!F9 -> 18539.396 | G9: =+'Precios bases'!G9*5.2%+'Precios bases'!G9 -> 13893.764 | H9: =+'Precios bases'!H9*5.2%+'Precios bases'!H9 -> 32433.16 | I9: =+'Precios bases'!I9*5.2%+'Precios bases'!I9 -> 19065.396 | J9: =+'Precios bases'!J9*5.2%+'Precios bases'!J9 -> 13893.764 | ... AI9: =+'Precios bases'!AI9*5.2%+'Precios bases'!AI9 -> 50843.16 | AL9: 31-40 minutos | AN9: =+H9-E9 -> 526 | AO9: =+K9-H9 -> 526 | AP9: =+N9-K9 -> 526 | AQ9: =+Q9-N9 -> 1052 | AR9: =+T9-Q9 -> 1578 | AS9: =+W9-T9 -> 3682 | AT9: =+Z9-W9 -> 3156 | AU9: =+AC9-Z9 -> 2630 | AV9: =+AF9-AC9 -> 2630 | AW9: =+AI9-AF9 -> 2630 | AX9: =+E9-E8 -> 3156 | AY9: =+H9-H8 -> 3156 | AZ9: =+K9-K8 -> 3156 | BA9: =+N9-N8 -> 3156 | BB9: =+Q9-Q8 -> 3156 | BC9: =+T9-T8 -> 3156 | BD9: =+W9-W8 -> 3156 | BE9: =+Z9-Z8 -> 2104 | BF9: =+AC9-AC8 -> 2104 | BG9: =+AF9-AF8 -> 2104 | BH9: =+AI9-AI8 -> 2104
A10: 50 | B10: 41-50 minutos | C10: =+'Precios bases'!C10*5.2%+'Precios bases'!C10 -> 21169.396 | D10: =+'Precios bases'!D10*5.2%+'Precios bases'!D10 -> 13893.764 | E10: =+'Precios bases'!E10*5.2%+'Precios bases'!E10 -> 35063.16 | F10: =+'Precios bases'!F10*5.2%+'Precios bases'!F10 -> 21695.396 | G10: =+'Precios bases'!G10*5.2%+'Precios bases'!G10 -> 13893.764 | H10: =+'Precios bases'!H10*5.2%+'Precios bases'!H10 -> 35589.16 | I10: =+'Precios bases'!I10*5.2%+'Precios bases'!I10 -> 22221.396 | J10: =+'Precios bases'!J10*5.2%+'Precios bases'!J10 -> 13893.764 | ... AI10: =+'Precios bases'!AI10*5.2%+'Precios bases'!AI10 -> 55051.16 | AL10: 41-50 minutos | AN10: =+H10-E10 -> 526 | AO10: =+K10-H10 -> 526 | AP10: =+N10-K10 -> 526 | AQ10: =+Q10-N10 -> 1052 | AR10: =+T10-Q10 -> 1578 | AS10: =+W10-T10 -> 3682 | AT10: =+Z10-W10 -> 4208 | AU10: =+AC10-Z10 -> 2630 | AV10: =+AF10-AC10 -> 2630 | AW10: =+AI10-AF10 -> 2630 | AX10: =+E10-E9 -> 3156 | AY10: =+H10-H9 -> 3156 | AZ10: =+K10-K9 -> 3156 | BA10: =+N10-N9 -> 3156 | BB10: =+Q10-Q9 -> 3156 | BC10: =+T10-T9 -> 3156 | BD10: =+W10-W9 -> 3156 | BE10: =+Z10-Z9 -> 4208 | BF10: =+AC10-AC9 -> 4208 | BG10: =+AF10-AF9 -> 4208 | BH10: =+AI10-AI9 -> 4208
A11: 60 | B11: 51 - 60 minutos | C11: =+'Precios bases'!C11*5.2%+'Precios bases'!C11 -> 26429.396 | D11: =+'Precios bases'!D11*5.2%+'Precios bases'!D11 -> 13893.764 | E11: =+'Precios bases'!E11*5.2%+'Precios bases'!E11 -> 40323.16 | F11: =+'Precios bases'!F11*5.2%+'Precios bases'!F11 -> 26955.396 | G11: =+'Precios bases'!G11*5.2%+'Precios bases'!G11 -> 13893.764 | H11: =+'Precios bases'!H11*5.2%+'Precios bases'!H11 -> 40849.16 | I11: =+'Precios bases'!I11*5.2%+'Precios bases'!I11 -> 27481.396 | J11: =+'Precios bases'!J11*5.2%+'Precios bases'!J11 -> 13893.764 | ... AI11: =+'Precios bases'!AI11*5.2%+'Precios bases'!AI11 -> 59259.16 | AL11: 51 - 60 minutos | AN11: =+H11-E11 -> 526 | AO11: =+K11-H11 -> 526 | AP11: =+N11-K11 -> 526 | AQ11: =+Q11-N11 -> 1052 | AR11: =+T11-Q11 -> 1578 | AS11: =+W11-T11 -> 3682 | AT11: =+Z11-W11 -> 3156 | AU11: =+AC11-Z11 -> 2630 | AV11: =+AF11-AC11 -> 2630 | AW11: =+AI11-AF11 -> 2630 | AX11: =+E11-E10 -> 5260 | AY11: =+H11-H10 -> 5260 | AZ11: =+K11-K10 -> 5260 | BA11: =+N11-N10 -> 5260 | BB11: =+Q11-Q10 -> 5260 | BC11: =+T11-T10 -> 5260 | BD11: =+W11-W10 -> 5260 | BE11: =+Z11-Z10 -> 4208 | BF11: =+AC11-AC10 -> 4208 | BG11: =+AF11-AF10 -> 4208 | BH11: =+AI11-AI10 -> 4208
T14: Diferencia entre perfiles | U14: Mas 75% | Z14: 51-75% | AC14: 31-50% | AD14: 16-30% | AE14: 0-15% Valor por encuesta no olvidar agregar precio de reclutamiento
B15: 0-5 minutos | C15: 5 | T15: 0-5 minutos | Z15: =+#REF!-#REF! -> #REF! | AC15: =+#REF!-#REF! -> #REF! | AD15: =+B15-#REF! -> #VALUE! | AE15: =+Q15-B15 -> #VALUE!
B16: 6-10 minutos | C16: 10 | T16: 11-15 minutos | Z16: =+#REF!-#REF! -> #REF! | AC16: =+#REF!-#REF! -> #REF! | AD16: =+B16-#REF! -> #VALUE! | AE16: =+Q16-B16 -> #VALUE!
B17: 11-15minutos | C17: 15 | T17: 16-25 minutos | Z17: =+#REF!-#REF! -> #REF! | AC17: =+#REF!-#REF! -> #REF! | AD17: =+B17-#REF! -> #VALUE! | AE17: =+Q17-B17 -> #VALUE!
B18: 16-20minutos | C18: 20 | T18: 26-35 minutos | Z18: =+#REF!-#REF! -> #REF! | AC18: =+#REF!-#REF! -> #REF! | AD18: =+B19-#REF! -> #VALUE! | AE18: =+Q18-B19 -> #VALUE!
B19: 21-30 minutos | C19: 30 | T19: 36-45 minutos | Z19: =+#REF!-#REF! -> #REF! | AC19: =+#REF!-#REF! -> #REF! | AD19: =+B20-#REF! -> #VALUE! | AE19: =+Q19-B20 -> #VALUE!
B20: 31-40 minutos | C20: 40 | T20: 46 minutos 1 hora | U20: 6 | Z20: 5 | AC20: 4 | AD20: 3 | AE20: 2
B21: 41-50 minutos | C21: 50
B22: 51 - 60 minutos | C22: 60
B24: Mas 82% | C24: 0.82
B25: 75%-82% | C25: 0.75
B26: 67%-74% | C26: 0.67
B27: 55-66% | C27: 0.55 | P27: Sin parafiscales | R27: Con parafiscales
B28: 46-54% | C28: 0.46 | O28: TARIFAS PRODUCTIVIDAD Hora | P28: EN COP | Q28: 0.16522 | R28: Valor total
B29: 37-45% | C29: 0.37 | O29: LIDER DE VERIFICACION | P29: 11436 | Q29: =+P29*$Q$28 -> 1889.4559 | R29: =+P29+Q29 -> 13325.456
B30: 30-36% | C30: 0.3 | O30: LIDER DE CRITICA | P30: 11436 | Q30: =+P30*$Q$28 -> 1889.4559 | R30: =+P30+Q30 -> 13325.456
B31: 22-29% | C31: 0.22 | O31: ASISTENTE CRITICA | P31: 9037 | Q31: =+P31*$Q$28 -> 1493.0931 | R31: =+P31+Q31 -> 10530.093
B32: 15-21% | C32: 0.15 | O32: ASISTENTE VERIFICACION | P32: 9037 | Q32: =+P32*$Q$28 -> 1493.0931 | R32: =+P32+Q32 -> 10530.093
B33: 10-14% | C33: 0.1 | O33: CODIFICACION | P33: 9859 | Q33: =+P33*$Q$28 -> 1628.904 | R33: =+P33+Q33 -> 11487.904
B34: 0-9% | C34: 0 | O34: ASISTENTE OPERACIONES (BQUILLA) | P34: 11261 | Q34: =+P34*$Q$28 -> 1860.5424 | R34: =+P34+Q34 -> 13121.542
O35: LIDER DE CALIDAD | P35: 14612 | Q35: =+P35*$Q$28 -> 2414.1946 | R35: =+P35+Q35 -> 17026.195
P36: Valor tablets al mes | Q36: Valor tablets al año | R36: # encuestas del 2023 | S36: Valor por encuestas contemplando
AA37: Por Mes | AB37: 6600000 | AC37: =+AB37*12 -> 79200000 | AD37: =34781*70% -> 24346.7 | AE37: =+AC37/AD37 -> 3253.0076
A40: Valores de reclutamiento /obsequios
C42: =+C1 -> Mas 82% | D42: =+F1 -> 75%-82% | E42: =+I1 -> 67%-74% | F42: =+L1 -> 55-66% | G42: =+O1 -> 46-54% | H42: =+R1 -> 37-45% | I42: =+U1 -> 30-36% | J42: =+X1 -> 22-29% | K42: =+AA1 -> 15-21% | L42: =+AD1 -> 10-14% | M42: =+AG1 -> 0-9%
A43: 1 | B43: 2 | C43: 3 | D43: 4 | E43: 5 | F43: 6 | G43: 7 | H43: 8 | I43: 9 | J43: 10 | K43: 11 | L43: 12 | M43: 13
B44: Parametros 3 | C44: Mas 82% | D44: 75%-82% | E44: 67%-74% | F44: 55-66% | G44: 46-54% | H44: 37-45% | I44: 30-36% | J44: 22-29% | K44: 15-21% | L44: 10-14% | M44: 0-9%
A45: 15 | B45: Reclutamiento NSE 5 y 6 | C45: 30000 | D45: =+C45+$D$53 -> 30000 | E45: =+D45+$E$53 -> 30000 | F45: =+E45+$F$53 -> 33000 | G45: =+F45+$G$53 -> 36000 | H45: =+G45+$H$53 -> 39000 | I45: =+H45+$I$53 -> 44000 | J45: =+I45+$J$53 -> 49000 | K45: =+J45+$K$53 -> 54000 | L45: =+K45+$L$53 -> 64000 | M45: =+L45+$M$53 -> 90000
A46: 16 | B46: Reclutamiento NSE 4 | C46: 25000 | D46: =+C46+$D$53 -> 25000 | E46: =+D46+$E$53 -> 25000 | F46: =+E46+$F$53 -> 28000 | G46: =+F46+$G$53 -> 31000 | H46: =+G46+$H$53 -> 34000 | I46: =+H46+$I$53 -> 39000 | J46: =+I46+$J$53 -> 44000 | K46: =+J46+$K$53 -> 49000 | L46: =+K46+$L$53 -> 59000 | M46: =+L46+$M$53 -> 85000
A47: 17 | B47: Reclutamiento NSE 3 | C47: 20000 | D47: =+C47+$D$53 -> 20000 | E47: =+D47+$E$53 -> 20000 | F47: =+E47+$F$53 -> 23000 | G47: =+F47+$G$53 -> 26000 | H47: =+G47+$H$53 -> 29000 | I47: =+H47+$I$53 -> 34000 | J47: =+I47+$J$53 -> 39000 | K47: =+J47+$K$53 -> 44000 | L47: =+K47+$L$53 -> 54000 | M47: =+L47+$M$53 -> 80000
A48: 18 | B48: Reclutamiento NSE 1 y 2 | C48: 20000 | D48: =+C48+$D$53 -> 20000 | E48: =+D48+$E$53 -> 20000 | F48: =+E48+$F$53 -> 23000 | G48: =+F48+$G$53 -> 26000 | H48: =+G48+$H$53 -> 29000 | I48: =+H48+$I$53 -> 34000 | J48: =+I48+$J$53 -> 39000 | K48: =+J48+$K$53 -> 44000 | L48: =+K48+$L$53 -> 54000 | M48: =+L48+$M$53 -> 80000
A49: 19 | B49: Obsequios NSE 5 y 6 | C49: 30000 | D49: =+C49+$D$54 -> 30000 | E49: =+D49+$E$54 -> 30000 | F49: =+E49+$F$54 -> 35000 | G49: =+F49+$G$54 -> 40000 | H49: =+G49+$H$54 -> 45000 | I49: =+H49+$I$54 -> 50000 | J49: =+I49+$J$54 -> 55000 | K49: =+J49+$K$54 -> 60000 | L49: =+K49+$L$54 -> 70000 | M49: =+L49+$M$54 -> 100000
A50: 20 | B50: Obsequios NSE 4 | C50: 30000 | D50: =+C50+$D$54 -> 30000 | E50: =+D50+$E$54 -> 30000 | F50: =+E50+$F$54 -> 35000 | G50: =+F50+$G$54 -> 40000 | H50: =+G50+$H$54 -> 45000 | I50: =+H50+$I$54 -> 50000 | J50: =+I50+$J$54 -> 55000 | K50: =+J50+$K$54 -> 60000 | L50: =+K50+$L$54 -> 70000 | M50: =+L50+$M$54 -> 100000
A51: 21 | B51: Obsequios NSE 3 | C51: 25000 | D51: =+C51+$D$54 -> 25000 | E51: =+D51+$E$54 -> 25000 | F51: =+E51+$F$54 -> 30000 | G51: =+F51+$G$54 -> 35000 | H51: =+G51+$H$54 -> 40000 | I51: =+H51+$I$54 -> 45000 | J51: =+I51+$J$54 -> 50000 | K51: =+J51+$K$54 -> 55000 | L51: =+K51+$L$54 -> 65000 | M51: =+L51+$M$54 -> 95000
A52: 22 | B52: Obsequios NSE 1 y 2 | C52: 25000 | D52: =+C52+$D$54 -> 25000 | E52: =+D52+$E$54 -> 25000 | F52: =+E52+$F$54 -> 30000 | G52: =+F52+$G$54 -> 35000 | H52: =+G52+$H$54 -> 40000 | I52: =+H52+$I$54 -> 45000 | J52: =+I52+$J$54 -> 50000 | K52: =+J52+$K$54 -> 55000 | L52: =+K52+$L$54 -> 65000 | M52: =+L52+$M$54 -> 95000
B53: Reclutamiento | F53: 3000 | G53: 3000 | H53: 3000 | I53: 5000 | J53: 5000 | K53: 5000 | L53: 10000 | M53: 26000
B54: Obsequios | F54: 5000 | G54: 5000 | H54: 5000 | I54: 5000 | J54: 5000 | K54: 5000 | L54: 10000 | M54: 30000
A56: CATI
B58: Valor encuesta incluye minuto y el valor encuestador | C58: Calidad se revisa internamente
B60: NIVEL | C60: 5 a 10 | D60: 10 A 20 | E60: 20 A 30 | F60: MAS DE 30 | G60: OBSERVACION
B61: ALTO(EMPRESARIALES, GOBIERNO,PROBABILISTICO) | C61: =+'Precios bases'!C61*5.2%+'Precios bases'!C61 -> 21040 | D61: =+'Precios bases'!D61*5.2%+'Precios bases'!D61 -> 26300 | E61: =+'Precios bases'!E61*5.2%+'Precios bases'!E61 -> 31560 | F61: =+'Precios bases'!F61*5.2%+'Precios bases'!F61 -> 38924 | G61: Depende el perfil bolsa de valores se ha pagado $120000 encuesta)
B62: MEDIANA | C62: =+'Precios bases'!C62*5.2%+'Precios bases'!C62 -> 14728 | D62: =+'Precios bases'!D62*5.2%+'Precios bases'!D62 -> 19988 | E62: =+'Precios bases'!E62*5.2%+'Precios bases'!E62 -> 26300 | F62: =+'Precios bases'!F62*5.2%+'Precios bases'!F62 -> 31560
B63: BAJO(MASIVO) | C63: =+'Precios bases'!C63*5.2%+'Precios bases'!C63 -> 10520 | D63: =+'Precios bases'!D63*5.2%+'Precios bases'!D63 -> 15780 | E63: =+'Precios bases'!E63*5.2%+'Precios bases'!E63 -> 21040 | F63: =+'Precios bases'!F63*5.2%+'Precios bases'!F63 -> 26300
B65: NIVEL | C65: 5 a 10 Min | D65: 10 A 20 min | E65: 20 A 30 min | F65: MAS DE 30 min | G65: OBSERVACION
A66: Efectividad minimo del 40% | B66: ALTO(EMPRESARIALES, GOBIERNO,PROBABILISTICO) | C66: =+'Precios bases'!C66*5.2%+'Precios bases'!C66 -> 21040 | D66: =+'Precios bases'!D66*5.2%+'Precios bases'!D66 -> 26300 | E66: =+'Precios bases'!E66*5.2%+'Precios bases'!E66 -> 31560 | F66: =+'Precios bases'!F66*5.2%+'Precios bases'!F66 -> 38924 | G66: Depende el perfil bolsa de valores se ha pagado $120000 encuesta)
A67: Efectividad minimo del 60% | B67: MEDIANA | C67: =+'Precios bases'!C67*5.2%+'Precios bases'!C67 -> 14728 | D67: =+'Precios bases'!D67*5.2%+'Precios bases'!D67 -> 19988 | E67: =+'Precios bases'!E67*5.2%+'Precios bases'!E67 -> 26300 | F67: =+'Precios bases'!F67*5.2%+'Precios bases'!F67 -> 31560
A68: incidencia 79%, Efectividad 90% | B68: BAJO(MASIVO) | C68: =+'Precios bases'!C68*5.2%+'Precios bases'!C68 -> 10520 | D68: =+'Precios bases'!D68*5.2%+'Precios bases'!D68 -> 15780 | E68: =+'Precios bases'!E68*5.2%+'Precios bases'!E68 -> 21040 | F68: =+'Precios bases'!F68*5.2%+'Precios bases'!F68 -> 26300
B70: NIVEL | C70: 5 a 10 Min | D70: 10 A 20 min | E70: 20 A 30 min | F70: MAS DE 30 min | G70: OBSERVACION | H70: Solo Colombia
A71: Efectividad minimo del 40% | B71: ALTO(EMPRESARIALES, GOBIERNO,PROBABILISTICO) | C71: =+'Precios bases'!C71*5.2%+'Precios bases'!C71 -> 26300 | D71: =+'Precios bases'!D71*5.2%+'Precios bases'!D71 -> 36820 | E71: =+'Precios bases'!E71*5.2%+'Precios bases'!E71 -> 42080 | F71: =+'Precios bases'!F71*5.2%+'Precios bases'!F71 -> 52600 | G71: Depende el perfil bolsa de valores se ha pagado $120000 encuesta)
A72: Efectividad minimo del 60% | B72: MEDIANA | C72: =+'Precios bases'!C72*5.2%+'Precios bases'!C72 -> 18785.714 | D72: =+'Precios bases'!D72*5.2%+'Precios bases'!D72 -> 24750.404 | E72: =+'Precios bases'!E72*5.2%+'Precios bases'!E72 -> 30057.143 | F72: =+'Precios bases'!F72*5.2%+'Precios bases'!F72 -> 37571.429
A73: incidencia 79%, Efectividad 90% | B73: BAJO(MASIVO) | C73: =+'Precios bases'!C73*5.2%+'Precios bases'!C73 -> 15028.571 | D73: =+'Precios bases'!D73*5.2%+'Precios bases'!D73 -> 19689.232 | E73: =+'Precios bases'!E73*5.2%+'Precios bases'!E73 -> 24045.714 | F73: =+'Precios bases'!F73*5.2%+'Precios bases'!F73 -> 30057.143
C74: =+C71/(1+40%) -> 18785.714 | D74: =+D71/(1+40%) -> 26300 | E74: =+E71/(1+40%) -> 30057.143 | F74: =+F71/(1+40%) -> 37571.429
C75: =+C72/(1+25%) -> 15028.571 | D75: =+D72/(1+25%) -> 19800.323 | E75: =+E72/(1+25%) -> 24045.714 | F75: =+F72/(1+25%) -> 30057.143
C77: Bajo | L77: Medio | R77: Alto
B78: =B80 -> Perfil | C78: =C80 -> Mas 82% | D78: =D80 -> Coordinación, supervisión y tablets | E78: =E80 -> Total Mas 82% | F78: =F80 -> 75%-82% | G78: =G80 -> Coordinación, supervisión y tablets | H78: =H80 -> Total 75%-82% | I78: =I80 -> 67%-74% | ... W78: =W80 -> Total Mas 30-36% | X78: 22-29% | Y78: =Y80 -> Coordinación, supervisión y tablets | Z78: =Z80 -> Total Mas 22-29% | AA78: 15-21% | AB78: =AB80 -> Coordinación, supervisión y tablets | AC78: =AC80 -> Total Mas 15-21% | AD78: 10-14% | AE78: =AE80 -> Coordinación, supervisión y tablets | AF78: =AF80 -> Total Mas 10-14% | AG78: 0-9% | AH78: =AH80 -> Coordinación, supervisión y tablets | AI78: =AI80 -> Total Mas 0-9%
B79: 1 | C79: 2 | D79: 3 | E79: 4 | F79: 5 | G79: 6 | H79: 7 | I79: 8 | J79: 9 | K79: 10 | L79: 11 | M79: 12 | N79: 13 | O79: 14 | P79: 15 | Q79: 16 | R79: 17 | S79: 18 | T79: 19 | U79: 20 | V79: 21 | W79: 22 | X79: 23 | Y79: 24 | Z79: 25 | AA79: 26 | AB79: 27 | AC79: 28 | AD79: 29 | AE79: 30 | AF79: 31 | AG79: 32 | AH79: 33 | AI79: 34 | AX79: Diferencia entre duraciones
B80: Perfil | C80: Mas 82% | D80: Coordinación, supervisión y tablets | E80: Total Mas 82% | F80: 75%-82% | G80: Coordinación, supervisión y tablets | H80: Total 75%-82% | I80: 67%-74% | J80: Coordinación, supervisión y tablets | K80: Total 67%-74% | L80: 55-66% | M80: Coordinación, supervisión y tablets | N80: Total Mas 55-66% | O80: 46-54% | P80: Coordinación, supervisión y tablets | Q80: Total Mas 46-54% | R80: 37-45% | S80: Coordinación, supervisión y tablets | T80: Total Mas 37-45% | U80: 30-36% | V80: Coordinación, supervisión y tablets | W80: Total Mas 30-36% | X80: 22-26% | Y80: Coordinación, supervisión y tablets | Z80: Total Mas 22-29% | AA80: 15-21% | AB80: Coordinación, supervisión y tablets | AC80: Total Mas 15-21% | AD80: 10-4% | AE80: Coordinación, supervisión y tablets | AF80: Total Mas 10-14% | AG80: =+AG78 -> 0-9% | AH80: Coordinación, supervisión y tablets | AI80: Total Mas 0-9% | AL80: Diferencia entre perfiles | AM80: Mas 82% | AN80: 75%-82% | AO80: 67%-74% | AP80: 55-66% | AQ80: 46-54% | AR80: 37-45% | AS80: 30-36% | AT80: 22-29% | AU80: 15-21% | AV80: 10-14% | AW80: 0-9% | AX80: Mas 82% | AY80: 75%-82% | AZ80: 67%-74% | BA80: 55-66% | BB80: 46-54% | BC80: 37-45% | BD80: 30-36% | BE80: 22-29% | BF80: 15-21% | BG80: 10-14% | BH80: 0-9%
A81: 5 | B81: 0-5 minutos | C81: =+'Precios bases'!C81*5.2%+'Precios bases'!C81 -> 15028.872 | D81: =+'Precios bases'!D81*5.2%+'Precios bases'!D81 -> 13893.764 | E81: =+'Precios bases'!E81*5.2%+'Precios bases'!E81 -> 21387.16 | F81: =+'Precios bases'!F81*5.2%+'Precios bases'!F81 -> 15028.872 | G81: =+'Precios bases'!G81*5.2%+'Precios bases'!G81 -> 13893.764 | H81: =+'Precios bases'!H81*5.2%+'Precios bases'!H81 -> 21913.16 | I81: =+'Precios bases'!I81*5.2%+'Precios bases'!I81 -> 15028.872 | J81: =+'Precios bases'!J81*5.2%+'Precios bases'!J81 -> 13893.764 | ... AI81: =+'Precios bases'!AI81*5.2%+'Precios bases'!AI81 -> 40323.16 | AL81: 0-5 minutos | AN81: =+H81-E81 -> 526 | AO81: =+K81-H81 -> 526 | AP81: =+N81-K81 -> 526 | AQ81: =+Q81-N81 -> 1052 | AR81: =+T81-Q81 -> 1578 | AS81: =+W81-T81 -> 3682 | AT81: =+Z81-W81 -> 3156 | AU81: =+AC81-Z81 -> 2630 | AV81: =+AF81-AC81 -> 2630 | AW81: =+AI81-AF81 -> 2630
A82: 10 | B82: 6-10 minutos | C82: =+'Precios bases'!C82*5.2%+'Precios bases'!C82 -> 15028.872 | D82: =+'Precios bases'!D82*5.2%+'Precios bases'!D82 -> 13893.764 | E82: =+'Precios bases'!E82*5.2%+'Precios bases'!E82 -> 22439.16 | F82: =+'Precios bases'!F82*5.2%+'Precios bases'!F82 -> 15028.872 | G82: =+'Precios bases'!G82*5.2%+'Precios bases'!G82 -> 13893.764 | H82: =+'Precios bases'!H82*5.2%+'Precios bases'!H82 -> 22965.16 | I82: =+'Precios bases'!I82*5.2%+'Precios bases'!I82 -> 15028.872 | J82: =+'Precios bases'!J82*5.2%+'Precios bases'!J82 -> 13893.764 | ... AI82: =+'Precios bases'!AI82*5.2%+'Precios bases'!AI82 -> 42427.16 | AL82: 6-10 minutos | AN82: =+H82-E82 -> 526 | AO82: =+K82-H82 -> 526 | AP82: =+N82-K82 -> 526 | AQ82: =+Q82-N82 -> 1052 | AR82: =+T82-Q82 -> 1578 | AS82: =+W82-T82 -> 3682 | AT82: =+Z82-W82 -> 4208 | AU82: =+AC82-Z82 -> 2630 | AV82: =+AF82-AC82 -> 2630 | AW82: =+AI82-AF82 -> 2630 | AX82: =+E82-E81 -> 1052 | AY82: =+H82-H81 -> 1052 | AZ82: =+K82-K81 -> 1052 | BA82: =+N82-N81 -> 1052 | BB82: =+Q82-Q81 -> 1052 | BC82: =+T82-T81 -> 1052 | BD82: =+W82-W81 -> 1052 | BE82: =+Z82-Z81 -> 2104 | BF82: =+AC82-AC81 -> 2104 | BG82: =+AF82-AF81 -> 2104 | BH82: =+AI82-AI81 -> 2104
A83: 15 | B83: 11-15minutos | C83: =+'Precios bases'!C83*5.2%+'Precios bases'!C83 -> 19689.232 | D83: =+'Precios bases'!D83*5.2%+'Precios bases'!D83 -> 13893.764 | E83: =+'Precios bases'!E83*5.2%+'Precios bases'!E83 -> 24017.16 | F83: =+'Precios bases'!F83*5.2%+'Precios bases'!F83 -> 19689.232 | G83: =+'Precios bases'!G83*5.2%+'Precios bases'!G83 -> 13893.764 | H83: =+'Precios bases'!H83*5.2%+'Precios bases'!H83 -> 24543.16 | I83: =+'Precios bases'!I83*5.2%+'Precios bases'!I83 -> 19689.232 | J83: =+'Precios bases'!J83*5.2%+'Precios bases'!J83 -> 13893.764 | ... AI83: =+'Precios bases'!AI83*5.2%+'Precios bases'!AI83 -> 44531.16 | AL83: 11-20minutos | AN83: =+H83-E83 -> 526 | AO83: =+K83-H83 -> 526 | AP83: =+N83-K83 -> 526 | AQ83: =+Q83-N83 -> 1052 | AR83: =+T83-Q83 -> 1578 | AS83: =+W83-T83 -> 3682 | AT83: =+Z83-W83 -> 4734 | AU83: =+AC83-Z83 -> 2630 | AV83: =+AF83-AC83 -> 2630 | AW83: =+AI83-AF83 -> 2630 | AX83: =+E83-E82 -> 1578 | AY83: =+H83-H82 -> 1578 | AZ83: =+K83-K82 -> 1578 | BA83: =+N83-N82 -> 1578 | BB83: =+Q83-Q82 -> 1578 | BC83: =+T83-T82 -> 1578 | BD83: =+W83-W82 -> 1578 | BE83: =+Z83-Z82 -> 2104 | BF83: =+AC83-AC82 -> 2104 | BG83: =+AF83-AF82 -> 2104 | BH83: =+AI83-AI82 -> 2104
A84: 20 | B84: 16-20minutos | C84: =+'Precios bases'!C84*5.2%+'Precios bases'!C84 -> 19689.232 | D84: =+'Precios bases'!D84*5.2%+'Precios bases'!D84 -> 13893.764 | E84: =+'Precios bases'!E84*5.2%+'Precios bases'!E84 -> 26121.16 | F84: =+'Precios bases'!F84*5.2%+'Precios bases'!F84 -> 19689.232 | G84: =+'Precios bases'!G84*5.2%+'Precios bases'!G84 -> 13893.764 | H84: =+'Precios bases'!H84*5.2%+'Precios bases'!H84 -> 26647.16 | I84: =+'Precios bases'!I84*5.2%+'Precios bases'!I84 -> 19689.232 | J84: =+'Precios bases'!J84*5.2%+'Precios bases'!J84 -> 13893.764 | ... AI84: =+'Precios bases'!AI84*5.2%+'Precios bases'!AI84 -> 46635.16
A85: 30 | B85: 21-30 minutos | C85: =+'Precios bases'!C85*5.2%+'Precios bases'!C85 -> 24045.564 | D85: =+'Precios bases'!D85*5.2%+'Precios bases'!D85 -> 13893.764 | E85: =+'Precios bases'!E85*5.2%+'Precios bases'!E85 -> 28751.16 | F85: =+'Precios bases'!F85*5.2%+'Precios bases'!F85 -> 24045.564 | G85: =+'Precios bases'!G85*5.2%+'Precios bases'!G85 -> 13893.764 | H85: =+'Precios bases'!H85*5.2%+'Precios bases'!H85 -> 29277.16 | I85: =+'Precios bases'!I85*5.2%+'Precios bases'!I85 -> 24045.564 | J85: =+'Precios bases'!J85*5.2%+'Precios bases'!J85 -> 13893.764 | ... AI85: =+'Precios bases'!AI85*5.2%+'Precios bases'!AI85 -> 46635.16 | AL85: 21-30 minutos | AN85: =+H85-E85 -> 526 | AO85: =+K85-H85 -> 526 | AP85: =+N85-K85 -> 526 | AQ85: =+Q85-N85 -> 1052 | AR85: =+T85-Q85 -> 1578 | AS85: =+W85-T85 -> 3682 | AT85: =+Z85-W85 -> 2104 | AU85: =+AC85-Z85 -> 2630 | AV85: =+AF85-AC85 -> 2630 | AW85: =+AI85-AF85 -> 2630 | AX85: =+E85-E83 -> 4734 | AY85: =+H85-H83 -> 4734 | AZ85: =+K85-K83 -> 4734 | BA85: =+N85-N83 -> 4734 | BB85: =+Q85-Q83 -> 4734 | BC85: =+T85-T83 -> 4734 | BD85: =+W85-W83 -> 4734 | BE85: =+Z85-Z83 -> 2104 | BF85: =+AC85-AC83 -> 2104 | BG85: =+AF85-AF83 -> 2104 | BH85: =+AI85-AI83 -> 2104
A86: 40 | B86: 31-40 minutos | C86: =+'Precios bases'!C86*5.2%+'Precios bases'!C86 -> 30056.692 | D86: =+'Precios bases'!D86*5.2%+'Precios bases'!D86 -> 13893.764 | E86: =+'Precios bases'!E86*5.2%+'Precios bases'!E86 -> 31907.16 | F86: =+'Precios bases'!F86*5.2%+'Precios bases'!F86 -> 30056.692 | G86: =+'Precios bases'!G86*5.2%+'Precios bases'!G86 -> 13893.764 | H86: =+'Precios bases'!H86*5.2%+'Precios bases'!H86 -> 32433.16 | I86: =+'Precios bases'!I86*5.2%+'Precios bases'!I86 -> 30056.692 | J86: =+'Precios bases'!J86*5.2%+'Precios bases'!J86 -> 13893.764 | ... AI86: =+'Precios bases'!AI86*5.2%+'Precios bases'!AI86 -> 48739.16 | AL86: 31-40 minutos | AN86: =+H86-E86 -> 526 | AO86: =+K86-H86 -> 526 | AP86: =+N86-K86 -> 526 | AQ86: =+Q86-N86 -> 1052 | AR86: =+T86-Q86 -> 1578 | AS86: =+W86-T86 -> 3682 | AT86: =+Z86-W86 -> 1052 | AU86: =+AC86-Z86 -> 2630 | AV86: =+AF86-AC86 -> 2630 | AW86: =+AI86-AF86 -> 2630 | AX86: =+E86-E85 -> 3156 | AY86: =+H86-H85 -> 3156 | AZ86: =+K86-K85 -> 3156 | BA86: =+N86-N85 -> 3156 | BB86: =+Q86-Q85 -> 3156 | BC86: =+T86-T85 -> 3156 | BD86: =+W86-W85 -> 3156 | BE86: =+Z86-Z85 -> 2104 | BF86: =+AC86-AC85 -> 2104 | BG86: =+AF86-AF85 -> 2104 | BH86: =+AI86-AI85 -> 2104
A87: 50 | B87: 41-50 minutos | C87: =+'Precios bases'!C87*5.2%+'Precios bases'!C87 -> 40586.16 | D87: =+'Precios bases'!D87*5.2%+'Precios bases'!D87 -> 13893.764 | E87: =+'Precios bases'!E87*5.2%+'Precios bases'!E87 -> 35063.16 | F87: =+'Precios bases'!F87*5.2%+'Precios bases'!F87 -> 40586.16 | G87: =+'Precios bases'!G87*5.2%+'Precios bases'!G87 -> 13893.764 | H87: =+'Precios bases'!H87*5.2%+'Precios bases'!H87 -> 35589.16 | I87: =+'Precios bases'!I87*5.2%+'Precios bases'!I87 -> 40586.16 | J87: =+'Precios bases'!J87*5.2%+'Precios bases'!J87 -> 13893.764 | ... AI87: =+'Precios bases'!AI87*5.2%+'Precios bases'!AI87 -> 52947.16 | AL87: 41-50 minutos | AN87: =+H87-E87 -> 526 | AO87: =+K87-H87 -> 526 | AP87: =+N87-K87 -> 526 | AQ87: =+Q87-N87 -> 1052 | AR87: =+T87-Q87 -> 1578 | AS87: =+W87-T87 -> 3682 | AT87: =+Z87-W87 -> 2104 | AU87: =+AC87-Z87 -> 2630 | AV87: =+AF87-AC87 -> 2630 | AW87: =+AI87-AF87 -> 2630 | AX87: =+E87-E86 -> 3156 | AY87: =+H87-H86 -> 3156 | AZ87: =+K87-K86 -> 3156 | BA87: =+N87-N86 -> 3156 | BB87: =+Q87-Q86 -> 3156 | BC87: =+T87-T86 -> 3156 | BD87: =+W87-W86 -> 3156 | BE87: =+Z87-Z86 -> 4208 | BF87: =+AC87-AC86 -> 4208 | BG87: =+AF87-AF86 -> 4208 | BH87: =+AI87-AI86 -> 4208
A88: 60 | B88: 51 - 60 minutos | C88: =+'Precios bases'!C88*5.2%+'Precios bases'!C88 -> 51106.16 | D88: =+'Precios bases'!D88*5.2%+'Precios bases'!D88 -> 13893.764 | E88: =+'Precios bases'!E88*5.2%+'Precios bases'!E88 -> 40323.16 | F88: =+'Precios bases'!F88*5.2%+'Precios bases'!F88 -> 51106.16 | G88: =+'Precios bases'!G88*5.2%+'Precios bases'!G88 -> 13893.764 | H88: =+'Precios bases'!H88*5.2%+'Precios bases'!H88 -> 40849.16 | I88: =+'Precios bases'!I88*5.2%+'Precios bases'!I88 -> 51106.16 | J88: =+'Precios bases'!J88*5.2%+'Precios bases'!J88 -> 13893.764 | ... AI88: =+'Precios bases'!AI88*5.2%+'Precios bases'!AI88 -> 57155.16 | AL88: 51 - 60 minutos | AN88: =+H88-E88 -> 526 | AO88: =+K88-H88 -> 526 | AP88: =+N88-K88 -> 526 | AQ88: =+Q88-N88 -> 1052 | AR88: =+T88-Q88 -> 1578 | AS88: =+W88-T88 -> 3682 | AT88: =+Z88-W88 -> 1052 | AU88: =+AC88-Z88 -> 2630 | AV88: =+AF88-AC88 -> 2630 | AW88: =+AI88-AF88 -> 2630 | AX88: =+E88-E87 -> 5260 | AY88: =+H88-H87 -> 5260 | AZ88: =+K88-K87 -> 5260 | BA88: =+N88-N87 -> 5260 | BB88: =+Q88-Q87 -> 5260 | BC88: =+T88-T87 -> 5260 | BD88: =+W88-W87 -> 5260 | BE88: =+Z88-Z87 -> 4208 | BF88: =+AC88-AC87 -> 4208 | BG88: =+AF88-AF87 -> 4208 | BH88: =+AI88-AI87 -> 4208
U89: 5000 | X89: 10000 | AA89: 10000 | AD89: 20000 | AG89: 20000
A91: Autoaplicado/Online
C93: Bajo | L93: Medio | R93: Alto
B94: =B96 -> Perfil | C94: =C96 -> Mas 82% | D94: =D96 -> Coordinación, supervisión y tablets | E94: =E96 -> Total Mas 82% | F94: =F96 -> 75%-82% | G94: =G96 -> Coordinación, supervisión y tablets | H94: =H96 -> Total 75%-82% | I94: =I96 -> 67%-74% | ... W94: =W96 -> Total Mas 30-36% | X94: 22-29% | Y94: =Y96 -> Coordinación, supervisión y tablets | Z94: =Z96 -> Total Mas 22-29% | AA94: 15-21% | AB94: =AB96 -> Coordinación, supervisión y tablets | AC94: =AC96 -> Total Mas 15-21% | AD94: 10-14% | AE94: =AE96 -> Coordinación, supervisión y tablets | AF94: =AF96 -> Total Mas 10-14% | AG94: 0-9% | AH94: =AH96 -> Coordinación, supervisión y tablets | AI94: =AI96 -> Total Mas 0-9%
B95: 1 | C95: 2 | D95: 3 | E95: 4 | F95: 5 | G95: 6 | H95: 7 | I95: 8 | J95: 9 | K95: 10 | L95: 11 | M95: 12 | N95: 13 | O95: 14 | P95: 15 | Q95: 16 | R95: 17 | S95: 18 | T95: 19 | U95: 20 | V95: 21 | W95: 22 | X95: 23 | Y95: 24 | Z95: 25 | AA95: 26 | AB95: 27 | AC95: 28 | AD95: 29 | AE95: 30 | AF95: 31 | AG95: 32 | AH95: 33 | AI95: 34 | AX95: Diferencia entre duraciones
B96: Perfil | C96: Mas 82% | D96: Coordinación, supervisión y tablets | E96: Total Mas 82% | F96: 75%-82% | G96: Coordinación, supervisión y tablets | H96: Total 75%-82% | I96: 67%-74% | J96: Coordinación, supervisión y tablets | K96: Total 67%-74% | L96: 55-66% | M96: Coordinación, supervisión y tablets | N96: Total Mas 55-66% | O96: 46-54% | P96: Coordinación, supervisión y tablets | Q96: Total Mas 46-54% | R96: 37-45% | S96: Coordinación, supervisión y tablets | T96: Total Mas 37-45% | U96: =+B290 -> 0 | V96: Coordinación, supervisión y tablets | W96: Total Mas 30-36% | X96: =+B291 -> 0 | Y96: Coordinación, supervisión y tablets | Z96: Total Mas 22-29% | AA96: =+B292 -> 0 | AB96: Coordinación, supervisión y tablets | AC96: Total Mas 15-21% | AD96: =+B293 -> 0 | AE96: Coordinación, supervisión y tablets | AF96: Total Mas 10-14% | AG96: =+B294 -> 0 | AH96: Coordinación, supervisión y tablets | AI96: Total Mas 0-9% | AL96: Diferencia entre perfiles | AM96: Mas 82% | AN96: 75%-82% | AO96: 67%-74% | AP96: 55-66% | AQ96: 46-54% | AR96: 37-45% | AS96: 30-36% | AT96: 22-29% | AU96: 15-21% | AV96: 10-14% | AW96: 0-9% | AX96: Mas 82% | AY96: 75%-82% | AZ96: 67%-74% | BA96: 55-66% | BB96: 46-54% | BC96: 37-45% | BD96: 30-36% | BE96: 22-29% | BF96: 15-21% | BG96: 10-14% | BH96: 0-9%
A97: 5 | B97: 0-5 minutos | C97: =+'Precios bases'!C97*5.2%+'Precios bases'!C97 -> 12020.152 | D97: =+'Precios bases'!D97*5.2%+'Precios bases'!D97 -> 13893.764 | E97: =+'Precios bases'!E97*5.2%+'Precios bases'!E97 -> 21387.16 | F97: =+'Precios bases'!F97*5.2%+'Precios bases'!F97 -> 12966.952 | G97: =+'Precios bases'!G97*5.2%+'Precios bases'!G97 -> 13893.764 | H97: =+'Precios bases'!H97*5.2%+'Precios bases'!H97 -> 21913.16 | I97: =+'Precios bases'!I97*5.2%+'Precios bases'!I97 -> 13913.752 | J97: =+'Precios bases'!J97*5.2%+'Precios bases'!J97 -> 13893.764 | ... AI97: =+'Precios bases'!AI97*5.2%+'Precios bases'!AI97 -> 40323.16 | AL97: 0-5 minutos | AN97: =+H97-E97 -> 526 | AO97: =+K97-H97 -> 526 | AP97: =+N97-K97 -> 526 | AQ97: =+Q97-N97 -> 1052 | AR97: =+T97-Q97 -> 1578 | AS97: =+W97-T97 -> 3682 | AT97: =+Z97-W97 -> 3156 | AU97: =+AC97-Z97 -> 2630 | AV97: =+AF97-AC97 -> 2630 | AW97: =+AI97-AF97 -> 2630
A98: 10 | B98: 6-10 minutos | C98: =+'Precios bases'!C98*5.2%+'Precios bases'!C98 -> 13913.752 | D98: =+'Precios bases'!D98*5.2%+'Precios bases'!D98 -> 13893.764 | E98: =+'Precios bases'!E98*5.2%+'Precios bases'!E98 -> 22439.16 | F98: =+'Precios bases'!F98*5.2%+'Precios bases'!F98 -> 14860.552 | G98: =+'Precios bases'!G98*5.2%+'Precios bases'!G98 -> 13893.764 | H98: =+'Precios bases'!H98*5.2%+'Precios bases'!H98 -> 22965.16 | I98: =+'Precios bases'!I98*5.2%+'Precios bases'!I98 -> 15807.352 | J98: =+'Precios bases'!J98*5.2%+'Precios bases'!J98 -> 13893.764 | ... AI98: =+'Precios bases'!AI98*5.2%+'Precios bases'!AI98 -> 42427.16 | AL98: 6-10 minutos | AN98: =+H98-E98 -> 526 | AO98: =+K98-H98 -> 526 | AP98: =+N98-K98 -> 526 | AQ98: =+Q98-N98 -> 1052 | AR98: =+T98-Q98 -> 1578 | AS98: =+W98-T98 -> 3682 | AT98: =+Z98-W98 -> 4208 | AU98: =+AC98-Z98 -> 2630 | AV98: =+AF98-AC98 -> 2630 | AW98: =+AI98-AF98 -> 2630 | AX98: =+E98-E97 -> 1052 | AY98: =+H98-H97 -> 1052 | AZ98: =+K98-K97 -> 1052 | BA98: =+N98-N97 -> 1052 | BB98: =+Q98-Q97 -> 1052 | BC98: =+T98-T97 -> 1052 | BD98: =+W98-W97 -> 1052 | BE98: =+Z98-Z97 -> 2104 | BF98: =+AC98-AC97 -> 2104 | BG98: =+AF98-AF97 -> 2104 | BH98: =+AI98-AI97 -> 2104
A99: 15 | B99: 11-15minutos | C99: =+'Precios bases'!C99*5.2%+'Precios bases'!C99 -> 15807.352 | D99: =+'Precios bases'!D99*5.2%+'Precios bases'!D99 -> 13893.764 | E99: =+'Precios bases'!E99*5.2%+'Precios bases'!E99 -> 24017.16 | F99: =+'Precios bases'!F99*5.2%+'Precios bases'!F99 -> 16754.152 | G99: =+'Precios bases'!G99*5.2%+'Precios bases'!G99 -> 13893.764 | H99: =+'Precios bases'!H99*5.2%+'Precios bases'!H99 -> 24543.16 | I99: =+'Precios bases'!I99*5.2%+'Precios bases'!I99 -> 17700.952 | J99: =+'Precios bases'!J99*5.2%+'Precios bases'!J99 -> 13893.764 | ... AI99: =+'Precios bases'!AI99*5.2%+'Precios bases'!AI99 -> 44531.16 | AL99: 11-20minutos | AN99: =+H99-E99 -> 526 | AO99: =+K99-H99 -> 526 | AP99: =+N99-K99 -> 526 | AQ99: =+Q99-N99 -> 1052 | AR99: =+T99-Q99 -> 1578 | AS99: =+W99-T99 -> 3682 | AT99: =+Z99-W99 -> 4734 | AU99: =+AC99-Z99 -> 2630 | AV99: =+AF99-AC99 -> 2630 | AW99: =+AI99-AF99 -> 2630 | AX99: =+E99-E98 -> 1578 | AY99: =+H99-H98 -> 1578 | AZ99: =+K99-K98 -> 1578 | BA99: =+N99-N98 -> 1578 | BB99: =+Q99-Q98 -> 1578 | BC99: =+T99-T98 -> 1578 | BD99: =+W99-W98 -> 1578 | BE99: =+Z99-Z98 -> 2104 | BF99: =+AC99-AC98 -> 2104 | BG99: =+AF99-AF98 -> 2104 | BH99: =+AI99-AI98 -> 2104
A100: 20 | B100: 16-20minutos | C100: =+'Precios bases'!C100*5.2%+'Precios bases'!C100 -> 17700.952 | D100: =+'Precios bases'!D100*5.2%+'Precios bases'!D100 -> 13893.764 | E100: =+'Precios bases'!E100*5.2%+'Precios bases'!E100 -> 26121.16 | F100: =+'Precios bases'!F100*5.2%+'Precios bases'!F100 -> 18647.752 | G100: =+'Precios bases'!G100*5.2%+'Precios bases'!G100 -> 13893.764 | H100: =+'Precios bases'!H100*5.2%+'Precios bases'!H100 -> 26647.16 | I100: =+'Precios bases'!I100*5.2%+'Precios bases'!I100 -> 19594.552 | J100: =+'Precios bases'!J100*5.2%+'Precios bases'!J100 -> 0 | ... AI100: =+'Precios bases'!AI100*5.2%+'Precios bases'!AI100 -> 46635.16
A101: 30 | B101: 21-30 minutos | C101: =+'Precios bases'!C101*5.2%+'Precios bases'!C101 -> 19594.552 | D101: =+'Precios bases'!D101*5.2%+'Precios bases'!D101 -> 13893.764 | E101: =+'Precios bases'!E101*5.2%+'Precios bases'!E101 -> 28751.16 | F101: =+'Precios bases'!F101*5.2%+'Precios bases'!F101 -> 20541.352 | G101: =+'Precios bases'!G101*5.2%+'Precios bases'!G101 -> 13893.764 | H101: =+'Precios bases'!H101*5.2%+'Precios bases'!H101 -> 29277.16 | I101: =+'Precios bases'!I101*5.2%+'Precios bases'!I101 -> 21488.152 | J101: =+'Precios bases'!J101*5.2%+'Precios bases'!J101 -> 2.0886583 | ... AI101: =+'Precios bases'!AI101*5.2%+'Precios bases'!AI101 -> 46635.16 | AL101: 21-30 minutos | AN101: =+H101-E101 -> 526 | AO101: =+K101-H101 -> 526 | AP101: =+N101-K101 -> 526 | AQ101: =+Q101-N101 -> 1052 | AR101: =+T101-Q101 -> 1578 | AS101: =+W101-T101 -> 3682 | AT101: =+Z101-W101 -> 2104 | AU101: =+AC101-Z101 -> 2630 | AV101: =+AF101-AC101 -> 2630 | AW101: =+AI101-AF101 -> 2630 | AX101: =+E101-E99 -> 4734 | AY101: =+H101-H99 -> 4734 | AZ101: =+K101-K99 -> 4734 | BA101: =+N101-N99 -> 4734 | BB101: =+Q101-Q99 -> 4734 | BC101: =+T101-T99 -> 4734 | BD101: =+W101-W99 -> 4734 | BE101: =+Z101-Z99 -> 2104 | BF101: =+AC101-AC99 -> 2104 | BG101: =+AF101-AF99 -> 2104 | BH101: =+AI101-AI99 -> 2104
A102: 40 | B102: 31-40 minutos | C102: =+'Precios bases'!C102*5.2%+'Precios bases'!C102 -> 21488.152 | D102: =+'Precios bases'!D102*5.2%+'Precios bases'!D102 -> 13893.764 | E102: =+'Precios bases'!E102*5.2%+'Precios bases'!E102 -> 31907.16 | F102: =+'Precios bases'!F102*5.2%+'Precios bases'!F102 -> 22434.952 | G102: =+'Precios bases'!G102*5.2%+'Precios bases'!G102 -> 13893.764 | H102: =+'Precios bases'!H102*5.2%+'Precios bases'!H102 -> 32433.16 | I102: =+'Precios bases'!I102*5.2%+'Precios bases'!I102 -> 23381.752 | J102: =+'Precios bases'!J102*5.2%+'Precios bases'!J102 -> 13893.764 | ... AI102: =+'Precios bases'!AI102*5.2%+'Precios bases'!AI102 -> 48739.16 | AL102: 31-40 minutos | AN102: =+H102-E102 -> 526 | AO102: =+K102-H102 -> 526 | AP102: =+N102-K102 -> 526 | AQ102: =+Q102-N102 -> 1052 | AR102: =+T102-Q102 -> 1578 | AS102: =+W102-T102 -> 3682 | AT102: =+Z102-W102 -> 1052 | AU102: =+AC102-Z102 -> 2630 | AV102: =+AF102-AC102 -> 2630 | AW102: =+AI102-AF102 -> 2630 | AX102: =+E102-E101 -> 3156 | AY102: =+H102-H101 -> 3156 | AZ102: =+K102-K101 -> 3156 | BA102: =+N102-N101 -> 3156 | BB102: =+Q102-Q101 -> 3156 | BC102: =+T102-T101 -> 3156 | BD102: =+W102-W101 -> 3156 | BE102: =+Z102-Z101 -> 2104 | BF102: =+AC102-AC101 -> 2104 | BG102: =+AF102-AF101 -> 2104 | BH102: =+AI102-AI101 -> 2104
A103: 50 | B103: 41-50 minutos | C103: =+'Precios bases'!C103*5.2%+'Precios bases'!C103 -> 23381.752 | D103: =+'Precios bases'!D103*5.2%+'Precios bases'!D103 -> 13893.764 | E103: =+'Precios bases'!E103*5.2%+'Precios bases'!E103 -> 35063.16 | F103: =+'Precios bases'!F103*5.2%+'Precios bases'!F103 -> 24328.552 | G103: =+'Precios bases'!G103*5.2%+'Precios bases'!G103 -> 13893.764 | H103: =+'Precios bases'!H103*5.2%+'Precios bases'!H103 -> 35589.16 | I103: =+'Precios bases'!I103*5.2%+'Precios bases'!I103 -> 25275.352 | J103: =+'Precios bases'!J103*5.2%+'Precios bases'!J103 -> 13893.764 | ... AI103: =+'Precios bases'!AI103*5.2%+'Precios bases'!AI103 -> 52947.16 | AL103: 41-50 minutos | AN103: =+H103-E103 -> 526 | AO103: =+K103-H103 -> 526 | AP103: =+N103-K103 -> 526 | AQ103: =+Q103-N103 -> 1052 | AR103: =+T103-Q103 -> 1578 | AS103: =+W103-T103 -> 3682 | AT103: =+Z103-W103 -> 2104 | AU103: =+AC103-Z103 -> 2630 | AV103: =+AF103-AC103 -> 2630 | AW103: =+AI103-AF103 -> 2630 | AX103: =+E103-E102 -> 3156 | AY103: =+H103-H102 -> 3156 | AZ103: =+K103-K102 -> 3156 | BA103: =+N103-N102 -> 3156 | BB103: =+Q103-Q102 -> 3156 | BC103: =+T103-T102 -> 3156 | BD103: =+W103-W102 -> 3156 | BE103: =+Z103-Z102 -> 4208 | BF103: =+AC103-AC102 -> 4208 | BG103: =+AF103-AF102 -> 4208 | BH103: =+AI103-AI102 -> 4208
A104: 60 | B104: 51 - 60 minutos | C104: =+'Precios bases'!C104*5.2%+'Precios bases'!C104 -> 25275.352 | D104: =+'Precios bases'!D104*5.2%+'Precios bases'!D104 -> 13893.764 | E104: =+'Precios bases'!E104*5.2%+'Precios bases'!E104 -> 40323.16 | F104: =+'Precios bases'!F104*5.2%+'Precios bases'!F104 -> 26222.152 | G104: =+'Precios bases'!G104*5.2%+'Precios bases'!G104 -> 13893.764 | H104: =+'Precios bases'!H104*5.2%+'Precios bases'!H104 -> 40849.16 | I104: =+'Precios bases'!I104*5.2%+'Precios bases'!I104 -> 27168.952 | J104: =+'Precios bases'!J104*5.2%+'Precios bases'!J104 -> 13893.764 | ... AI104: =+'Precios bases'!AI104*5.2%+'Precios bases'!AI104 -> 57155.16 | AL104: 51 - 60 minutos | AN104: =+H104-E104 -> 526 | AO104: =+K104-H104 -> 526 | AP104: =+N104-K104 -> 526 | AQ104: =+Q104-N104 -> 1052 | AR104: =+T104-Q104 -> 1578 | AS104: =+W104-T104 -> 3682 | AT104: =+Z104-W104 -> 1052 | AU104: =+AC104-Z104 -> 2630 | AV104: =+AF104-AC104 -> 2630 | AW104: =+AI104-AF104 -> 2630 | AX104: =+E104-E103 -> 5260 | AY104: =+H104-H103 -> 5260 | AZ104: =+K104-K103 -> 5260 | BA104: =+N104-N103 -> 5260 | BB104: =+Q104-Q103 -> 5260 | BC104: =+T104-T103 -> 5260 | BD104: =+W104-W103 -> 5260 | BE104: =+Z104-Z103 -> 4208 | BF104: =+AC104-AC103 -> 4208 | BG104: =+AF104-AF103 -> 4208 | BH104: =+AI104-AI103 -> 4208
F105: 5 | I105: 10 | L105: 15 | O105: 20 | R105: 30 | U105: 40 | X105: 50 | AA105: 60 | AD105: 70 | AG105: 80
A107: Mystery
B109: TIPO DE VISITA | C109: VALOR DE LA VISITA PARA PAGO A MYSTERY A LA SL DESDE | D109: VALOR DE LA VISITA PARA PAGO A MYSTERY A LA SL HASTA | E109: EJEMPLO DE ESTUDIOS | F109: Valor a Contratistas | J109: CPI SL INCLUIDO EL GM
B110: Básica - Audio /fotos | C110: =+'Precios bases'!C110*5.2%+'Precios bases'!C110 -> 23144 | D110: 40000 | E110: ROMANELLI - DROGUERIAS | F110: Aprox. $4.000 por debajo de la tarifa cobrada a la SL, el valor minimo debe ser de $18.000 para la visita más básica | J110: Desde | K110: Hasta
B111: Medía - Audio/fotos | C111: =+'Precios bases'!C111*5.2%+'Precios bases'!C111 -> 29457.052 | D111: 47000 | E111: WOM | I111: Básica | J111: 220000 | K111: 283000
B112: Alta - Audio /fotos | C112: =+'Precios bases'!C112*5.2%+'Precios bases'!C112 -> 36821.052 | D112: 53000 | E112: SOFASA - AUDITORIAS | I112: Media | J112: 283001 | K112: 355000
B113: Auditorias Basicas | D113: 100000 | I113: Alta | J113: 355001 | K113: 480000
B114: AuditoriasMedia | D114: 120000
B115: Auditoriasalta | D115: 150000
B116: Básica - Video | C116: =+'Precios bases'!C113*5.2%+'Precios bases'!C113 -> 47341.052 | D116: 55000 | E116: Tigo - Dealers
...

Sheet Precios bases
B1: =B3 -> Perfil | C1: =C3 -> Mas 82% | D1: =D3 -> Coordinación, supervisión y tablets | E1: =E3 -> Total Mas 82% | F1: =F3 -> 75%-82% | G1: =G3 -> Coordinación, supervisión y tablets | H1: =H3 -> Total 75%-82% | I1: =I3 -> 67%-74% | ... AI1: =AI3 -> Total Mas 0-9%
B2: 1 | C2: 2 | D2: 3 | E2: 4 | F2: 5 | G2: 6 | H2: 7 | I2: 8 | J2: 9 | K2: 10 | L2: 11 | M2: 12 | N2: 13 | O2: 14 | P2: 15 | Q2: 16 | R2: 17 | S2: 18 | T2: 19 | U2: 20 | V2: 21 | W2: 22 | X2: 23 | Y2: 24 | Z2: 25 | AA2: 26 | AB2: 27 | AC2: 28 | AD2: 29 | AE2: 30 | AF2: 31 | AG2: 32 | AH2: 33 | AI2: 34 | AX2: Diferencia entre duraciones
B3: Perfil | C3: Mas 82% | D3: Coordinación, supervisión y tablets | E3: Total Mas 82% | F3: 75%-82% | G3: Coordinación, supervisión y tablets | H3: Total 75%-82% | I3: 67%-74% | J3: Coordinación, supervisión y tablets | K3: Total 67%-74% | L3: 55-66% | M3: Coordinación, supervisión y tablets | N3: Total Mas 55-66% | O3: 46-54% | P3: Coordinación, supervisión y tablets | Q3: Total Mas 46-54% | R3: 37-45% | S3: Coordinación, supervisión y tablets | T3: Total Mas 37-45% | U3: =+B194 -> 30-36% | V3: Coordinación, supervisión y tablets | W3: Total Mas 30-36% | X3: =+B195 -> 22-29% | Y3: Coordinación, supervisión y tablets | Z3: Total Mas 22-29% | AA3: =+B196 -> 15-21% | AB3: Coordinación, supervisión y tablets | AC3: Total Mas 15-21% | AD3: =+B197 -> 10-14% | AE3: Coordinación, supervisión y tablets | AF3: Total Mas 10-14% | AG3: =+B198 -> 0-9% | AH3: Coordinación, supervisión y tablets | AI3: Total Mas 0-9% | AL3: Diferencia entre perfiles | AM3: Mas 82% | AN3: 75%-82% | AO3: 67%-74% | AP3: 55-66% | AQ3: 46-54% | AR3: 37-45% | AS3: 30-36% | AT3: 22-29% | AU3: 15-21% | AV3: 10-14% | AW3: 0-9% | AX3: Mas 82% | AY3: 75%-82% | AZ3: 67%-74% | BA3: 55-66% | BB3: 46-54% | BC3: 37-45% | BD3: 30-36% | BE3: 22-29% | BF3: 15-21% | BG3: 10-14% | BH3: 0-9%
A4: 5 | B4: 0-5 minutos | C4: =+E4-D4 -> 7123 | D4: 13207 | E4: 20330 | F4: =+H4-G4 -> 7623 | G4: 13207 | H4: =+E4+500 -> 20830 | I4: =+K4-J4 -> 8123 | J4: 13207 | K4: =+H4+500 -> 21330 | L4: =+N4-M4 -> 8523 | M4: 13307 | N4: =+K4+500 -> 21830 | O4: =+Q4-P4 -> 9362 | P4: 13468 | Q4: =+N4+1000 -> 22830 | R4: =+T4-S4 -> 10225 | S4: 14105 | T4: =+Q4+1500 -> 24330 | U4: =+W4-V4 -> 12630 | V4: 15200 | W4: =+T4+3500 -> 27830 | X4: =+Z4-Y4 -> 15630 | Y4: 15200 | Z4: =+W4+3000 -> 30830 | AA4: =+AC4-AB4 -> 18130 | AB4: 15200 | AC4: =+Z4+2500 -> 33330 | AD4: =+AF4-AE4 -> 20630 | AE4: 15200 | AF4: =+AC4+2500 -> 35830 | AG4: =+AI4-AH4 -> 23130 | AH4: 15200 | AI4: =+AF4+2500 -> 38330 | AL4: 0-5 minutos | AN4: =+H4-E4 -> 500 | AO4: =+K4-H4 -> 500 | AP4: =+N4-K4 -> 500 | AQ4: =+Q4-N4 -> 1000 | AR4: =+T4-Q4 -> 1500 | AS4: =+W4-T4 -> 3500 | AT4: =+Z4-W4 -> 3000 | AU4: =+AC4-Z4 -> 2500 | AV4: =+AF4-AC4 -> 2500 | AW4: =+AI4-AF4 -> 2500
A5: 10 | B5: 6-10 minutos | C5: =+E5-D5 -> 8123 | D5: 13207 | E5: =+E4+1000 -> 21330 | F5: =+H5-G5 -> 8623 | G5: 13207 | H5: =+E5+500 -> 21830 | I5: =+K5-J5 -> 9123 | J5: 13207 | K5: =+H5+500 -> 22330 | L5: =+N5-M5 -> 9523 | M5: 13307 | N5: =+K5+500 -> 22830 | O5: =+Q5-P5 -> 10362 | P5: 13468 | Q5: =+N5+1000 -> 23830 | R5: =+T5-S5 -> 11225 | S5: 14105 | T5: =+Q5+1500 -> 25330 | U5: =+W5-V5 -> 13630 | V5: 15200 | W5: =+T5+3500 -> 28830 | X5: =+Z5-Y5 -> 17630 | Y5: 15200 | Z5: =+Z4+2000 -> 32830 | AA5: =+AC5-AB5 -> 20130 | AB5: 15200 | AC5: =+AC4+2000 -> 35330 | AD5: =+AF5-AE5 -> 22630 | AE5: 15200 | AF5: =+AF4+2000 -> 37830 | AG5: =+AI5-AH5 -> 25130 | AH5: 15200 | AI5: =+AI4+2000 -> 40330 | AL5: 6-10 minutos | AN5: =+H5-E5 -> 500 | AO5: =+K5-H5 -> 500 | AP5: =+N5-K5 -> 500 | AQ5: =+Q5-N5 -> 1000 | AR5: =+T5-Q5 -> 1500 | AS5: =+W5-T5 -> 3500 | AT5: =+Z5-W5 -> 4000 | AU5: =+AC5-Z5 -> 2500 | AV5: =+AF5-AC5 -> 2500 | AW5: =+AI5-AF5 -> 2500 | AX5: =+E5-E4 -> 1000 | AY5: =+H5-H4 -> 1000 | AZ5: =+K5-K4 -> 1000 | BA5: =+N5-N4 -> 1000 | BB5: =+Q5-Q4 -> 1000 | BC5: =+T5-T4 -> 1000 | BD5: =+W5-W4 -> 1000 | BE5: =+Z5-Z4 -> 2000 | BF5: =+AC5-AC4 -> 2000 | BG5: =+AF5-AF4 -> 2000 | BH5: =+AI5-AI4 -> 2000
A6: 15 | B6: 11-15minutos | C6: =+E6-D6 -> 9623 | D6: 13207 | E6: =+E5+1500 -> 22830 | F6: =+H6-G6 -> 10123 | G6: 13207 | H6: =+E6+500 -> 23330 | I6: =+K6-J6 -> 10623 | J6: 13207 | K6: =+H6+500 -> 23830 | L6: =+N6-M6 -> 11023 | M6: 13307 | N6: =+K6+500 -> 24330 | O6: =+Q6-P6 -> 11862 | P6: 13468 | Q6: =+N6+1000 -> 25330 | R6: =+T6-S6 -> 12725 | S6: 14105 | T6: =+Q6+1500 -> 26830 | U6: =+W6-V6 -> 15130 | V6: 15200 | W6: =+T6+3500 -> 30330 | X6: =+Z6-Y6 -> 19630 | Y6: 15200 | Z6: =+Z5+2000 -> 34830 | AA6: =+AC6-AB6 -> 22130 | AB6: 15200 | AC6: =+AC5+2000 -> 37330 | AD6: =+AF6-AE6 -> 24630 | AE6: 15200 | AF6: =+AF5+2000 -> 39830 | AG6: =+AI6-AH6 -> 27130 | AH6: 15200 | AI6: =+AI5+2000 -> 42330 | AL6: 11-20minutos | AN6: =+H6-E6 -> 500 | AO6: =+K6-H6 -> 500 | AP6: =+N6-K6 -> 500 | AQ6: =+Q6-N6 -> 1000 | AR6: =+T6-Q6 -> 1500 | AS6: =+W6-T6 -> 3500 | AT6: =+Z6-W6 -> 4500 | AU6: =+AC6-Z6 -> 2500 | AV6: =+AF6-AC6 -> 2500 | AW6: =+AI6-AF6 -> 2500 | AX6: =+E6-E5 -> 1500 | AY6: =+H6-H5 -> 1500 | AZ6: =+K6-K5 -> 1500 | BA6: =+N6-N5 -> 1500 | BB6: =+Q6-Q5 -> 1500 | BC6: =+T6-T5 -> 1500 | BD6: =+W6-W5 -> 1500 | BE6: =+Z6-Z5 -> 2000 | BF6: =+AC6-AC5 -> 2000 | BG6: =+AF6-AF5 -> 2000 | BH6: =+AI6-AI5 -> 2000
A7: 20 | B7: 16-20minutos | C7: =+E7-D7 -> 11623 | D7: 13207 | E7: =+E6+2000 -> 24830 | F7: =+H7-G7 -> 12123 | G7: 13207 | H7: =+E7+500 -> 25330 | I7: =+K7-J7 -> 12623 | J7: 13207 | K7: =+H7+500 -> 25830 | L7: =+N7-M7 -> 13023 | M7: 13307 | N7: =+K7+500 -> 26330 | O7: =+Q7-P7 -> 13862 | P7: 13468 | Q7: =+N7+1000 -> 27330 | R7: =+T7-S7 -> 14725 | S7: 14105 | T7: =+Q7+1500 -> 28830 | U7: =+W7-V7 -> 17130 | V7: 15200 | W7: =+T7+3500 -> 32330 | X7: =+Z7-Y7 -> 21630 | Y7: 15200 | Z7: =+Z6+2000 -> 36830 | AA7: =+AC7-AB7 -> 24130 | AB7: 15200 | AC7: =+AC6+2000 -> 39330 | AD7: =+AF7-AE7 -> 26630 | AE7: 15200 | AF7: =+AF6+2000 -> 41830 | AG7: =+AI7-AH7 -> 29130 | AH7: 15200 | AI7: =+AI6+2000 -> 44330
A8: 30 | B8: 21-30 minutos | C8: =+E8-D8 -> 14123 | D8: 13207 | E8: =+E7+2500 -> 27330 | F8: =+H8-G8 -> 14623 | G8: 13207 | H8: =+E8+500 -> 27830 | I8: =+K8-J8 -> 15123 | J8: 13207 | K8: =+H8+500 -> 28330 | L8: =+N8-M8 -> 15523 | M8: 13307 | N8: =+K8+500 -> 28830 | O8: =+Q8-P8 -> 16362 | P8: 13468 | Q8: =+N8+1000 -> 29830 | R8: =+T8-S8 -> 17225 | S8: 14105 | T8: =+Q8+1500 -> 31330 | U8: =+W8-V8 -> 19630 | V8: 15200 | W8: =+T8+3500 -> 34830 | X8: =+Z8-Y8 -> 23630 | Y8: 15200 | Z8: =+Z7+2000 -> 38830 | AA8: =+AC8-AB8 -> 26130 | AB8: 15200 | AC8: =+AC7+2000 -> 41330 | AD8: =+AF8-AE8 -> 28630 | AE8: 15200 | AF8: =+AF7+2000 -> 43830 | AG8: =+AI8-AH8 -> 31130 | AH8: 15200 | AI8: =+AI7+2000 -> 46330 | AL8: 21-30 minutos | AN8: =+H8-E8 -> 500 | AO8: =+K8-H8 -> 500 | AP8: =+N8-K8 -> 500 | AQ8: =+Q8-N8 -> 1000 | AR8: =+T8-Q8 -> 1500 | AS8: =+W8-T8 -> 3500 | AT8: =+Z8-W8 -> 4000 | AU8: =+AC8-Z8 -> 2500 | AV8: =+AF8-AC8 -> 2500 | AW8: =+AI8-AF8 -> 2500 | AX8: =+E8-E6 -> 4500 | AY8: =+H8-H6 -> 4500 | AZ8: =+K8-K6 -> 4500 | BA8: =+N8-N6 -> 4500 | BB8: =+Q8-Q6 -> 4500 | BC8: =+T8-T6 -> 4500 | BD8: =+W8-W6 -> 4500 | BE8: =+Z8-Z6 -> 4000 | BF8: =+AC8-AC6 -> 4000 | BG8: =+AF8-AF6 -> 4000 | BH8: =+AI8-AI6 -> 4000
A9: 40 | B9: 31-40 minutos | C9: =+E9-D9 -> 17123 | D9: 13207 | E9: =+E8+3000 -> 30330 | F9: =+H9-G9 -> 17623 | G9: 13207 | H9: =+E9+500 -> 30830 | I9: =+K9-J9 -> 18123 | J9: 13207 | K9: =+H9+500 -> 31330 | L9: =+N9-M9 -> 18523 | M9: 13307 | N9: =+K9+500 -> 31830 | O9: =+Q9-P9 -> 19362 | P9: 13468 | Q9: =+N9+1000 -> 32830 | R9: =+T9-S9 -> 20225 | S9: 14105 | T9: =+Q9+1500 -> 34330 | U9: =+W9-V9 -> 22630 | V9: 15200 | W9: =+T9+3500 -> 37830 | X9: =+Z9-Y9 -> 25630 | Y9: 15200 | Z9: =+Z8+2000 -> 40830 | AA9: =+AC9-AB9 -> 28130 | AB9: 15200 | AC9: =+AC8+2000 -> 43330 | AD9: =+AF9-AE9 -> 30630 | AE9: 15200 | AF9: =+AF8+2000 -> 45830 | AG9: =+AI9-AH9 -> 33130 | AH9: 15200 | AI9: =+AI8+2000 -> 48330 | AL9: 31-40 minutos | AN9: =+H9-E9 -> 500 | AO9: =+K9-H9 -> 500 | AP9: =+N9-K9 -> 500 | AQ9: =+Q9-N9 -> 1000 | AR9: =+T9-Q9 -> 1500 | AS9: =+W9-T9 -> 3500 | AT9: =+Z9-W9 -> 3000 | AU9: =+AC9-Z9 -> 2500 | AV9: =+AF9-AC9 -> 2500 | AW9: =+AI9-AF9 -> 2500 | AX9: =+E9-E8 -> 3000 | AY9: =+H9-H8 -> 3000 | AZ9: =+K9-K8 -> 3000 | BA9: =+N9-N8 -> 3000 | BB9: =+Q9-Q8 -> 3000 | BC9: =+T9-T8 -> 3000 | BD9: =+W9-W8 -> 3000 | BE9: =+Z9-Z8 -> 2000 | BF9: =+AC9-AC8 -> 2000 | BG9: =+AF9-AF8 -> 2000 | BH9: =+AI9-AI8 -> 2000
A10: 50 | B10: 41-50 minutos | C10: =+E10-D10 -> 20123 | D10: 13207 | E10: =+E9+3000 -> 33330 | F10: =+H10-G10 -> 20623 | G10: 13207 | H10: =+E10+500 -> 33830 | I10: =+K10-J10 -> 21123 | J10: 13207 | K10: =+H10+500 -> 34330 | L10: =+N10-M10 -> 21523 | M10: 13307 | N10: =+K10+500 -> 34830 | O10: =+Q10-P10 -> 22362 | P10: 13468 | Q10: =+N10+1000 -> 35830 | R10: =+T10-S10 -> 23225 | S10: 14105 | T10: =+Q10+1500 -> 37330 | U10: =+W10-V10 -> 25630 | V10: 15200 | W10: =+T10+3500 -> 40830 | X10: =+Z10-Y10 -> 29630 | Y10: 15200 | Z10: =+Z9+4000 -> 44830 | AA10: =+AC10-AB10 -> 32130 | AB10: 15200 | AC10: =+AC9+4000 -> 47330 | AD10: =+AF10-AE10 -> 34630 | AE10: 15200 | AF10: =+AF9+4000 -> 49830 | AG10: =+AI10-AH10 -> 37130 | AH10: 15200 | AI10: =+AI9+4000 -> 52330 | AL10: 41-50 minutos | AN10: =+H10-E10 -> 500 | AO10: =+K10-H10 -> 500 | AP10: =+N10-K10 -> 500 | AQ10: =+Q10-N10 -> 1000 | AR10: =+T10-Q10 -> 1500 | AS10: =+W10-T10 -> 3500 | AT10: =+Z10-W10 -> 4000 | AU10: =+AC10-Z10 -> 2500 | AV10: =+AF10-AC10 -> 2500 | AW10: =+AI10-AF10 -> 2500 | AX10: =+E10-E9 -> 3000 | AY10: =+H10-H9 -> 3000 | AZ10: =+K10-K9 -> 3000 | BA10: =+N10-N9 -> 3000 | BB10: =+Q10-Q9 -> 3000 | BC10: =+T10-T9 -> 3000 | BD10: =+W10-W9 -> 3000 | BE10: =+Z10-Z9 -> 4000 | BF10: =+AC10-AC9 -> 4000 | BG10: =+AF10-AF9 -> 4000 | BH10: =+AI10-AI9 -> 4000
A11: 60 | B11: 51 - 60 minutos | C11: =+E11-D11 -> 25123 | D11: 13207 | E11: =+E10+5000 -> 38330 | F11: =+H11-G11 -> 25623 | G11: 13207 | H11: =+E11+500 -> 38830 | I11: =+K11-J11 -> 26123 | J11: 13207 | K11: =+H11+500 -> 39330 | L11: =+N11-M11 -> 26523 | M11: 13307 | N11: =+K11+500 -> 39830 | O11: =+Q11-P11 -> 27362 | P11: 13468 | Q11: =+N11+1000 -> 40830 | R11: =+T11-S11 -> 28225 | S11: 14105 | T11: =+Q11+1500 -> 42330 | U11: =+W11-V11 -> 30630 | V11: 15200 | W11: =+T11+3500 -> 45830 | X11: =+Z11-Y11 -> 33630 | Y11: 15200 | Z11: =+Z10+4000 -> 48830 | AA11: =+AC11-AB11 -> 36130 | AB11: 15200 | AC11: =+AC10+4000 -> 51330 | AD11: =+AF11-AE11 -> 38630 | AE11: 15200 | AF11: =+AF10+4000 -> 53830 | AG11: =+AI11-AH11 -> 41130 | AH11: 15200 | AI11: =+AI10+4000 -> 56330 | AL11: 51 - 60 minutos | AN11: =+H11-E11 -> 500 | AO11: =+K11-H11 -> 500 | AP11: =+N11-K11 -> 500 | AQ11: =+Q11-N11 -> 1000 | AR11: =+T11-Q11 -> 1500 | AS11: =+W11-T11 -> 3500 | AT11: =+Z11-W11 -> 3000 | AU11: =+AC11-Z11 -> 2500 | AV11: =+AF11-AC11 -> 2500 | AW11: =+AI11-AF11 -> 2500 | AX11: =+E11-E10 -> 5000 | AY11: =+H11-H10 -> 5000 | AZ11: =+K11-K10 -> 5000 | BA11: =+N11-N10 -> 5000 | BB11: =+Q11-Q10 -> 5000 | BC11: =+T11-T10 -> 5000 | BD11: =+W11-W10 -> 5000 | BE11: =+Z11-Z10 -> 4000 | BF11: =+AC11-AC10 -> 4000 | BG11: =+AF11-AF10 -> 4000 | BH11: =+AI11-AI10 -> 4000
T14: Diferencia entre perfiles | U14: Mas 75% | Z14: 51-75% | AC14: 31-50% | AD14: 16-30% | AE14: 0-15% Valor por encuesta no olvidar agregar precio de reclutamiento
B15: 0-5 minutos | C15: 5 | T15: 0-5 minutos | Z15: =+#REF!-#REF! -> #REF! | AC15: =+#REF!-#REF! -> #REF! | AD15: =+B15-#REF! -> #VALUE! | AE15: =+Q15-B15 -> #VALUE!
B16: 6-10 minutos | C16: 10 | T16: 11-15 minutos | Z16: =+#REF!-#REF! -> #REF! | AC16: =+#REF!-#REF! -> #REF! | AD16: =+B16-#REF! -> #VALUE! | AE16: =+Q16-B16 -> #VALUE!
B17: 11-15minutos | C17: 15 | T17: 16-25 minutos | Z17: =+#REF!-#REF! -> #REF! | AC17: =+#REF!-#REF! -> #REF! | AD17: =+B17-#REF! -> #VALUE! | AE17: =+Q17-B17 -> #VALUE!
B18: 16-20minutos | C18: 20 | T18: 26-35 minutos | Z18: =+#REF!-#REF! -> #REF! | AC18: =+#REF!-#REF! -> #REF! | AD18: =+B19-#REF! -> #VALUE! | AE18: =+Q18-B19 -> #VALUE!
B19: 21-30 minutos | C19: 30 | T19: 36-45 minutos | Z19: =+#REF!-#REF! -> #REF! | AC19: =+#REF!-#REF! -> #REF! | AD19: =+B20-#REF! -> #VALUE! | AE19: =+Q19-B20 -> #VALUE!
B20: 31-40 minutos | C20: 40 | T20: 46 minutos 1 hora | U20: 6 | Z20: 5 | AC20: 4 | AD20: 3 | AE20: 2
B21: 41-50 minutos | C21: 50
B22: 51 - 60 minutos | C22: 60
B24: Mas 82% | C24: 0.82
B25: 75%-82% | C25: 0.75
B26: 67%-74% | C26: 0.67
B27: 55-66% | C27: 0.55 | P27: Sin parafiscales | R27: Con parafiscales
B28: 46-54% | C28: 0.46 | O28: TARIFAS PRODUCTIVIDAD Hora | P28: EN COP | Q28: 0.16522 | R28: Valor total
B29: 37-45% | C29: 0.37 | O29: LIDER DE VERIFICACION | P29: 11436 | Q29: =+P29*$Q$28 -> 1889.4559 | R29: =+P29+Q29 -> 13325.456
B30: 30-36% | C30: 0.3 | O30: LIDER DE CRITICA | P30: 11436 | Q30: =+P30*$Q$28 -> 1889.4559 | R30: =+P30+Q30 -> 13325.456
B31: 22-29% | C31: 0.22 | O31: ASISTENTE CRITICA | P31: 9037 | Q31: =+P31*$Q$28 -> 1493.0931 | R31: =+P31+Q31 -> 10530.093
B32: 15-21% | C32: 0.15 | O32: ASISTENTE VERIFICACION | P32: 9037 | Q32: =+P32*$Q$28 -> 1493.0931 | R32: =+P32+Q32 -> 10530.093
B33: 10-14% | C33: 0.1 | O33: CODIFICACION | P33: 9859 | Q33: =+P33*$Q$28 -> 1628.904 | R33: =+P33+Q33 -> 11487.904
B34: 0-9% | C34: 0 | O34: ASISTENTE OPERACIONES (BQUILLA) | P34: 11261 | Q34: =+P34*$Q$28 -> 1860.5424 | R34: =+P34+Q34 -> 13121.542
O35: LIDER DE CALIDAD | P35: 14612 | Q35: =+P35*$Q$28 -> 2414.1946 | R35: =+P35+Q35 -> 17026.195
P36: Valor tablets al mes | Q36: Valor tablets al año | R36: # encuestas del 2023 | S36: Valor por encuestas contemplando
AA37: Por Mes | AB37: 6600000 | AC37: =+AB37*12 -> 79200000 | AD37: =34781*70% -> 24346.7 | AE37: =+AC37/AD37 -> 3253.0076
A40: Valores de reclutamiento /obsequios
C42: =+C1 -> Mas 82% | D42: =+F1 -> 75%-82% | E42: =+I1 -> 67%-74% | F42: =+L1 -> 55-66% | G42: =+O1 -> 46-54% | H42: =+R1 -> 37-45% | I42: =+U1 -> 30-36% | J42: =+X1 -> 22-29% | K42: =+AA1 -> 15-21% | L42: =+AD1 -> 10-14% | M42: =+AG1 -> 0-9%
A43: 1 | B43: 2 | C43: 3 | D43: 4 | E43: 5 | F43: 6 | G43: 7 | H43: 8 | I43: 9 | J43: 10 | K43: 11 | L43: 12 | M43: 13
B44: Parametros 3 | C44: Mas 82% | D44: 75%-82% | E44: 67%-74% | F44: 55-66% | G44: 46-54% | H44: 37-45% | I44: 30-36% | J44: 22-29% | K44: 15-21% | L44: 10-14% | M44: 0-9%
A45: 15 | B45: Reclutamiento NSE 5 y 6 | C45: 30000 | D45: =+C45+$D$53 -> 30000 | E45: =+D45+$E$53 -> 33000 | F45: =+E45+$F$53 -> 35000 | G45: =+F45+$G$53 -> 37000 | H45: =+G45+$H$53 -> 39500 | I45: =+H45+$I$53 -> 42000 | J45: =+I45+$J$53 -> 44500 | K45: =+J45+$K$53 -> 47000 | L45: =+K45+$L$53 -> 49500 | M45: =+L45+$M$53 -> 89500
A46: 16 | B46: Reclutamiento NSE 4 | C46: 30000 | D46: =+C46+$D$53 -> 30000 | E46: =+D46+$E$53 -> 33000 | F46: =+E46+$F$53 -> 35000 | G46: =+F46+$G$53 -> 37000 | H46: =+G46+$H$53 -> 39500 | I46: =+H46+$I$53 -> 42000 | J46: =+I46+$J$53 -> 44500 | K46: =+J46+$K$53 -> 47000 | L46: =+K46+$L$53 -> 49500 | M46: =+L46+$M$53 -> 89500
A47: 17 | B47: Reclutamiento NSE 3 | C47: 25000 | D47: =+C47+$D$53 -> 25000 | E47: =+D47+$E$53 -> 28000 | F47: =+E47+$F$53 -> 30000 | G47: =+F47+$G$53 -> 32000 | H47: =+G47+$H$53 -> 34500 | I47: =+H47+$I$53 -> 37000 | J47: =+I47+$J$53 -> 39500 | K47: =+J47+$K$53 -> 42000 | L47: =+K47+$L$53 -> 44500 | M47: =+L47+$M$53 -> 84500
A48: 18 | B48: Reclutamiento NSE 1 y 2 | C48: 20000 | D48: =+C48+$D$53 -> 20000 | E48: =+D48+$E$53 -> 23000 | F48: =+E48+$F$53 -> 25000 | G48: =+F48+$G$53 -> 27000 | H48: =+G48+$H$53 -> 29500 | I48: =+H48+$I$53 -> 32000 | J48: =+I48+$J$53 -> 34500 | K48: =+J48+$K$53 -> 37000 | L48: =+K48+$L$53 -> 39500 | M48: =+L48+$M$53 -> 79500
A49: 19 | B49: Obsequios NSE 5 y 6 | C49: 30000 | D49: =+C49+$D$54 -> 30000 | E49: =+D49+$E$54 -> 35000 | F49: =+E49+$F$54 -> 40000 | G49: =+F49+$G$54 -> 45000 | H49: =+G49+$H$54 -> 50000 | I49: =+H49+$I$54 -> 55000 | J49: =+I49+$J$54 -> 60000 | K49: =+J49+$K$54 -> 65000 | L49: =+K49+$L$54 -> 70000 | M49: =+L49+$M$54 -> 120000
A50: 20 | B50: Obsequios NSE 4 | C50: 30000 | D50: =+C50+$D$54 -> 30000 | E50: =+D50+$E$54 -> 35000 | F50: =+E50+$F$54 -> 40000 | G50: =+F50+$G$54 -> 45000 | H50: =+G50+$H$54 -> 50000 | I50: =+H50+$I$54 -> 55000 | J50: =+I50+$J$54 -> 60000 | K50: =+J50+$K$54 -> 65000 | L50: =+K50+$L$54 -> 70000 | M50: =+L50+$M$54 -> 120000
A51: 21 | B51: Obsequios NSE 3 | C51: 25000 | D51: =+C51+$D$54 -> 25000 | E51: =+D51+$E$54 -> 30000 | F51: =+E51+$F$54 -> 35000 | G51: =+F51+$G$54 -> 40000 | H51: =+G51+$H$54 -> 45000 | I51: =+H51+$I$54 -> 50000 | J51: =+I51+$J$54 -> 55000 | K51: =+J51+$K$54 -> 60000 | L51: =+K51+$L$54 -> 65000 | M51: =+L51+$M$54 -> 115000
